[[{"boundingPoly": {"vertices": [{"y": 514, "x": 67}, {"y": 514, "x": 547}, {"y": 960, "x": 547}, {"y": 960, "x": 67}]}, "description": "QUALES UTAN\nMake your money work too \u2014\nBUY\navinos\nWar CERTIFICATES\nYOUR MONEY WILL GROW AND\nSECURE YOUR COMFORT IN THE FUTURE.\nLI for 15/6\n", "locale": "en"}, {"boundingPoly": {"vertices": [{"y": 514, "x": 468}, {"y": 514, "x": 498}, {"y": 520, "x": 498}, {"y": 520, "x": 468}]}, "description": "QUALES"}, {"boundingPoly": {"vertices": [{"y": 514, "x": 508}, {"y": 514, "x": 529}, {"y": 520, "x": 529}, {"y": 520, "x": 508}]}, "description": "UTAN"}, {"boundingPoly": {"vertices": [{"y": 538, "x": 74}, {"y": 538, "x": 152}, {"y": 580, "x": 152}, {"y": 580, "x": 74}]}, "description": "Make"}, {"boundingPoly": {"vertices": [{"y": 538, "x": 169}, {"y": 538, "x": 238}, {"y": 580, "x": 238}, {"y": 580, "x": 169}]}, "description": "your"}, {"boundingPoly": {"vertices": [{"y": 538, "x": 251}, {"y": 538, "x": 352}, {"y": 580, "x": 352}, {"y": 580, "x": 251}]}, "description": "money"}, {"boundingPoly": {"vertices": [{"y": 538, "x": 364}, {"y": 538, "x": 436}, {"y": 580, "x": 436}, {"y": 580, "x": 364}]}, "description": "work"}, {"boundingPoly": {"vertices": [{"y": 538, "x": 449}, {"y": 538, "x": 498}, {"y": 580, "x": 498}, {"y": 580, "x": 449}]}, "description": "too"}, {"boundingPoly": {"vertices": [{"y": 538, "x": 514}, {"y": 538, "x": 525}, {"y": 580, "x": 525}, {"y": 580, "x": 514}]}, "description": "\u2014"}, {"boundingPoly": {"vertices": [{"y": 655, "x": 73}, {"y": 646, "x": 150}, {"y": 674, "x": 154}, {"y": 684, "x": 77}]}, "description": "BUY"}, {"boundingPoly": {"vertices": [{"y": 677, "x": 153}, {"y": 677, "x": 546}, {"y": 785, "x": 546}, {"y": 785, "x": 153}]}, "description": "avinos"}, {"boundingPoly": {"vertices": [{"y": 769, "x": 67}, {"y": 769, "x": 120}, {"y": 843, "x": 120}, {"y": 843, "x": 67}]}, "description": "War"}, {"boundingPoly": {"vertices": [{"y": 769, "x": 158}, {"y": 769, "x": 546}, {"y": 843, "x": 546}, {"y": 843, "x": 158}]}, "description": "CERTIFICATES"}, {"boundingPoly": {"vertices": [{"y": 857, "x": 76}, {"y": 858, "x": 147}, {"y": 881, "x": 147}, {"y": 880, "x": 76}]}, "description": "YOUR"}, {"boundingPoly": {"vertices": [{"y": 858, "x": 167}, {"y": 859, "x": 277}, {"y": 881, "x": 277}, {"y": 880, "x": 167}]}, "description": "MONEY"}, {"boundingPoly": {"vertices": [{"y": 859, "x": 295}, {"y": 860, "x": 361}, {"y": 882, "x": 361}, {"y": 881, "x": 295}]}, "description": "WILL"}, {"boundingPoly": {"vertices": [{"y": 859, "x": 373}, {"y": 860, "x": 455}, {"y": 883, "x": 455}, {"y": 882, "x": 373}]}, "description": "GROW"}, {"boundingPoly": {"vertices": [{"y": 861, "x": 475}, {"y": 862, "x": 535}, {"y": 884, "x": 535}, {"y": 883, "x": 475}]}, "description": "AND"}, {"boundingPoly": {"vertices": [{"y": 887, "x": 71}, {"y": 887, "x": 160}, {"y": 919, "x": 160}, {"y": 919, "x": 71}]}, "description": "SECURE"}, {"boundingPoly": {"vertices": [{"y": 887, "x": 168}, {"y": 887, "x": 226}, {"y": 919, "x": 226}, {"y": 919, "x": 168}]}, "description": "YOUR"}, {"boundingPoly": {"vertices": [{"y": 887, "x": 241}, {"y": 887, "x": 354}, {"y": 919, "x": 354}, {"y": 919, "x": 241}]}, "description": "COMFORT"}, {"boundingPoly": {"vertices": [{"y": 887, "x": 367}, {"y": 887, "x": 385}, {"y": 919, "x": 385}, {"y": 919, "x": 367}]}, "description": "IN"}, {"boundingPoly": {"vertices": [{"y": 887, "x": 402}, {"y": 887, "x": 443}, {"y": 919, "x": 443}, {"y": 919, "x": 402}]}, "description": "THE"}, {"boundingPoly": {"vertices": [{"y": 887, "x": 456}, {"y": 887, "x": 536}, {"y": 919, "x": 536}, {"y": 919, "x": 456}]}, "description": "FUTURE"}, {"boundingPoly": {"vertices": [{"y": 887, "x": 539}, {"y": 887, "x": 547}, {"y": 919, "x": 547}, {"y": 919, "x": 539}]}, "description": "."}, {"boundingPoly": {"vertices": [{"y": 931, "x": 253}, {"y": 931, "x": 280}, {"y": 960, "x": 280}, {"y": 960, "x": 253}]}, "description": "LI"}, {"boundingPoly": {"vertices": [{"y": 931, "x": 290}, {"y": 931, "x": 313}, {"y": 960, "x": 313}, {"y": 960, "x": 290}]}, "description": "for"}, {"boundingPoly": {"vertices": [{"y": 931, "x": 324}, {"y": 931, "x": 340}, {"y": 960, "x": 340}, {"y": 960, "x": 324}]}, "description": "15"}, {"boundingPoly": {"vertices": [{"y": 931, "x": 345}, {"y": 931, "x": 353}, {"y": 960, "x": 353}, {"y": 960, "x": 345}]}, "description": "/"}, {"boundingPoly": {"vertices": [{"y": 931, "x": 351}, {"y": 931, "x": 359}, {"y": 960, "x": 359}, {"y": 960, "x": 351}]}, "description": "6"}]]