[[{"boundingPoly": {"vertices": [{"y": 76, "x": 29}, {"y": 76, "x": 637}, {"y": 942, "x": 637}, {"y": 942, "x": 29}]}, "description": "ALL ABOUT W.S.S.\nTHEY ARE WAR SAVINGS STAMPS ISSUED\nBY THE UNITED STATES GOVERNMENT\nTHEY ARE OF TWO KINDS\nUnited States Thrift Stamps (25c. each).\nUnited States War Savings Stamps ($4.12 to $4.23 each, depending upon the month in which you purchase them).\nSixteen U.S. Thrift Stamps plus twelve cents in cash in January, 1918 (for each succeeding month in 1918 the price will be increased one\ncent), will purchase a War Savings Stamp, which, when affixed to a War Savings Certificate, is the guarantee of the Government\nand the People of the United States to repay on January 1, 1923, the full amount with interest at 4 per cent compounded quarterly.\nThe U.S. Thrift card is a pocket-size card given free of charge to purchasers of U.S. Thrift Stamps.\nThe War Savings Certificate is a pocket-size folder given to holders of War Savings Stamps.\nWar Savings Stamps are as safe as the United States.\nWhy Should I Buy Them? BECAUSE WE ARE AT WAR\nBECAUSE--the more we save, the more labor and material will be available for the use of the Government and for the support of our army.\nBECAUSE-we must have dollars as well as men in the fight for freedom.\nBECAUSE-they establish the soundest and simplest basis of saving, which is the key to individual success\nBECAUSE there is no safer investment in the world.\nBECAUSE-War Savings Stamps must increase each month in value.\nHow Can I Buy Them? AS POSTALE STAMPS\nAS SIMPLY AS BUYING\nPOSTAGE STAMPS\nThis is the simplest security ever offered by a great government to its people. Any man, woman, or child who can save twenty-five\ncents can obtain at any Post Office or Bank a U.S. Government Thrift Stamp and a Thrift card to which to attach it. This starts\nyou as an investor, and puts you behind the Government.\nBUY THEM NOW!!!\nWhen Shall I Buy Them? BUY THEM NOW!!!\nSehemu\nBecause the cost increases one cent cach month after the 31st of January, 1918. The sooner you buy them the less they cost.\nThe price of War Savings Stamps is 54.12 In January, 1918, and increases one cent each month until in December 1918, when the\nprice is $4.23.\nThe cost is as follows:\nJan. ... $4.12 Apr. ... $4.15 July . . . $4.18 Oct.... $4.21\nFeb. ... 4.13 May... 4:16 Aug.... 4.19 Nov. ... 4.22\nMar.... 4.14 June... 4.17 Sept.... 4.20 Dec. . . . 4.23\nNo commissions are charged to you, or paid to anyone.\nOur soldiers and sailors may give their lives: you are asked only to lend your money,\nWhere Can I Buy Them? ARUSSTCOMPAESEBANKS\nMANY OTHER AUTHORIZED SELLING AGENCIES\nAT POST OFFICES, BANKS,\n\u2022 TRUST COMPANIES, AND\nEVERY STAMP HELPS TO SAVE A LIFE\nEVERY STAMP HELPS TO END THE WAR\nWAR SAVINGS STAMPS\nISSUED BY THE\nUNITED STATES\nGOVERNMENT\nUNITED STATES TREASURY DEPARTMENT\n", "locale": "en"}, {"boundingPoly": {"vertices": [{"y": 76, "x": 72}, {"y": 76, "x": 163}, {"y": 140, "x": 163}, {"y": 140, "x": 72}]}, "description": "ALL"}, {"boundingPoly": {"vertices": [{"y": 76, "x": 206}, {"y": 76, "x": 389}, {"y": 140, "x": 389}, {"y": 140, "x": 206}]}, "description": "ABOUT"}, {"boundingPoly": {"vertices": [{"y": 76, "x": 460}, {"y": 76, "x": 478}, {"y": 140, "x": 478}, {"y": 140, "x": 460}]}, "description": "W"}, {"boundingPoly": {"vertices": [{"y": 76, "x": 492}, {"y": 76, "x": 510}, {"y": 140, "x": 510}, {"y": 140, "x": 492}]}, "description": "."}, {"boundingPoly": {"vertices": [{"y": 76, "x": 518}, {"y": 76, "x": 536}, {"y": 140, "x": 536}, {"y": 140, "x": 518}]}, "description": "S"}, {"boundingPoly": {"vertices": [{"y": 76, "x": 538}, {"y": 76, "x": 556}, {"y": 140, "x": 556}, {"y": 140, "x": 538}]}, "description": "."}, {"boundingPoly": {"vertices": [{"y": 76, "x": 557}, {"y": 76, "x": 575}, {"y": 140, "x": 575}, {"y": 140, "x": 557}]}, "description": "S"}, {"boundingPoly": {"vertices": [{"y": 76, "x": 577}, {"y": 76, "x": 595}, {"y": 140, "x": 595}, {"y": 140, "x": 577}]}, "description": "."}, {"boundingPoly": {"vertices": [{"y": 156, "x": 297}, {"y": 156, "x": 338}, {"y": 174, "x": 338}, {"y": 174, "x": 297}]}, "description": "THEY"}, {"boundingPoly": {"vertices": [{"y": 156, "x": 347}, {"y": 156, "x": 373}, {"y": 174, "x": 373}, {"y": 174, "x": 347}]}, "description": "ARE"}, {"boundingPoly": {"vertices": [{"y": 156, "x": 385}, {"y": 156, "x": 418}, {"y": 174, "x": 418}, {"y": 174, "x": 385}]}, "description": "WAR"}, {"boundingPoly": {"vertices": [{"y": 156, "x": 430}, {"y": 156, "x": 494}, {"y": 174, "x": 494}, {"y": 174, "x": 430}]}, "description": "SAVINGS"}, {"boundingPoly": {"vertices": [{"y": 156, "x": 506}, {"y": 156, "x": 565}, {"y": 174, "x": 565}, {"y": 174, "x": 506}]}, "description": "STAMPS"}, {"boundingPoly": {"vertices": [{"y": 156, "x": 575}, {"y": 156, "x": 629}, {"y": 174, "x": 629}, {"y": 174, "x": 575}]}, "description": "ISSUED"}, {"boundingPoly": {"vertices": [{"y": 174, "x": 296}, {"y": 174, "x": 315}, {"y": 192, "x": 315}, {"y": 192, "x": 296}]}, "description": "BY"}, {"boundingPoly": {"vertices": [{"y": 174, "x": 331}, {"y": 174, "x": 360}, {"y": 192, "x": 360}, {"y": 192, "x": 331}]}, "description": "THE"}, {"boundingPoly": {"vertices": [{"y": 174, "x": 374}, {"y": 174, "x": 431}, {"y": 192, "x": 431}, {"y": 192, "x": 374}]}, "description": "UNITED"}, {"boundingPoly": {"vertices": [{"y": 174, "x": 446}, {"y": 174, "x": 505}, {"y": 192, "x": 505}, {"y": 192, "x": 446}]}, "description": "STATES"}, {"boundingPoly": {"vertices": [{"y": 174, "x": 518}, {"y": 174, "x": 632}, {"y": 192, "x": 632}, {"y": 192, "x": 518}]}, "description": "GOVERNMENT"}, {"boundingPoly": {"vertices": [{"y": 199, "x": 54}, {"y": 199, "x": 77}, {"y": 211, "x": 77}, {"y": 211, "x": 54}]}, "description": "THEY"}, {"boundingPoly": {"vertices": [{"y": 199, "x": 83}, {"y": 199, "x": 101}, {"y": 211, "x": 101}, {"y": 211, "x": 83}]}, "description": "ARE"}, {"boundingPoly": {"vertices": [{"y": 199, "x": 107}, {"y": 199, "x": 118}, {"y": 211, "x": 118}, {"y": 211, "x": 107}]}, "description": "OF"}, {"boundingPoly": {"vertices": [{"y": 199, "x": 125}, {"y": 199, "x": 145}, {"y": 211, "x": 145}, {"y": 211, "x": 125}]}, "description": "TWO"}, {"boundingPoly": {"vertices": [{"y": 199, "x": 151}, {"y": 199, "x": 179}, {"y": 211, "x": 179}, {"y": 211, "x": 151}]}, "description": "KINDS"}, {"boundingPoly": {"vertices": [{"y": 212, "x": 70}, {"y": 212, "x": 96}, {"y": 225, "x": 96}, {"y": 225, "x": 70}]}, "description": "United"}, {"boundingPoly": {"vertices": [{"y": 212, "x": 101}, {"y": 212, "x": 127}, {"y": 225, "x": 127}, {"y": 225, "x": 101}]}, "description": "States"}, {"boundingPoly": {"vertices": [{"y": 212, "x": 133}, {"y": 212, "x": 155}, {"y": 225, "x": 155}, {"y": 225, "x": 133}]}, "description": "Thrift"}, {"boundingPoly": {"vertices": [{"y": 212, "x": 159}, {"y": 212, "x": 191}, {"y": 225, "x": 191}, {"y": 225, "x": 159}]}, "description": "Stamps"}, {"boundingPoly": {"vertices": [{"y": 212, "x": 194}, {"y": 212, "x": 197}, {"y": 225, "x": 197}, {"y": 225, "x": 194}]}, "description": "("}, {"boundingPoly": {"vertices": [{"y": 212, "x": 196}, {"y": 212, "x": 210}, {"y": 225, "x": 210}, {"y": 225, "x": 196}]}, "description": "25c"}, {"boundingPoly": {"vertices": [{"y": 212, "x": 209}, {"y": 212, "x": 212}, {"y": 225, "x": 212}, {"y": 225, "x": 209}]}, "description": "."}, {"boundingPoly": {"vertices": [{"y": 212, "x": 217}, {"y": 212, "x": 232}, {"y": 225, "x": 232}, {"y": 225, "x": 217}]}, "description": "each"}, {"boundingPoly": {"vertices": [{"y": 212, "x": 235}, {"y": 212, "x": 238}, {"y": 225, "x": 238}, {"y": 225, "x": 235}]}, "description": ")"}, {"boundingPoly": {"vertices": [{"y": 212, "x": 237}, {"y": 212, "x": 240}, {"y": 225, "x": 240}, {"y": 225, "x": 237}]}, "description": "."}, {"boundingPoly": {"vertices": [{"y": 225, "x": 70}, {"y": 225, "x": 96}, {"y": 235, "x": 96}, {"y": 235, "x": 70}]}, "description": "United"}, {"boundingPoly": {"vertices": [{"y": 225, "x": 100}, {"y": 225, "x": 126}, {"y": 235, "x": 126}, {"y": 235, "x": 100}]}, "description": "States"}, {"boundingPoly": {"vertices": [{"y": 225, "x": 129}, {"y": 225, "x": 148}, {"y": 235, "x": 148}, {"y": 235, "x": 129}]}, "description": "War"}, {"boundingPoly": {"vertices": [{"y": 225, "x": 152}, {"y": 225, "x": 184}, {"y": 235, "x": 184}, {"y": 235, "x": 152}]}, "description": "Savings"}, {"boundingPoly": {"vertices": [{"y": 225, "x": 191}, {"y": 225, "x": 219}, {"y": 235, "x": 219}, {"y": 235, "x": 191}]}, "description": "Stamps"}, {"boundingPoly": {"vertices": [{"y": 225, "x": 225}, {"y": 225, "x": 227}, {"y": 235, "x": 227}, {"y": 235, "x": 225}]}, "description": "("}, {"boundingPoly": {"vertices": [{"y": 225, "x": 228}, {"y": 225, "x": 230}, {"y": 235, "x": 230}, {"y": 235, "x": 228}]}, "description": "$"}, {"boundingPoly": {"vertices": [{"y": 225, "x": 233}, {"y": 225, "x": 235}, {"y": 235, "x": 235}, {"y": 235, "x": 233}]}, "description": "4"}, {"boundingPoly": {"vertices": [{"y": 225, "x": 237}, {"y": 225, "x": 239}, {"y": 235, "x": 239}, {"y": 235, "x": 237}]}, "description": "."}, {"boundingPoly": {"vertices": [{"y": 225, "x": 240}, {"y": 225, "x": 248}, {"y": 235, "x": 248}, {"y": 235, "x": 240}]}, "description": "12"}, {"boundingPoly": {"vertices": [{"y": 225, "x": 253}, {"y": 225, "x": 259}, {"y": 235, "x": 259}, {"y": 235, "x": 253}]}, "description": "to"}, {"boundingPoly": {"vertices": [{"y": 225, "x": 264}, {"y": 225, "x": 266}, {"y": 235, "x": 266}, {"y": 235, "x": 264}]}, "description": "$"}, {"boundingPoly": {"vertices": [{"y": 225, "x": 270}, {"y": 225, "x": 272}, {"y": 235, "x": 272}, {"y": 235, "x": 270}]}, "description": "4"}, {"boundingPoly": {"vertices": [{"y": 225, "x": 273}, {"y": 225, "x": 275}, {"y": 235, "x": 275}, {"y": 235, "x": 273}]}, "description": "."}, {"boundingPoly": {"vertices": [{"y": 225, "x": 277}, {"y": 225, "x": 284}, {"y": 235, "x": 284}, {"y": 235, "x": 277}]}, "description": "23"}, {"boundingPoly": {"vertices": [{"y": 225, "x": 290}, {"y": 225, "x": 305}, {"y": 235, "x": 305}, {"y": 235, "x": 290}]}, "description": "each"}, {"boundingPoly": {"vertices": [{"y": 225, "x": 308}, {"y": 225, "x": 310}, {"y": 235, "x": 310}, {"y": 235, "x": 308}]}, "description": ","}, {"boundingPoly": {"vertices": [{"y": 225, "x": 313}, {"y": 225, "x": 355}, {"y": 235, "x": 355}, {"y": 235, "x": 313}]}, "description": "depending"}, {"boundingPoly": {"vertices": [{"y": 225, "x": 359}, {"y": 225, "x": 377}, {"y": 235, "x": 377}, {"y": 235, "x": 359}]}, "description": "upon"}, {"boundingPoly": {"vertices": [{"y": 225, "x": 384}, {"y": 225, "x": 396}, {"y": 235, "x": 396}, {"y": 235, "x": 384}]}, "description": "the"}, {"boundingPoly": {"vertices": [{"y": 225, "x": 399}, {"y": 225, "x": 425}, {"y": 235, "x": 425}, {"y": 235, "x": 399}]}, "description": "month"}, {"boundingPoly": {"vertices": [{"y": 225, "x": 431}, {"y": 225, "x": 437}, {"y": 235, "x": 437}, {"y": 235, "x": 431}]}, "description": "in"}, {"boundingPoly": {"vertices": [{"y": 225, "x": 442}, {"y": 225, "x": 465}, {"y": 235, "x": 465}, {"y": 235, "x": 442}]}, "description": "which"}, {"boundingPoly": {"vertices": [{"y": 225, "x": 472}, {"y": 225, "x": 484}, {"y": 235, "x": 484}, {"y": 235, "x": 472}]}, "description": "you"}, {"boundingPoly": {"vertices": [{"y": 225, "x": 491}, {"y": 225, "x": 527}, {"y": 235, "x": 527}, {"y": 235, "x": 491}]}, "description": "purchase"}, {"boundingPoly": {"vertices": [{"y": 225, "x": 531}, {"y": 225, "x": 547}, {"y": 235, "x": 547}, {"y": 235, "x": 531}]}, "description": "them"}, {"boundingPoly": {"vertices": [{"y": 225, "x": 553}, {"y": 225, "x": 555}, {"y": 235, "x": 555}, {"y": 235, "x": 553}]}, "description": ")"}, {"boundingPoly": {"vertices": [{"y": 225, "x": 556}, {"y": 225, "x": 558}, {"y": 235, "x": 558}, {"y": 235, "x": 556}]}, "description": "."}, {"boundingPoly": {"vertices": [{"y": 235, "x": 52}, {"y": 235, "x": 80}, {"y": 247, "x": 80}, {"y": 247, "x": 52}]}, "description": "Sixteen"}, {"boundingPoly": {"vertices": [{"y": 235, "x": 87}, {"y": 235, "x": 89}, {"y": 247, "x": 89}, {"y": 247, "x": 87}]}, "description": "U"}, {"boundingPoly": {"vertices": [{"y": 235, "x": 92}, {"y": 235, "x": 94}, {"y": 247, "x": 94}, {"y": 247, "x": 92}]}, "description": "."}, {"boundingPoly": {"vertices": [{"y": 235, "x": 97}, {"y": 235, "x": 99}, {"y": 247, "x": 99}, {"y": 247, "x": 97}]}, "description": "S"}, {"boundingPoly": {"vertices": [{"y": 235, "x": 103}, {"y": 235, "x": 105}, {"y": 247, "x": 105}, {"y": 247, "x": 103}]}, "description": "."}, {"boundingPoly": {"vertices": [{"y": 235, "x": 109}, {"y": 235, "x": 132}, {"y": 247, "x": 132}, {"y": 247, "x": 109}]}, "description": "Thrift"}, {"boundingPoly": {"vertices": [{"y": 235, "x": 135}, {"y": 235, "x": 166}, {"y": 247, "x": 166}, {"y": 247, "x": 135}]}, "description": "Stamps"}, {"boundingPoly": {"vertices": [{"y": 235, "x": 171}, {"y": 235, "x": 187}, {"y": 247, "x": 187}, {"y": 247, "x": 171}]}, "description": "plus"}, {"boundingPoly": {"vertices": [{"y": 235, "x": 192}, {"y": 235, "x": 218}, {"y": 247, "x": 218}, {"y": 247, "x": 192}]}, "description": "twelve"}, {"boundingPoly": {"vertices": [{"y": 235, "x": 222}, {"y": 235, "x": 243}, {"y": 247, "x": 243}, {"y": 247, "x": 222}]}, "description": "cents"}, {"boundingPoly": {"vertices": [{"y": 235, "x": 247}, {"y": 235, "x": 251}, {"y": 247, "x": 251}, {"y": 247, "x": 247}]}, "description": "in"}, {"boundingPoly": {"vertices": [{"y": 235, "x": 259}, {"y": 235, "x": 274}, {"y": 247, "x": 274}, {"y": 247, "x": 259}]}, "description": "cash"}, {"boundingPoly": {"vertices": [{"y": 235, "x": 279}, {"y": 235, "x": 286}, {"y": 247, "x": 286}, {"y": 247, "x": 279}]}, "description": "in"}, {"boundingPoly": {"vertices": [{"y": 235, "x": 292}, {"y": 235, "x": 323}, {"y": 247, "x": 323}, {"y": 247, "x": 292}]}, "description": "January"}, {"boundingPoly": {"vertices": [{"y": 235, "x": 326}, {"y": 235, "x": 328}, {"y": 247, "x": 328}, {"y": 247, "x": 326}]}, "description": ","}, {"boundingPoly": {"vertices": [{"y": 235, "x": 333}, {"y": 235, "x": 348}, {"y": 247, "x": 348}, {"y": 247, "x": 333}]}, "description": "1918"}, {"boundingPoly": {"vertices": [{"y": 235, "x": 352}, {"y": 235, "x": 354}, {"y": 247, "x": 354}, {"y": 247, "x": 352}]}, "description": "("}, {"boundingPoly": {"vertices": [{"y": 235, "x": 356}, {"y": 235, "x": 366}, {"y": 247, "x": 366}, {"y": 247, "x": 356}]}, "description": "for"}, {"boundingPoly": {"vertices": [{"y": 235, "x": 370}, {"y": 235, "x": 386}, {"y": 247, "x": 386}, {"y": 247, "x": 370}]}, "description": "each"}, {"boundingPoly": {"vertices": [{"y": 235, "x": 392}, {"y": 235, "x": 436}, {"y": 247, "x": 436}, {"y": 247, "x": 392}]}, "description": "succeeding"}, {"boundingPoly": {"vertices": [{"y": 235, "x": 439}, {"y": 235, "x": 465}, {"y": 247, "x": 465}, {"y": 247, "x": 439}]}, "description": "month"}, {"boundingPoly": {"vertices": [{"y": 235, "x": 472}, {"y": 235, "x": 476}, {"y": 247, "x": 476}, {"y": 247, "x": 472}]}, "description": "in"}, {"boundingPoly": {"vertices": [{"y": 235, "x": 482}, {"y": 235, "x": 500}, {"y": 247, "x": 500}, {"y": 247, "x": 482}]}, "description": "1918"}, {"boundingPoly": {"vertices": [{"y": 235, "x": 506}, {"y": 235, "x": 517}, {"y": 247, "x": 517}, {"y": 247, "x": 506}]}, "description": "the"}, {"boundingPoly": {"vertices": [{"y": 235, "x": 522}, {"y": 235, "x": 540}, {"y": 247, "x": 540}, {"y": 247, "x": 522}]}, "description": "price"}, {"boundingPoly": {"vertices": [{"y": 235, "x": 543}, {"y": 235, "x": 560}, {"y": 247, "x": 560}, {"y": 247, "x": 543}]}, "description": "will"}, {"boundingPoly": {"vertices": [{"y": 235, "x": 563}, {"y": 235, "x": 572}, {"y": 247, "x": 572}, {"y": 247, "x": 563}]}, "description": "be"}, {"boundingPoly": {"vertices": [{"y": 235, "x": 575}, {"y": 235, "x": 613}, {"y": 247, "x": 613}, {"y": 247, "x": 575}]}, "description": "increased"}, {"boundingPoly": {"vertices": [{"y": 235, "x": 616}, {"y": 235, "x": 630}, {"y": 247, "x": 630}, {"y": 247, "x": 616}]}, "description": "one"}, {"boundingPoly": {"vertices": [{"y": 247, "x": 70}, {"y": 247, "x": 86}, {"y": 259, "x": 86}, {"y": 259, "x": 70}]}, "description": "cent"}, {"boundingPoly": {"vertices": [{"y": 247, "x": 87}, {"y": 247, "x": 89}, {"y": 259, "x": 89}, {"y": 259, "x": 87}]}, "description": ")"}, {"boundingPoly": {"vertices": [{"y": 247, "x": 91}, {"y": 247, "x": 93}, {"y": 259, "x": 93}, {"y": 259, "x": 91}]}, "description": ","}, {"boundingPoly": {"vertices": [{"y": 247, "x": 94}, {"y": 247, "x": 112}, {"y": 259, "x": 112}, {"y": 259, "x": 94}]}, "description": "will"}, {"boundingPoly": {"vertices": [{"y": 247, "x": 115}, {"y": 247, "x": 151}, {"y": 259, "x": 151}, {"y": 259, "x": 115}]}, "description": "purchase"}, {"boundingPoly": {"vertices": [{"y": 247, "x": 157}, {"y": 247, "x": 159}, {"y": 259, "x": 159}, {"y": 259, "x": 157}]}, "description": "a"}, {"boundingPoly": {"vertices": [{"y": 247, "x": 164}, {"y": 247, "x": 181}, {"y": 259, "x": 181}, {"y": 259, "x": 164}]}, "description": "War"}, {"boundingPoly": {"vertices": [{"y": 247, "x": 186}, {"y": 247, "x": 219}, {"y": 259, "x": 219}, {"y": 259, "x": 186}]}, "description": "Savings"}, {"boundingPoly": {"vertices": [{"y": 247, "x": 223}, {"y": 247, "x": 251}, {"y": 259, "x": 251}, {"y": 259, "x": 223}]}, "description": "Stamp"}, {"boundingPoly": {"vertices": [{"y": 247, "x": 250}, {"y": 247, "x": 252}, {"y": 259, "x": 252}, {"y": 259, "x": 250}]}, "description": ","}, {"boundingPoly": {"vertices": [{"y": 247, "x": 255}, {"y": 247, "x": 279}, {"y": 259, "x": 279}, {"y": 259, "x": 255}]}, "description": "which"}, {"boundingPoly": {"vertices": [{"y": 247, "x": 282}, {"y": 247, "x": 284}, {"y": 259, "x": 284}, {"y": 259, "x": 282}]}, "description": ","}, {"boundingPoly": {"vertices": [{"y": 247, "x": 286}, {"y": 247, "x": 307}, {"y": 259, "x": 307}, {"y": 259, "x": 286}]}, "description": "when"}, {"boundingPoly": {"vertices": [{"y": 247, "x": 312}, {"y": 247, "x": 339}, {"y": 259, "x": 339}, {"y": 259, "x": 312}]}, "description": "affixed"}, {"boundingPoly": {"vertices": [{"y": 247, "x": 345}, {"y": 247, "x": 349}, {"y": 259, "x": 349}, {"y": 259, "x": 345}]}, "description": "to"}, {"boundingPoly": {"vertices": [{"y": 247, "x": 356}, {"y": 247, "x": 358}, {"y": 259, "x": 358}, {"y": 259, "x": 356}]}, "description": "a"}, {"boundingPoly": {"vertices": [{"y": 247, "x": 363}, {"y": 247, "x": 381}, {"y": 259, "x": 381}, {"y": 259, "x": 363}]}, "description": "War"}, {"boundingPoly": {"vertices": [{"y": 247, "x": 386}, {"y": 247, "x": 418}, {"y": 259, "x": 418}, {"y": 259, "x": 386}]}, "description": "Savings"}, {"boundingPoly": {"vertices": [{"y": 247, "x": 422}, {"y": 247, "x": 465}, {"y": 259, "x": 465}, {"y": 259, "x": 422}]}, "description": "Certificate"}, {"boundingPoly": {"vertices": [{"y": 247, "x": 466}, {"y": 247, "x": 468}, {"y": 259, "x": 468}, {"y": 259, "x": 466}]}, "description": ","}, {"boundingPoly": {"vertices": [{"y": 247, "x": 473}, {"y": 247, "x": 477}, {"y": 259, "x": 477}, {"y": 259, "x": 473}]}, "description": "is"}, {"boundingPoly": {"vertices": [{"y": 247, "x": 483}, {"y": 247, "x": 497}, {"y": 259, "x": 497}, {"y": 259, "x": 483}]}, "description": "the"}, {"boundingPoly": {"vertices": [{"y": 247, "x": 500}, {"y": 247, "x": 543}, {"y": 259, "x": 543}, {"y": 259, "x": 500}]}, "description": "guarantee"}, {"boundingPoly": {"vertices": [{"y": 247, "x": 549}, {"y": 247, "x": 556}, {"y": 259, "x": 556}, {"y": 259, "x": 549}]}, "description": "of"}, {"boundingPoly": {"vertices": [{"y": 247, "x": 561}, {"y": 247, "x": 573}, {"y": 259, "x": 573}, {"y": 259, "x": 561}]}, "description": "the"}, {"boundingPoly": {"vertices": [{"y": 247, "x": 578}, {"y": 247, "x": 632}, {"y": 259, "x": 632}, {"y": 259, "x": 578}]}, "description": "Government"}, {"boundingPoly": {"vertices": [{"y": 259, "x": 69}, {"y": 259, "x": 84}, {"y": 271, "x": 84}, {"y": 271, "x": 69}]}, "description": "and"}, {"boundingPoly": {"vertices": [{"y": 259, "x": 89}, {"y": 259, "x": 100}, {"y": 271, "x": 100}, {"y": 271, "x": 89}]}, "description": "the"}, {"boundingPoly": {"vertices": [{"y": 259, "x": 105}, {"y": 259, "x": 132}, {"y": 271, "x": 132}, {"y": 271, "x": 105}]}, "description": "People"}, {"boundingPoly": {"vertices": [{"y": 259, "x": 135}, {"y": 259, "x": 143}, {"y": 271, "x": 143}, {"y": 271, "x": 135}]}, "description": "of"}, {"boundingPoly": {"vertices": [{"y": 259, "x": 148}, {"y": 259, "x": 159}, {"y": 271, "x": 159}, {"y": 271, "x": 148}]}, "description": "the"}, {"boundingPoly": {"vertices": [{"y": 259, "x": 163}, {"y": 259, "x": 190}, {"y": 271, "x": 190}, {"y": 271, "x": 163}]}, "description": "United"}, {"boundingPoly": {"vertices": [{"y": 259, "x": 195}, {"y": 259, "x": 220}, {"y": 271, "x": 220}, {"y": 271, "x": 195}]}, "description": "States"}, {"boundingPoly": {"vertices": [{"y": 259, "x": 224}, {"y": 259, "x": 230}, {"y": 271, "x": 230}, {"y": 271, "x": 224}]}, "description": "to"}, {"boundingPoly": {"vertices": [{"y": 259, "x": 236}, {"y": 259, "x": 256}, {"y": 271, "x": 256}, {"y": 271, "x": 236}]}, "description": "repay"}, {"boundingPoly": {"vertices": [{"y": 259, "x": 262}, {"y": 259, "x": 268}, {"y": 271, "x": 268}, {"y": 271, "x": 262}]}, "description": "on"}, {"boundingPoly": {"vertices": [{"y": 259, "x": 274}, {"y": 259, "x": 307}, {"y": 271, "x": 307}, {"y": 271, "x": 274}]}, "description": "January"}, {"boundingPoly": {"vertices": [{"y": 259, "x": 314}, {"y": 259, "x": 316}, {"y": 271, "x": 316}, {"y": 271, "x": 314}]}, "description": "1"}, {"boundingPoly": {"vertices": [{"y": 259, "x": 318}, {"y": 259, "x": 320}, {"y": 271, "x": 320}, {"y": 271, "x": 318}]}, "description": ","}, {"boundingPoly": {"vertices": [{"y": 259, "x": 324}, {"y": 259, "x": 341}, {"y": 271, "x": 341}, {"y": 271, "x": 324}]}, "description": "1923"}, {"boundingPoly": {"vertices": [{"y": 259, "x": 342}, {"y": 259, "x": 344}, {"y": 271, "x": 344}, {"y": 271, "x": 342}]}, "description": ","}, {"boundingPoly": {"vertices": [{"y": 259, "x": 348}, {"y": 259, "x": 361}, {"y": 271, "x": 361}, {"y": 271, "x": 348}]}, "description": "the"}, {"boundingPoly": {"vertices": [{"y": 259, "x": 365}, {"y": 259, "x": 379}, {"y": 271, "x": 379}, {"y": 271, "x": 365}]}, "description": "full"}, {"boundingPoly": {"vertices": [{"y": 259, "x": 380}, {"y": 259, "x": 415}, {"y": 271, "x": 415}, {"y": 271, "x": 380}]}, "description": "amount"}, {"boundingPoly": {"vertices": [{"y": 259, "x": 416}, {"y": 259, "x": 434}, {"y": 271, "x": 434}, {"y": 271, "x": 416}]}, "description": "with"}, {"boundingPoly": {"vertices": [{"y": 259, "x": 440}, {"y": 259, "x": 472}, {"y": 271, "x": 472}, {"y": 271, "x": 440}]}, "description": "interest"}, {"boundingPoly": {"vertices": [{"y": 259, "x": 473}, {"y": 259, "x": 485}, {"y": 271, "x": 485}, {"y": 271, "x": 473}]}, "description": "at"}, {"boundingPoly": {"vertices": [{"y": 259, "x": 488}, {"y": 259, "x": 490}, {"y": 271, "x": 490}, {"y": 271, "x": 488}]}, "description": "4"}, {"boundingPoly": {"vertices": [{"y": 259, "x": 495}, {"y": 259, "x": 507}, {"y": 271, "x": 507}, {"y": 271, "x": 495}]}, "description": "per"}, {"boundingPoly": {"vertices": [{"y": 259, "x": 511}, {"y": 259, "x": 529}, {"y": 271, "x": 529}, {"y": 271, "x": 511}]}, "description": "cent"}, {"boundingPoly": {"vertices": [{"y": 259, "x": 532}, {"y": 259, "x": 581}, {"y": 271, "x": 581}, {"y": 271, "x": 532}]}, "description": "compounded"}, {"boundingPoly": {"vertices": [{"y": 259, "x": 589}, {"y": 259, "x": 627}, {"y": 271, "x": 627}, {"y": 271, "x": 589}]}, "description": "quarterly"}, {"boundingPoly": {"vertices": [{"y": 259, "x": 629}, {"y": 259, "x": 631}, {"y": 271, "x": 631}, {"y": 271, "x": 629}]}, "description": "."}, {"boundingPoly": {"vertices": [{"y": 270, "x": 53}, {"y": 270, "x": 66}, {"y": 282, "x": 66}, {"y": 282, "x": 53}]}, "description": "The"}, {"boundingPoly": {"vertices": [{"y": 270, "x": 72}, {"y": 270, "x": 74}, {"y": 282, "x": 74}, {"y": 282, "x": 72}]}, "description": "U"}, {"boundingPoly": {"vertices": [{"y": 270, "x": 77}, {"y": 270, "x": 79}, {"y": 282, "x": 79}, {"y": 282, "x": 77}]}, "description": "."}, {"boundingPoly": {"vertices": [{"y": 270, "x": 84}, {"y": 270, "x": 86}, {"y": 282, "x": 86}, {"y": 282, "x": 84}]}, "description": "S"}, {"boundingPoly": {"vertices": [{"y": 270, "x": 88}, {"y": 270, "x": 90}, {"y": 282, "x": 90}, {"y": 282, "x": 88}]}, "description": "."}, {"boundingPoly": {"vertices": [{"y": 270, "x": 94}, {"y": 270, "x": 118}, {"y": 282, "x": 118}, {"y": 282, "x": 94}]}, "description": "Thrift"}, {"boundingPoly": {"vertices": [{"y": 270, "x": 123}, {"y": 270, "x": 138}, {"y": 282, "x": 138}, {"y": 282, "x": 123}]}, "description": "card"}, {"boundingPoly": {"vertices": [{"y": 270, "x": 144}, {"y": 270, "x": 150}, {"y": 282, "x": 150}, {"y": 282, "x": 144}]}, "description": "is"}, {"boundingPoly": {"vertices": [{"y": 270, "x": 154}, {"y": 270, "x": 156}, {"y": 282, "x": 156}, {"y": 282, "x": 154}]}, "description": "a"}, {"boundingPoly": {"vertices": [{"y": 270, "x": 161}, {"y": 270, "x": 187}, {"y": 282, "x": 187}, {"y": 282, "x": 161}]}, "description": "pocket"}, {"boundingPoly": {"vertices": [{"y": 270, "x": 189}, {"y": 270, "x": 191}, {"y": 282, "x": 191}, {"y": 282, "x": 189}]}, "description": "-"}, {"boundingPoly": {"vertices": [{"y": 270, "x": 193}, {"y": 270, "x": 206}, {"y": 282, "x": 206}, {"y": 282, "x": 193}]}, "description": "size"}, {"boundingPoly": {"vertices": [{"y": 270, "x": 211}, {"y": 270, "x": 226}, {"y": 282, "x": 226}, {"y": 282, "x": 211}]}, "description": "card"}, {"boundingPoly": {"vertices": [{"y": 270, "x": 231}, {"y": 270, "x": 252}, {"y": 282, "x": 252}, {"y": 282, "x": 231}]}, "description": "given"}, {"boundingPoly": {"vertices": [{"y": 270, "x": 258}, {"y": 270, "x": 272}, {"y": 282, "x": 272}, {"y": 282, "x": 258}]}, "description": "free"}, {"boundingPoly": {"vertices": [{"y": 270, "x": 275}, {"y": 270, "x": 284}, {"y": 282, "x": 284}, {"y": 282, "x": 275}]}, "description": "of"}, {"boundingPoly": {"vertices": [{"y": 270, "x": 288}, {"y": 270, "x": 313}, {"y": 282, "x": 313}, {"y": 282, "x": 288}]}, "description": "charge"}, {"boundingPoly": {"vertices": [{"y": 270, "x": 319}, {"y": 270, "x": 324}, {"y": 282, "x": 324}, {"y": 282, "x": 319}]}, "description": "to"}, {"boundingPoly": {"vertices": [{"y": 270, "x": 328}, {"y": 270, "x": 373}, {"y": 282, "x": 373}, {"y": 282, "x": 328}]}, "description": "purchasers"}, {"boundingPoly": {"vertices": [{"y": 270, "x": 379}, {"y": 270, "x": 385}, {"y": 282, "x": 385}, {"y": 282, "x": 379}]}, "description": "of"}, {"boundingPoly": {"vertices": [{"y": 270, "x": 389}, {"y": 270, "x": 391}, {"y": 282, "x": 391}, {"y": 282, "x": 389}]}, "description": "U"}, {"boundingPoly": {"vertices": [{"y": 270, "x": 396}, {"y": 270, "x": 398}, {"y": 282, "x": 398}, {"y": 282, "x": 396}]}, "description": "."}, {"boundingPoly": {"vertices": [{"y": 270, "x": 402}, {"y": 270, "x": 404}, {"y": 282, "x": 404}, {"y": 282, "x": 402}]}, "description": "S"}, {"boundingPoly": {"vertices": [{"y": 270, "x": 406}, {"y": 270, "x": 408}, {"y": 282, "x": 408}, {"y": 282, "x": 406}]}, "description": "."}, {"boundingPoly": {"vertices": [{"y": 270, "x": 414}, {"y": 270, "x": 437}, {"y": 282, "x": 437}, {"y": 282, "x": 414}]}, "description": "Thrift"}, {"boundingPoly": {"vertices": [{"y": 270, "x": 440}, {"y": 270, "x": 471}, {"y": 282, "x": 471}, {"y": 282, "x": 440}]}, "description": "Stamps"}, {"boundingPoly": {"vertices": [{"y": 270, "x": 472}, {"y": 270, "x": 474}, {"y": 282, "x": 474}, {"y": 282, "x": 472}]}, "description": "."}, {"boundingPoly": {"vertices": [{"y": 283, "x": 54}, {"y": 283, "x": 67}, {"y": 293, "x": 67}, {"y": 293, "x": 54}]}, "description": "The"}, {"boundingPoly": {"vertices": [{"y": 283, "x": 70}, {"y": 283, "x": 88}, {"y": 293, "x": 88}, {"y": 293, "x": 70}]}, "description": "War"}, {"boundingPoly": {"vertices": [{"y": 283, "x": 94}, {"y": 283, "x": 125}, {"y": 293, "x": 125}, {"y": 293, "x": 94}]}, "description": "Savings"}, {"boundingPoly": {"vertices": [{"y": 283, "x": 130}, {"y": 283, "x": 171}, {"y": 293, "x": 171}, {"y": 293, "x": 130}]}, "description": "Certificate"}, {"boundingPoly": {"vertices": [{"y": 283, "x": 176}, {"y": 283, "x": 182}, {"y": 293, "x": 182}, {"y": 293, "x": 176}]}, "description": "is"}, {"boundingPoly": {"vertices": [{"y": 283, "x": 187}, {"y": 283, "x": 189}, {"y": 293, "x": 189}, {"y": 293, "x": 187}]}, "description": "a"}, {"boundingPoly": {"vertices": [{"y": 283, "x": 194}, {"y": 283, "x": 220}, {"y": 293, "x": 220}, {"y": 293, "x": 194}]}, "description": "pocket"}, {"boundingPoly": {"vertices": [{"y": 283, "x": 221}, {"y": 283, "x": 223}, {"y": 293, "x": 223}, {"y": 293, "x": 221}]}, "description": "-"}, {"boundingPoly": {"vertices": [{"y": 283, "x": 225}, {"y": 283, "x": 238}, {"y": 293, "x": 238}, {"y": 293, "x": 225}]}, "description": "size"}, {"boundingPoly": {"vertices": [{"y": 283, "x": 243}, {"y": 283, "x": 265}, {"y": 293, "x": 265}, {"y": 293, "x": 243}]}, "description": "folder"}, {"boundingPoly": {"vertices": [{"y": 283, "x": 269}, {"y": 283, "x": 290}, {"y": 293, "x": 290}, {"y": 293, "x": 269}]}, "description": "given"}, {"boundingPoly": {"vertices": [{"y": 283, "x": 297}, {"y": 283, "x": 302}, {"y": 293, "x": 302}, {"y": 293, "x": 297}]}, "description": "to"}, {"boundingPoly": {"vertices": [{"y": 283, "x": 306}, {"y": 283, "x": 335}, {"y": 293, "x": 335}, {"y": 293, "x": 306}]}, "description": "holders"}, {"boundingPoly": {"vertices": [{"y": 283, "x": 339}, {"y": 283, "x": 347}, {"y": 293, "x": 347}, {"y": 293, "x": 339}]}, "description": "of"}, {"boundingPoly": {"vertices": [{"y": 283, "x": 349}, {"y": 283, "x": 368}, {"y": 293, "x": 368}, {"y": 293, "x": 349}]}, "description": "War"}, {"boundingPoly": {"vertices": [{"y": 283, "x": 373}, {"y": 283, "x": 406}, {"y": 293, "x": 406}, {"y": 293, "x": 373}]}, "description": "Savings"}, {"boundingPoly": {"vertices": [{"y": 283, "x": 410}, {"y": 283, "x": 441}, {"y": 293, "x": 441}, {"y": 293, "x": 410}]}, "description": "Stamps"}, {"boundingPoly": {"vertices": [{"y": 283, "x": 442}, {"y": 283, "x": 444}, {"y": 293, "x": 444}, {"y": 293, "x": 442}]}, "description": "."}, {"boundingPoly": {"vertices": [{"y": 295, "x": 51}, {"y": 295, "x": 69}, {"y": 305, "x": 69}, {"y": 305, "x": 51}]}, "description": "War"}, {"boundingPoly": {"vertices": [{"y": 295, "x": 74}, {"y": 295, "x": 106}, {"y": 305, "x": 106}, {"y": 305, "x": 74}]}, "description": "Savings"}, {"boundingPoly": {"vertices": [{"y": 295, "x": 112}, {"y": 295, "x": 143}, {"y": 305, "x": 143}, {"y": 305, "x": 112}]}, "description": "Stamps"}, {"boundingPoly": {"vertices": [{"y": 295, "x": 145}, {"y": 295, "x": 158}, {"y": 305, "x": 158}, {"y": 305, "x": 145}]}, "description": "are"}, {"boundingPoly": {"vertices": [{"y": 295, "x": 162}, {"y": 295, "x": 170}, {"y": 305, "x": 170}, {"y": 305, "x": 162}]}, "description": "as"}, {"boundingPoly": {"vertices": [{"y": 295, "x": 175}, {"y": 295, "x": 190}, {"y": 305, "x": 190}, {"y": 305, "x": 175}]}, "description": "safe"}, {"boundingPoly": {"vertices": [{"y": 295, "x": 194}, {"y": 295, "x": 202}, {"y": 305, "x": 202}, {"y": 305, "x": 194}]}, "description": "as"}, {"boundingPoly": {"vertices": [{"y": 295, "x": 207}, {"y": 295, "x": 220}, {"y": 305, "x": 220}, {"y": 305, "x": 207}]}, "description": "the"}, {"boundingPoly": {"vertices": [{"y": 295, "x": 223}, {"y": 295, "x": 248}, {"y": 305, "x": 248}, {"y": 305, "x": 223}]}, "description": "United"}, {"boundingPoly": {"vertices": [{"y": 295, "x": 255}, {"y": 295, "x": 278}, {"y": 305, "x": 278}, {"y": 305, "x": 255}]}, "description": "States"}, {"boundingPoly": {"vertices": [{"y": 295, "x": 280}, {"y": 295, "x": 282}, {"y": 305, "x": 282}, {"y": 305, "x": 280}]}, "description": "."}, {"boundingPoly": {"vertices": [{"y": 315, "x": 32}, {"y": 315, "x": 110}, {"y": 354, "x": 110}, {"y": 354, "x": 32}]}, "description": "Why"}, {"boundingPoly": {"vertices": [{"y": 315, "x": 126}, {"y": 315, "x": 221}, {"y": 354, "x": 221}, {"y": 354, "x": 126}]}, "description": "Should"}, {"boundingPoly": {"vertices": [{"y": 315, "x": 239}, {"y": 315, "x": 250}, {"y": 354, "x": 250}, {"y": 354, "x": 239}]}, "description": "I"}, {"boundingPoly": {"vertices": [{"y": 315, "x": 264}, {"y": 315, "x": 320}, {"y": 354, "x": 320}, {"y": 354, "x": 264}]}, "description": "Buy"}, {"boundingPoly": {"vertices": [{"y": 315, "x": 342}, {"y": 315, "x": 407}, {"y": 354, "x": 407}, {"y": 354, "x": 342}]}, "description": "Them"}, {"boundingPoly": {"vertices": [{"y": 315, "x": 423}, {"y": 315, "x": 434}, {"y": 354, "x": 434}, {"y": 354, "x": 423}]}, "description": "?"}, {"boundingPoly": {"vertices": [{"y": 315, "x": 457}, {"y": 315, "x": 511}, {"y": 354, "x": 511}, {"y": 354, "x": 457}]}, "description": "BECAUSE"}, {"boundingPoly": {"vertices": [{"y": 315, "x": 520}, {"y": 315, "x": 541}, {"y": 354, "x": 541}, {"y": 354, "x": 520}]}, "description": "WE"}, {"boundingPoly": {"vertices": [{"y": 315, "x": 549}, {"y": 315, "x": 571}, {"y": 354, "x": 571}, {"y": 354, "x": 549}]}, "description": "ARE"}, {"boundingPoly": {"vertices": [{"y": 315, "x": 581}, {"y": 315, "x": 595}, {"y": 354, "x": 595}, {"y": 354, "x": 581}]}, "description": "AT"}, {"boundingPoly": {"vertices": [{"y": 315, "x": 604}, {"y": 315, "x": 631}, {"y": 354, "x": 631}, {"y": 354, "x": 604}]}, "description": "WAR"}, {"boundingPoly": {"vertices": [{"y": 360, "x": 52}, {"y": 360, "x": 92}, {"y": 372, "x": 92}, {"y": 372, "x": 52}]}, "description": "BECAUSE"}, {"boundingPoly": {"vertices": [{"y": 360, "x": 97}, {"y": 360, "x": 99}, {"y": 372, "x": 99}, {"y": 372, "x": 97}]}, "description": "-"}, {"boundingPoly": {"vertices": [{"y": 360, "x": 99}, {"y": 360, "x": 101}, {"y": 372, "x": 101}, {"y": 372, "x": 99}]}, "description": "-"}, {"boundingPoly": {"vertices": [{"y": 360, "x": 104}, {"y": 360, "x": 116}, {"y": 372, "x": 116}, {"y": 372, "x": 104}]}, "description": "the"}, {"boundingPoly": {"vertices": [{"y": 360, "x": 118}, {"y": 360, "x": 139}, {"y": 372, "x": 139}, {"y": 372, "x": 118}]}, "description": "more"}, {"boundingPoly": {"vertices": [{"y": 360, "x": 144}, {"y": 360, "x": 155}, {"y": 372, "x": 155}, {"y": 372, "x": 144}]}, "description": "we"}, {"boundingPoly": {"vertices": [{"y": 360, "x": 158}, {"y": 360, "x": 174}, {"y": 372, "x": 174}, {"y": 372, "x": 158}]}, "description": "save"}, {"boundingPoly": {"vertices": [{"y": 360, "x": 176}, {"y": 360, "x": 178}, {"y": 372, "x": 178}, {"y": 372, "x": 176}]}, "description": ","}, {"boundingPoly": {"vertices": [{"y": 360, "x": 181}, {"y": 360, "x": 193}, {"y": 372, "x": 193}, {"y": 372, "x": 181}]}, "description": "the"}, {"boundingPoly": {"vertices": [{"y": 360, "x": 195}, {"y": 360, "x": 216}, {"y": 372, "x": 216}, {"y": 372, "x": 195}]}, "description": "more"}, {"boundingPoly": {"vertices": [{"y": 360, "x": 219}, {"y": 360, "x": 239}, {"y": 372, "x": 239}, {"y": 372, "x": 219}]}, "description": "labor"}, {"boundingPoly": {"vertices": [{"y": 360, "x": 243}, {"y": 360, "x": 256}, {"y": 372, "x": 256}, {"y": 372, "x": 243}]}, "description": "and"}, {"boundingPoly": {"vertices": [{"y": 360, "x": 260}, {"y": 360, "x": 297}, {"y": 372, "x": 297}, {"y": 372, "x": 260}]}, "description": "material"}, {"boundingPoly": {"vertices": [{"y": 360, "x": 300}, {"y": 360, "x": 316}, {"y": 372, "x": 316}, {"y": 372, "x": 300}]}, "description": "will"}, {"boundingPoly": {"vertices": [{"y": 360, "x": 318}, {"y": 360, "x": 326}, {"y": 372, "x": 326}, {"y": 372, "x": 318}]}, "description": "be"}, {"boundingPoly": {"vertices": [{"y": 360, "x": 330}, {"y": 360, "x": 366}, {"y": 372, "x": 366}, {"y": 372, "x": 330}]}, "description": "available"}, {"boundingPoly": {"vertices": [{"y": 360, "x": 371}, {"y": 360, "x": 381}, {"y": 372, "x": 381}, {"y": 372, "x": 371}]}, "description": "for"}, {"boundingPoly": {"vertices": [{"y": 360, "x": 385}, {"y": 360, "x": 398}, {"y": 372, "x": 398}, {"y": 372, "x": 385}]}, "description": "the"}, {"boundingPoly": {"vertices": [{"y": 360, "x": 400}, {"y": 360, "x": 412}, {"y": 372, "x": 412}, {"y": 372, "x": 400}]}, "description": "use"}, {"boundingPoly": {"vertices": [{"y": 360, "x": 415}, {"y": 360, "x": 424}, {"y": 372, "x": 424}, {"y": 372, "x": 415}]}, "description": "of"}, {"boundingPoly": {"vertices": [{"y": 360, "x": 427}, {"y": 360, "x": 439}, {"y": 372, "x": 439}, {"y": 372, "x": 427}]}, "description": "the"}, {"boundingPoly": {"vertices": [{"y": 360, "x": 441}, {"y": 360, "x": 493}, {"y": 372, "x": 493}, {"y": 372, "x": 441}]}, "description": "Government"}, {"boundingPoly": {"vertices": [{"y": 360, "x": 496}, {"y": 360, "x": 510}, {"y": 372, "x": 510}, {"y": 372, "x": 496}]}, "description": "and"}, {"boundingPoly": {"vertices": [{"y": 360, "x": 514}, {"y": 360, "x": 525}, {"y": 372, "x": 525}, {"y": 372, "x": 514}]}, "description": "for"}, {"boundingPoly": {"vertices": [{"y": 360, "x": 528}, {"y": 360, "x": 542}, {"y": 372, "x": 542}, {"y": 372, "x": 528}]}, "description": "the"}, {"boundingPoly": {"vertices": [{"y": 360, "x": 543}, {"y": 360, "x": 576}, {"y": 372, "x": 576}, {"y": 372, "x": 543}]}, "description": "support"}, {"boundingPoly": {"vertices": [{"y": 360, "x": 578}, {"y": 360, "x": 586}, {"y": 372, "x": 586}, {"y": 372, "x": 578}]}, "description": "of"}, {"boundingPoly": {"vertices": [{"y": 360, "x": 589}, {"y": 360, "x": 603}, {"y": 372, "x": 603}, {"y": 372, "x": 589}]}, "description": "our"}, {"boundingPoly": {"vertices": [{"y": 360, "x": 603}, {"y": 360, "x": 629}, {"y": 372, "x": 629}, {"y": 372, "x": 603}]}, "description": "army"}, {"boundingPoly": {"vertices": [{"y": 360, "x": 628}, {"y": 360, "x": 630}, {"y": 372, "x": 630}, {"y": 372, "x": 628}]}, "description": "."}, {"boundingPoly": {"vertices": [{"y": 371, "x": 51}, {"y": 371, "x": 94}, {"y": 382, "x": 94}, {"y": 382, "x": 51}]}, "description": "BECAUSE"}, {"boundingPoly": {"vertices": [{"y": 371, "x": 99}, {"y": 371, "x": 101}, {"y": 382, "x": 101}, {"y": 382, "x": 99}]}, "description": "-"}, {"boundingPoly": {"vertices": [{"y": 371, "x": 105}, {"y": 371, "x": 117}, {"y": 382, "x": 117}, {"y": 382, "x": 105}]}, "description": "we"}, {"boundingPoly": {"vertices": [{"y": 371, "x": 120}, {"y": 371, "x": 142}, {"y": 383, "x": 142}, {"y": 383, "x": 120}]}, "description": "must"}, {"boundingPoly": {"vertices": [{"y": 372, "x": 147}, {"y": 372, "x": 167}, {"y": 383, "x": 167}, {"y": 383, "x": 147}]}, "description": "have"}, {"boundingPoly": {"vertices": [{"y": 372, "x": 172}, {"y": 372, "x": 199}, {"y": 383, "x": 199}, {"y": 383, "x": 172}]}, "description": "dollars"}, {"boundingPoly": {"vertices": [{"y": 372, "x": 204}, {"y": 372, "x": 211}, {"y": 383, "x": 211}, {"y": 383, "x": 204}]}, "description": "as"}, {"boundingPoly": {"vertices": [{"y": 372, "x": 215}, {"y": 372, "x": 233}, {"y": 383, "x": 233}, {"y": 383, "x": 215}]}, "description": "well"}, {"boundingPoly": {"vertices": [{"y": 372, "x": 237}, {"y": 372, "x": 247}, {"y": 383, "x": 247}, {"y": 383, "x": 237}]}, "description": "as"}, {"boundingPoly": {"vertices": [{"y": 372, "x": 250}, {"y": 372, "x": 267}, {"y": 383, "x": 267}, {"y": 383, "x": 250}]}, "description": "men"}, {"boundingPoly": {"vertices": [{"y": 372, "x": 275}, {"y": 372, "x": 280}, {"y": 383, "x": 280}, {"y": 383, "x": 275}]}, "description": "in"}, {"boundingPoly": {"vertices": [{"y": 372, "x": 288}, {"y": 372, "x": 300}, {"y": 383, "x": 300}, {"y": 383, "x": 288}]}, "description": "the"}, {"boundingPoly": {"vertices": [{"y": 373, "x": 305}, {"y": 373, "x": 326}, {"y": 384, "x": 326}, {"y": 384, "x": 305}]}, "description": "fight"}, {"boundingPoly": {"vertices": [{"y": 373, "x": 330}, {"y": 373, "x": 342}, {"y": 384, "x": 342}, {"y": 384, "x": 330}]}, "description": "for"}, {"boundingPoly": {"vertices": [{"y": 373, "x": 347}, {"y": 373, "x": 375}, {"y": 384, "x": 375}, {"y": 384, "x": 347}]}, "description": "freedom"}, {"boundingPoly": {"vertices": [{"y": 373, "x": 381}, {"y": 373, "x": 383}, {"y": 384, "x": 383}, {"y": 384, "x": 381}]}, "description": "."}, {"boundingPoly": {"vertices": [{"y": 383, "x": 51}, {"y": 383, "x": 94}, {"y": 394, "x": 94}, {"y": 394, "x": 51}]}, "description": "BECAUSE"}, {"boundingPoly": {"vertices": [{"y": 383, "x": 98}, {"y": 383, "x": 100}, {"y": 394, "x": 100}, {"y": 394, "x": 98}]}, "description": "-"}, {"boundingPoly": {"vertices": [{"y": 383, "x": 105}, {"y": 383, "x": 121}, {"y": 394, "x": 121}, {"y": 394, "x": 105}]}, "description": "they"}, {"boundingPoly": {"vertices": [{"y": 383, "x": 129}, {"y": 383, "x": 162}, {"y": 394, "x": 162}, {"y": 394, "x": 129}]}, "description": "establish"}, {"boundingPoly": {"vertices": [{"y": 384, "x": 171}, {"y": 384, "x": 181}, {"y": 395, "x": 181}, {"y": 395, "x": 171}]}, "description": "the"}, {"boundingPoly": {"vertices": [{"y": 384, "x": 189}, {"y": 384, "x": 225}, {"y": 395, "x": 225}, {"y": 395, "x": 189}]}, "description": "soundest"}, {"boundingPoly": {"vertices": [{"y": 384, "x": 230}, {"y": 384, "x": 244}, {"y": 395, "x": 244}, {"y": 395, "x": 230}]}, "description": "and"}, {"boundingPoly": {"vertices": [{"y": 384, "x": 250}, {"y": 384, "x": 283}, {"y": 395, "x": 283}, {"y": 395, "x": 250}]}, "description": "simplest"}, {"boundingPoly": {"vertices": [{"y": 384, "x": 290}, {"y": 384, "x": 310}, {"y": 395, "x": 310}, {"y": 395, "x": 290}]}, "description": "basis"}, {"boundingPoly": {"vertices": [{"y": 384, "x": 315}, {"y": 384, "x": 323}, {"y": 395, "x": 323}, {"y": 395, "x": 315}]}, "description": "of"}, {"boundingPoly": {"vertices": [{"y": 384, "x": 327}, {"y": 384, "x": 354}, {"y": 395, "x": 354}, {"y": 395, "x": 327}]}, "description": "saving"}, {"boundingPoly": {"vertices": [{"y": 384, "x": 356}, {"y": 384, "x": 358}, {"y": 395, "x": 358}, {"y": 395, "x": 356}]}, "description": ","}, {"boundingPoly": {"vertices": [{"y": 384, "x": 361}, {"y": 384, "x": 384}, {"y": 395, "x": 384}, {"y": 395, "x": 361}]}, "description": "which"}, {"boundingPoly": {"vertices": [{"y": 384, "x": 392}, {"y": 384, "x": 397}, {"y": 395, "x": 397}, {"y": 395, "x": 392}]}, "description": "is"}, {"boundingPoly": {"vertices": [{"y": 384, "x": 404}, {"y": 384, "x": 416}, {"y": 396, "x": 416}, {"y": 396, "x": 404}]}, "description": "the"}, {"boundingPoly": {"vertices": [{"y": 385, "x": 421}, {"y": 385, "x": 433}, {"y": 396, "x": 433}, {"y": 396, "x": 421}]}, "description": "key"}, {"boundingPoly": {"vertices": [{"y": 385, "x": 441}, {"y": 385, "x": 447}, {"y": 396, "x": 447}, {"y": 396, "x": 441}]}, "description": "to"}, {"boundingPoly": {"vertices": [{"y": 385, "x": 453}, {"y": 385, "x": 498}, {"y": 396, "x": 498}, {"y": 396, "x": 453}]}, "description": "individual"}, {"boundingPoly": {"vertices": [{"y": 385, "x": 502}, {"y": 385, "x": 531}, {"y": 396, "x": 531}, {"y": 396, "x": 502}]}, "description": "success"}, {"boundingPoly": {"vertices": [{"y": 395, "x": 52}, {"y": 395, "x": 93}, {"y": 405, "x": 93}, {"y": 405, "x": 52}]}, "description": "BECAUSE"}, {"boundingPoly": {"vertices": [{"y": 395, "x": 105}, {"y": 395, "x": 124}, {"y": 406, "x": 124}, {"y": 406, "x": 105}]}, "description": "there"}, {"boundingPoly": {"vertices": [{"y": 396, "x": 131}, {"y": 396, "x": 136}, {"y": 406, "x": 136}, {"y": 406, "x": 131}]}, "description": "is"}, {"boundingPoly": {"vertices": [{"y": 396, "x": 143}, {"y": 396, "x": 151}, {"y": 406, "x": 151}, {"y": 406, "x": 143}]}, "description": "no"}, {"boundingPoly": {"vertices": [{"y": 396, "x": 157}, {"y": 396, "x": 177}, {"y": 406, "x": 177}, {"y": 406, "x": 157}]}, "description": "safer"}, {"boundingPoly": {"vertices": [{"y": 396, "x": 181}, {"y": 396, "x": 230}, {"y": 406, "x": 230}, {"y": 406, "x": 181}]}, "description": "investment"}, {"boundingPoly": {"vertices": [{"y": 397, "x": 233}, {"y": 397, "x": 238}, {"y": 407, "x": 238}, {"y": 407, "x": 233}]}, "description": "in"}, {"boundingPoly": {"vertices": [{"y": 397, "x": 246}, {"y": 397, "x": 259}, {"y": 407, "x": 259}, {"y": 407, "x": 246}]}, "description": "the"}, {"boundingPoly": {"vertices": [{"y": 397, "x": 264}, {"y": 397, "x": 286}, {"y": 407, "x": 286}, {"y": 407, "x": 264}]}, "description": "world"}, {"boundingPoly": {"vertices": [{"y": 397, "x": 288}, {"y": 397, "x": 290}, {"y": 407, "x": 290}, {"y": 407, "x": 288}]}, "description": "."}, {"boundingPoly": {"vertices": [{"y": 407, "x": 50}, {"y": 407, "x": 93}, {"y": 418, "x": 93}, {"y": 418, "x": 50}]}, "description": "BECAUSE"}, {"boundingPoly": {"vertices": [{"y": 407, "x": 98}, {"y": 407, "x": 100}, {"y": 418, "x": 100}, {"y": 418, "x": 98}]}, "description": "-"}, {"boundingPoly": {"vertices": [{"y": 407, "x": 104}, {"y": 407, "x": 123}, {"y": 418, "x": 123}, {"y": 418, "x": 104}]}, "description": "War"}, {"boundingPoly": {"vertices": [{"y": 407, "x": 128}, {"y": 407, "x": 162}, {"y": 418, "x": 162}, {"y": 418, "x": 128}]}, "description": "Savings"}, {"boundingPoly": {"vertices": [{"y": 407, "x": 166}, {"y": 407, "x": 197}, {"y": 418, "x": 197}, {"y": 418, "x": 166}]}, "description": "Stamps"}, {"boundingPoly": {"vertices": [{"y": 407, "x": 200}, {"y": 407, "x": 223}, {"y": 418, "x": 223}, {"y": 418, "x": 200}]}, "description": "must"}, {"boundingPoly": {"vertices": [{"y": 407, "x": 230}, {"y": 407, "x": 262}, {"y": 418, "x": 262}, {"y": 418, "x": 230}]}, "description": "increase"}, {"boundingPoly": {"vertices": [{"y": 407, "x": 267}, {"y": 407, "x": 285}, {"y": 418, "x": 285}, {"y": 418, "x": 267}]}, "description": "each"}, {"boundingPoly": {"vertices": [{"y": 407, "x": 290}, {"y": 407, "x": 317}, {"y": 418, "x": 317}, {"y": 418, "x": 290}]}, "description": "month"}, {"boundingPoly": {"vertices": [{"y": 407, "x": 324}, {"y": 407, "x": 330}, {"y": 418, "x": 330}, {"y": 418, "x": 324}]}, "description": "in"}, {"boundingPoly": {"vertices": [{"y": 407, "x": 338}, {"y": 407, "x": 359}, {"y": 418, "x": 359}, {"y": 418, "x": 338}]}, "description": "value"}, {"boundingPoly": {"vertices": [{"y": 407, "x": 360}, {"y": 407, "x": 362}, {"y": 418, "x": 362}, {"y": 418, "x": 360}]}, "description": "."}, {"boundingPoly": {"vertices": [{"y": 423, "x": 35}, {"y": 424, "x": 99}, {"y": 464, "x": 98}, {"y": 463, "x": 34}]}, "description": "How"}, {"boundingPoly": {"vertices": [{"y": 425, "x": 129}, {"y": 426, "x": 181}, {"y": 467, "x": 180}, {"y": 466, "x": 128}]}, "description": "Can"}, {"boundingPoly": {"vertices": [{"y": 427, "x": 203}, {"y": 427, "x": 214}, {"y": 467, "x": 213}, {"y": 467, "x": 202}]}, "description": "I"}, {"boundingPoly": {"vertices": [{"y": 427, "x": 229}, {"y": 428, "x": 287}, {"y": 469, "x": 286}, {"y": 468, "x": 228}]}, "description": "Buy"}, {"boundingPoly": {"vertices": [{"y": 429, "x": 313}, {"y": 430, "x": 379}, {"y": 470, "x": 378}, {"y": 469, "x": 312}]}, "description": "Them"}, {"boundingPoly": {"vertices": [{"y": 431, "x": 396}, {"y": 431, "x": 407}, {"y": 471, "x": 406}, {"y": 471, "x": 395}]}, "description": "?"}, {"boundingPoly": {"vertices": [{"y": 432, "x": 434}, {"y": 432, "x": 455}, {"y": 472, "x": 454}, {"y": 472, "x": 433}]}, "description": "AS"}, {"boundingPoly": {"vertices": [{"y": 431, "x": 454}, {"y": 433, "x": 532}, {"y": 474, "x": 531}, {"y": 472, "x": 453}]}, "description": "POSTALE"}, {"boundingPoly": {"vertices": [{"y": 434, "x": 547}, {"y": 435, "x": 610}, {"y": 475, "x": 609}, {"y": 474, "x": 546}]}, "description": "STAMPS"}, {"boundingPoly": {"vertices": [{"y": 430, "x": 431}, {"y": 430, "x": 450}, {"y": 448, "x": 450}, {"y": 448, "x": 431}]}, "description": "AS"}, {"boundingPoly": {"vertices": [{"y": 430, "x": 462}, {"y": 430, "x": 522}, {"y": 448, "x": 522}, {"y": 448, "x": 462}]}, "description": "SIMPLY"}, {"boundingPoly": {"vertices": [{"y": 430, "x": 535}, {"y": 430, "x": 556}, {"y": 448, "x": 556}, {"y": 448, "x": 535}]}, "description": "AS"}, {"boundingPoly": {"vertices": [{"y": 430, "x": 566}, {"y": 430, "x": 628}, {"y": 448, "x": 628}, {"y": 448, "x": 566}]}, "description": "BUYING"}, {"boundingPoly": {"vertices": [{"y": 449, "x": 455}, {"y": 449, "x": 529}, {"y": 465, "x": 529}, {"y": 465, "x": 455}]}, "description": "POSTAGE"}, {"boundingPoly": {"vertices": [{"y": 449, "x": 540}, {"y": 449, "x": 606}, {"y": 465, "x": 606}, {"y": 465, "x": 540}]}, "description": "STAMPS"}, {"boundingPoly": {"vertices": [{"y": 472, "x": 52}, {"y": 472, "x": 68}, {"y": 483, "x": 68}, {"y": 483, "x": 52}]}, "description": "This"}, {"boundingPoly": {"vertices": [{"y": 472, "x": 74}, {"y": 472, "x": 80}, {"y": 483, "x": 80}, {"y": 483, "x": 74}]}, "description": "is"}, {"boundingPoly": {"vertices": [{"y": 472, "x": 86}, {"y": 472, "x": 99}, {"y": 483, "x": 99}, {"y": 483, "x": 86}]}, "description": "the"}, {"boundingPoly": {"vertices": [{"y": 472, "x": 104}, {"y": 472, "x": 138}, {"y": 483, "x": 138}, {"y": 483, "x": 104}]}, "description": "simplest"}, {"boundingPoly": {"vertices": [{"y": 472, "x": 145}, {"y": 472, "x": 174}, {"y": 483, "x": 174}, {"y": 483, "x": 145}]}, "description": "security"}, {"boundingPoly": {"vertices": [{"y": 472, "x": 181}, {"y": 472, "x": 196}, {"y": 484, "x": 196}, {"y": 484, "x": 181}]}, "description": "ever"}, {"boundingPoly": {"vertices": [{"y": 473, "x": 202}, {"y": 473, "x": 228}, {"y": 484, "x": 228}, {"y": 484, "x": 202}]}, "description": "offered"}, {"boundingPoly": {"vertices": [{"y": 473, "x": 235}, {"y": 473, "x": 242}, {"y": 484, "x": 242}, {"y": 484, "x": 235}]}, "description": "by"}, {"boundingPoly": {"vertices": [{"y": 473, "x": 248}, {"y": 473, "x": 250}, {"y": 484, "x": 250}, {"y": 484, "x": 248}]}, "description": "a"}, {"boundingPoly": {"vertices": [{"y": 473, "x": 257}, {"y": 473, "x": 278}, {"y": 484, "x": 278}, {"y": 484, "x": 257}]}, "description": "great"}, {"boundingPoly": {"vertices": [{"y": 473, "x": 284}, {"y": 473, "x": 334}, {"y": 484, "x": 334}, {"y": 484, "x": 284}]}, "description": "government"}, {"boundingPoly": {"vertices": [{"y": 473, "x": 338}, {"y": 473, "x": 344}, {"y": 484, "x": 344}, {"y": 484, "x": 338}]}, "description": "to"}, {"boundingPoly": {"vertices": [{"y": 473, "x": 349}, {"y": 473, "x": 358}, {"y": 484, "x": 358}, {"y": 484, "x": 349}]}, "description": "its"}, {"boundingPoly": {"vertices": [{"y": 473, "x": 364}, {"y": 473, "x": 388}, {"y": 484, "x": 388}, {"y": 484, "x": 364}]}, "description": "people"}, {"boundingPoly": {"vertices": [{"y": 473, "x": 390}, {"y": 473, "x": 392}, {"y": 484, "x": 392}, {"y": 484, "x": 390}]}, "description": "."}, {"boundingPoly": {"vertices": [{"y": 473, "x": 403}, {"y": 473, "x": 417}, {"y": 484, "x": 417}, {"y": 484, "x": 403}]}, "description": "Any"}, {"boundingPoly": {"vertices": [{"y": 473, "x": 420}, {"y": 473, "x": 438}, {"y": 484, "x": 438}, {"y": 484, "x": 420}]}, "description": "man"}, {"boundingPoly": {"vertices": [{"y": 473, "x": 440}, {"y": 473, "x": 442}, {"y": 484, "x": 442}, {"y": 484, "x": 440}]}, "description": ","}, {"boundingPoly": {"vertices": [{"y": 473, "x": 446}, {"y": 473, "x": 474}, {"y": 484, "x": 474}, {"y": 484, "x": 446}]}, "description": "woman"}, {"boundingPoly": {"vertices": [{"y": 473, "x": 478}, {"y": 473, "x": 480}, {"y": 484, "x": 480}, {"y": 484, "x": 478}]}, "description": ","}, {"boundingPoly": {"vertices": [{"y": 474, "x": 484}, {"y": 474, "x": 492}, {"y": 485, "x": 492}, {"y": 485, "x": 484}]}, "description": "or"}, {"boundingPoly": {"vertices": [{"y": 474, "x": 496}, {"y": 474, "x": 515}, {"y": 485, "x": 515}, {"y": 485, "x": 496}]}, "description": "child"}, {"boundingPoly": {"vertices": [{"y": 474, "x": 520}, {"y": 474, "x": 538}, {"y": 485, "x": 538}, {"y": 485, "x": 520}]}, "description": "who"}, {"boundingPoly": {"vertices": [{"y": 474, "x": 542}, {"y": 474, "x": 555}, {"y": 485, "x": 555}, {"y": 485, "x": 542}]}, "description": "can"}, {"boundingPoly": {"vertices": [{"y": 474, "x": 560}, {"y": 474, "x": 576}, {"y": 485, "x": 576}, {"y": 485, "x": 560}]}, "description": "save"}, {"boundingPoly": {"vertices": [{"y": 474, "x": 581}, {"y": 474, "x": 609}, {"y": 485, "x": 609}, {"y": 485, "x": 581}]}, "description": "twenty"}, {"boundingPoly": {"vertices": [{"y": 474, "x": 612}, {"y": 474, "x": 614}, {"y": 485, "x": 614}, {"y": 485, "x": 612}]}, "description": "-"}, {"boundingPoly": {"vertices": [{"y": 474, "x": 615}, {"y": 474, "x": 630}, {"y": 485, "x": 630}, {"y": 485, "x": 615}]}, "description": "five"}, {"boundingPoly": {"vertices": [{"y": 483, "x": 69}, {"y": 483, "x": 89}, {"y": 494, "x": 89}, {"y": 494, "x": 69}]}, "description": "cents"}, {"boundingPoly": {"vertices": [{"y": 483, "x": 94}, {"y": 483, "x": 105}, {"y": 494, "x": 105}, {"y": 494, "x": 94}]}, "description": "can"}, {"boundingPoly": {"vertices": [{"y": 483, "x": 111}, {"y": 483, "x": 135}, {"y": 494, "x": 135}, {"y": 494, "x": 111}]}, "description": "obtain"}, {"boundingPoly": {"vertices": [{"y": 483, "x": 141}, {"y": 483, "x": 149}, {"y": 494, "x": 149}, {"y": 494, "x": 141}]}, "description": "at"}, {"boundingPoly": {"vertices": [{"y": 483, "x": 153}, {"y": 483, "x": 167}, {"y": 495, "x": 167}, {"y": 495, "x": 153}]}, "description": "any"}, {"boundingPoly": {"vertices": [{"y": 484, "x": 171}, {"y": 484, "x": 189}, {"y": 495, "x": 189}, {"y": 495, "x": 171}]}, "description": "Post"}, {"boundingPoly": {"vertices": [{"y": 484, "x": 193}, {"y": 484, "x": 215}, {"y": 495, "x": 215}, {"y": 495, "x": 193}]}, "description": "Office"}, {"boundingPoly": {"vertices": [{"y": 484, "x": 219}, {"y": 484, "x": 227}, {"y": 495, "x": 227}, {"y": 495, "x": 219}]}, "description": "or"}, {"boundingPoly": {"vertices": [{"y": 484, "x": 231}, {"y": 484, "x": 252}, {"y": 495, "x": 252}, {"y": 495, "x": 231}]}, "description": "Bank"}, {"boundingPoly": {"vertices": [{"y": 484, "x": 257}, {"y": 484, "x": 259}, {"y": 495, "x": 259}, {"y": 495, "x": 257}]}, "description": "a"}, {"boundingPoly": {"vertices": [{"y": 484, "x": 266}, {"y": 484, "x": 268}, {"y": 495, "x": 268}, {"y": 495, "x": 266}]}, "description": "U"}, {"boundingPoly": {"vertices": [{"y": 484, "x": 271}, {"y": 484, "x": 273}, {"y": 495, "x": 273}, {"y": 495, "x": 271}]}, "description": "."}, {"boundingPoly": {"vertices": [{"y": 484, "x": 278}, {"y": 484, "x": 280}, {"y": 495, "x": 280}, {"y": 495, "x": 278}]}, "description": "S"}, {"boundingPoly": {"vertices": [{"y": 484, "x": 283}, {"y": 484, "x": 285}, {"y": 495, "x": 285}, {"y": 495, "x": 283}]}, "description": "."}, {"boundingPoly": {"vertices": [{"y": 484, "x": 288}, {"y": 484, "x": 340}, {"y": 495, "x": 340}, {"y": 495, "x": 288}]}, "description": "Government"}, {"boundingPoly": {"vertices": [{"y": 484, "x": 345}, {"y": 484, "x": 367}, {"y": 496, "x": 367}, {"y": 496, "x": 345}]}, "description": "Thrift"}, {"boundingPoly": {"vertices": [{"y": 485, "x": 372}, {"y": 485, "x": 399}, {"y": 496, "x": 399}, {"y": 496, "x": 372}]}, "description": "Stamp"}, {"boundingPoly": {"vertices": [{"y": 485, "x": 402}, {"y": 485, "x": 416}, {"y": 496, "x": 416}, {"y": 496, "x": 402}]}, "description": "and"}, {"boundingPoly": {"vertices": [{"y": 485, "x": 422}, {"y": 485, "x": 424}, {"y": 496, "x": 424}, {"y": 496, "x": 422}]}, "description": "a"}, {"boundingPoly": {"vertices": [{"y": 485, "x": 431}, {"y": 485, "x": 455}, {"y": 496, "x": 455}, {"y": 496, "x": 431}]}, "description": "Thrift"}, {"boundingPoly": {"vertices": [{"y": 485, "x": 459}, {"y": 485, "x": 474}, {"y": 496, "x": 474}, {"y": 496, "x": 459}]}, "description": "card"}, {"boundingPoly": {"vertices": [{"y": 485, "x": 482}, {"y": 485, "x": 487}, {"y": 496, "x": 487}, {"y": 496, "x": 482}]}, "description": "to"}, {"boundingPoly": {"vertices": [{"y": 485, "x": 491}, {"y": 485, "x": 515}, {"y": 496, "x": 515}, {"y": 496, "x": 491}]}, "description": "which"}, {"boundingPoly": {"vertices": [{"y": 485, "x": 524}, {"y": 485, "x": 529}, {"y": 496, "x": 529}, {"y": 496, "x": 524}]}, "description": "to"}, {"boundingPoly": {"vertices": [{"y": 486, "x": 535}, {"y": 486, "x": 559}, {"y": 497, "x": 559}, {"y": 497, "x": 535}]}, "description": "attach"}, {"boundingPoly": {"vertices": [{"y": 486, "x": 566}, {"y": 486, "x": 571}, {"y": 497, "x": 571}, {"y": 497, "x": 566}]}, "description": "it"}, {"boundingPoly": {"vertices": [{"y": 486, "x": 573}, {"y": 486, "x": 575}, {"y": 497, "x": 575}, {"y": 497, "x": 573}]}, "description": "."}, {"boundingPoly": {"vertices": [{"y": 486, "x": 586}, {"y": 486, "x": 601}, {"y": 497, "x": 601}, {"y": 497, "x": 586}]}, "description": "This"}, {"boundingPoly": {"vertices": [{"y": 486, "x": 606}, {"y": 486, "x": 629}, {"y": 497, "x": 629}, {"y": 497, "x": 606}]}, "description": "starts"}, {"boundingPoly": {"vertices": [{"y": 497, "x": 69}, {"y": 497, "x": 81}, {"y": 507, "x": 81}, {"y": 507, "x": 69}]}, "description": "you"}, {"boundingPoly": {"vertices": [{"y": 497, "x": 87}, {"y": 497, "x": 96}, {"y": 507, "x": 96}, {"y": 507, "x": 87}]}, "description": "as"}, {"boundingPoly": {"vertices": [{"y": 497, "x": 101}, {"y": 497, "x": 109}, {"y": 507, "x": 109}, {"y": 507, "x": 101}]}, "description": "an"}, {"boundingPoly": {"vertices": [{"y": 497, "x": 117}, {"y": 497, "x": 149}, {"y": 507, "x": 149}, {"y": 507, "x": 117}]}, "description": "investor"}, {"boundingPoly": {"vertices": [{"y": 497, "x": 150}, {"y": 497, "x": 152}, {"y": 507, "x": 152}, {"y": 507, "x": 150}]}, "description": ","}, {"boundingPoly": {"vertices": [{"y": 497, "x": 156}, {"y": 497, "x": 171}, {"y": 507, "x": 171}, {"y": 507, "x": 156}]}, "description": "and"}, {"boundingPoly": {"vertices": [{"y": 497, "x": 177}, {"y": 497, "x": 194}, {"y": 507, "x": 194}, {"y": 507, "x": 177}]}, "description": "puts"}, {"boundingPoly": {"vertices": [{"y": 497, "x": 201}, {"y": 497, "x": 214}, {"y": 507, "x": 214}, {"y": 507, "x": 201}]}, "description": "you"}, {"boundingPoly": {"vertices": [{"y": 497, "x": 218}, {"y": 497, "x": 247}, {"y": 507, "x": 247}, {"y": 507, "x": 218}]}, "description": "behind"}, {"boundingPoly": {"vertices": [{"y": 497, "x": 253}, {"y": 497, "x": 264}, {"y": 507, "x": 264}, {"y": 507, "x": 253}]}, "description": "the"}, {"boundingPoly": {"vertices": [{"y": 497, "x": 269}, {"y": 497, "x": 321}, {"y": 507, "x": 321}, {"y": 507, "x": 269}]}, "description": "Government"}, {"boundingPoly": {"vertices": [{"y": 497, "x": 322}, {"y": 497, "x": 324}, {"y": 507, "x": 324}, {"y": 507, "x": 322}]}, "description": "."}, {"boundingPoly": {"vertices": [{"y": 522, "x": 444}, {"y": 522, "x": 480}, {"y": 540, "x": 480}, {"y": 540, "x": 444}]}, "description": "BUY"}, {"boundingPoly": {"vertices": [{"y": 522, "x": 493}, {"y": 522, "x": 539}, {"y": 540, "x": 539}, {"y": 540, "x": 493}]}, "description": "THEM"}, {"boundingPoly": {"vertices": [{"y": 522, "x": 557}, {"y": 522, "x": 595}, {"y": 540, "x": 595}, {"y": 540, "x": 557}]}, "description": "NOW"}, {"boundingPoly": {"vertices": [{"y": 522, "x": 609}, {"y": 522, "x": 613}, {"y": 540, "x": 613}, {"y": 540, "x": 609}]}, "description": "!"}, {"boundingPoly": {"vertices": [{"y": 522, "x": 619}, {"y": 522, "x": 623}, {"y": 540, "x": 623}, {"y": 540, "x": 619}]}, "description": "!"}, {"boundingPoly": {"vertices": [{"y": 522, "x": 626}, {"y": 522, "x": 630}, {"y": 540, "x": 630}, {"y": 540, "x": 626}]}, "description": "!"}, {"boundingPoly": {"vertices": [{"y": 520, "x": 32}, {"y": 519, "x": 117}, {"y": 553, "x": 117}, {"y": 554, "x": 32}]}, "description": "When"}, {"boundingPoly": {"vertices": [{"y": 518, "x": 144}, {"y": 517, "x": 212}, {"y": 552, "x": 212}, {"y": 553, "x": 144}]}, "description": "Shall"}, {"boundingPoly": {"vertices": [{"y": 518, "x": 229}, {"y": 518, "x": 238}, {"y": 552, "x": 238}, {"y": 552, "x": 229}]}, "description": "I"}, {"boundingPoly": {"vertices": [{"y": 517, "x": 250}, {"y": 516, "x": 308}, {"y": 551, "x": 308}, {"y": 552, "x": 250}]}, "description": "Buy"}, {"boundingPoly": {"vertices": [{"y": 517, "x": 329}, {"y": 516, "x": 393}, {"y": 550, "x": 393}, {"y": 551, "x": 329}]}, "description": "Them"}, {"boundingPoly": {"vertices": [{"y": 516, "x": 411}, {"y": 516, "x": 420}, {"y": 550, "x": 420}, {"y": 550, "x": 411}]}, "description": "?"}, {"boundingPoly": {"vertices": [{"y": 515, "x": 445}, {"y": 515, "x": 484}, {"y": 550, "x": 484}, {"y": 550, "x": 445}]}, "description": "BUY"}, {"boundingPoly": {"vertices": [{"y": 515, "x": 495}, {"y": 515, "x": 542}, {"y": 549, "x": 542}, {"y": 549, "x": 495}]}, "description": "THEM"}, {"boundingPoly": {"vertices": [{"y": 514, "x": 561}, {"y": 514, "x": 600}, {"y": 549, "x": 600}, {"y": 549, "x": 561}]}, "description": "NOW"}, {"boundingPoly": {"vertices": [{"y": 514, "x": 611}, {"y": 514, "x": 620}, {"y": 548, "x": 620}, {"y": 548, "x": 611}]}, "description": "!"}, {"boundingPoly": {"vertices": [{"y": 514, "x": 618}, {"y": 514, "x": 627}, {"y": 548, "x": 627}, {"y": 548, "x": 618}]}, "description": "!"}, {"boundingPoly": {"vertices": [{"y": 514, "x": 628}, {"y": 514, "x": 637}, {"y": 548, "x": 637}, {"y": 548, "x": 628}]}, "description": "!"}, {"boundingPoly": {"vertices": [{"y": 560, "x": 36}, {"y": 560, "x": 81}, {"y": 603, "x": 81}, {"y": 603, "x": 36}]}, "description": "Sehemu"}, {"boundingPoly": {"vertices": [{"y": 562, "x": 51}, {"y": 562, "x": 83}, {"y": 573, "x": 83}, {"y": 573, "x": 51}]}, "description": "Because"}, {"boundingPoly": {"vertices": [{"y": 562, "x": 89}, {"y": 562, "x": 102}, {"y": 573, "x": 102}, {"y": 573, "x": 89}]}, "description": "the"}, {"boundingPoly": {"vertices": [{"y": 562, "x": 107}, {"y": 562, "x": 123}, {"y": 573, "x": 123}, {"y": 573, "x": 107}]}, "description": "cost"}, {"boundingPoly": {"vertices": [{"y": 562, "x": 128}, {"y": 562, "x": 165}, {"y": 574, "x": 165}, {"y": 574, "x": 128}]}, "description": "increases"}, {"boundingPoly": {"vertices": [{"y": 563, "x": 171}, {"y": 563, "x": 185}, {"y": 574, "x": 185}, {"y": 574, "x": 171}]}, "description": "one"}, {"boundingPoly": {"vertices": [{"y": 563, "x": 190}, {"y": 563, "x": 206}, {"y": 574, "x": 206}, {"y": 574, "x": 190}]}, "description": "cent"}, {"boundingPoly": {"vertices": [{"y": 563, "x": 212}, {"y": 563, "x": 228}, {"y": 574, "x": 228}, {"y": 574, "x": 212}]}, "description": "cach"}, {"boundingPoly": {"vertices": [{"y": 563, "x": 231}, {"y": 563, "x": 259}, {"y": 574, "x": 259}, {"y": 574, "x": 231}]}, "description": "month"}, {"boundingPoly": {"vertices": [{"y": 563, "x": 266}, {"y": 563, "x": 283}, {"y": 574, "x": 283}, {"y": 574, "x": 266}]}, "description": "after"}, {"boundingPoly": {"vertices": [{"y": 563, "x": 290}, {"y": 563, "x": 302}, {"y": 574, "x": 302}, {"y": 574, "x": 290}]}, "description": "the"}, {"boundingPoly": {"vertices": [{"y": 563, "x": 308}, {"y": 563, "x": 323}, {"y": 574, "x": 323}, {"y": 574, "x": 308}]}, "description": "31st"}, {"boundingPoly": {"vertices": [{"y": 564, "x": 329}, {"y": 564, "x": 337}, {"y": 575, "x": 337}, {"y": 575, "x": 329}]}, "description": "of"}, {"boundingPoly": {"vertices": [{"y": 564, "x": 341}, {"y": 564, "x": 373}, {"y": 575, "x": 373}, {"y": 575, "x": 341}]}, "description": "January"}, {"boundingPoly": {"vertices": [{"y": 564, "x": 376}, {"y": 564, "x": 378}, {"y": 575, "x": 378}, {"y": 575, "x": 376}]}, "description": ","}, {"boundingPoly": {"vertices": [{"y": 564, "x": 383}, {"y": 564, "x": 399}, {"y": 575, "x": 399}, {"y": 575, "x": 383}]}, "description": "1918"}, {"boundingPoly": {"vertices": [{"y": 564, "x": 401}, {"y": 564, "x": 403}, {"y": 575, "x": 403}, {"y": 575, "x": 401}]}, "description": "."}, {"boundingPoly": {"vertices": [{"y": 564, "x": 414}, {"y": 564, "x": 427}, {"y": 575, "x": 427}, {"y": 575, "x": 414}]}, "description": "The"}, {"boundingPoly": {"vertices": [{"y": 564, "x": 431}, {"y": 564, "x": 456}, {"y": 575, "x": 456}, {"y": 575, "x": 431}]}, "description": "sooner"}, {"boundingPoly": {"vertices": [{"y": 564, "x": 461}, {"y": 564, "x": 474}, {"y": 575, "x": 474}, {"y": 575, "x": 461}]}, "description": "you"}, {"boundingPoly": {"vertices": [{"y": 564, "x": 478}, {"y": 564, "x": 494}, {"y": 575, "x": 494}, {"y": 575, "x": 478}]}, "description": "buy"}, {"boundingPoly": {"vertices": [{"y": 564, "x": 498}, {"y": 564, "x": 514}, {"y": 576, "x": 514}, {"y": 576, "x": 498}]}, "description": "them"}, {"boundingPoly": {"vertices": [{"y": 565, "x": 524}, {"y": 565, "x": 536}, {"y": 576, "x": 536}, {"y": 576, "x": 524}]}, "description": "the"}, {"boundingPoly": {"vertices": [{"y": 565, "x": 539}, {"y": 565, "x": 553}, {"y": 576, "x": 553}, {"y": 576, "x": 539}]}, "description": "less"}, {"boundingPoly": {"vertices": [{"y": 565, "x": 558}, {"y": 565, "x": 576}, {"y": 576, "x": 576}, {"y": 576, "x": 558}]}, "description": "they"}, {"boundingPoly": {"vertices": [{"y": 565, "x": 581}, {"y": 565, "x": 595}, {"y": 576, "x": 595}, {"y": 576, "x": 581}]}, "description": "cost"}, {"boundingPoly": {"vertices": [{"y": 565, "x": 597}, {"y": 565, "x": 599}, {"y": 576, "x": 599}, {"y": 576, "x": 597}]}, "description": "."}, {"boundingPoly": {"vertices": [{"y": 574, "x": 53}, {"y": 574, "x": 66}, {"y": 585, "x": 66}, {"y": 585, "x": 53}]}, "description": "The"}, {"boundingPoly": {"vertices": [{"y": 574, "x": 70}, {"y": 574, "x": 91}, {"y": 585, "x": 91}, {"y": 585, "x": 70}]}, "description": "price"}, {"boundingPoly": {"vertices": [{"y": 574, "x": 96}, {"y": 574, "x": 103}, {"y": 585, "x": 103}, {"y": 585, "x": 96}]}, "description": "of"}, {"boundingPoly": {"vertices": [{"y": 574, "x": 108}, {"y": 574, "x": 127}, {"y": 585, "x": 127}, {"y": 585, "x": 108}]}, "description": "War"}, {"boundingPoly": {"vertices": [{"y": 574, "x": 132}, {"y": 574, "x": 166}, {"y": 585, "x": 166}, {"y": 585, "x": 132}]}, "description": "Savings"}, {"boundingPoly": {"vertices": [{"y": 574, "x": 170}, {"y": 574, "x": 201}, {"y": 586, "x": 201}, {"y": 586, "x": 170}]}, "description": "Stamps"}, {"boundingPoly": {"vertices": [{"y": 575, "x": 207}, {"y": 575, "x": 213}, {"y": 586, "x": 213}, {"y": 586, "x": 207}]}, "description": "is"}, {"boundingPoly": {"vertices": [{"y": 575, "x": 218}, {"y": 575, "x": 228}, {"y": 586, "x": 228}, {"y": 586, "x": 218}]}, "description": "54"}, {"boundingPoly": {"vertices": [{"y": 575, "x": 229}, {"y": 575, "x": 231}, {"y": 586, "x": 231}, {"y": 586, "x": 229}]}, "description": "."}, {"boundingPoly": {"vertices": [{"y": 575, "x": 233}, {"y": 575, "x": 239}, {"y": 586, "x": 239}, {"y": 586, "x": 233}]}, "description": "12"}, {"boundingPoly": {"vertices": [{"y": 575, "x": 245}, {"y": 575, "x": 251}, {"y": 586, "x": 251}, {"y": 586, "x": 245}]}, "description": "In"}, {"boundingPoly": {"vertices": [{"y": 575, "x": 260}, {"y": 575, "x": 293}, {"y": 586, "x": 293}, {"y": 586, "x": 260}]}, "description": "January"}, {"boundingPoly": {"vertices": [{"y": 575, "x": 293}, {"y": 575, "x": 295}, {"y": 586, "x": 295}, {"y": 586, "x": 293}]}, "description": ","}, {"boundingPoly": {"vertices": [{"y": 575, "x": 300}, {"y": 575, "x": 316}, {"y": 586, "x": 316}, {"y": 586, "x": 300}]}, "description": "1918"}, {"boundingPoly": {"vertices": [{"y": 575, "x": 319}, {"y": 575, "x": 321}, {"y": 586, "x": 321}, {"y": 586, "x": 319}]}, "description": ","}, {"boundingPoly": {"vertices": [{"y": 575, "x": 324}, {"y": 575, "x": 338}, {"y": 586, "x": 338}, {"y": 586, "x": 324}]}, "description": "and"}, {"boundingPoly": {"vertices": [{"y": 575, "x": 346}, {"y": 575, "x": 383}, {"y": 586, "x": 383}, {"y": 586, "x": 346}]}, "description": "increases"}, {"boundingPoly": {"vertices": [{"y": 575, "x": 387}, {"y": 575, "x": 401}, {"y": 586, "x": 401}, {"y": 586, "x": 387}]}, "description": "one"}, {"boundingPoly": {"vertices": [{"y": 575, "x": 406}, {"y": 575, "x": 424}, {"y": 586, "x": 424}, {"y": 586, "x": 406}]}, "description": "cent"}, {"boundingPoly": {"vertices": [{"y": 575, "x": 429}, {"y": 575, "x": 445}, {"y": 586, "x": 445}, {"y": 586, "x": 429}]}, "description": "each"}, {"boundingPoly": {"vertices": [{"y": 575, "x": 450}, {"y": 575, "x": 477}, {"y": 586, "x": 477}, {"y": 586, "x": 450}]}, "description": "month"}, {"boundingPoly": {"vertices": [{"y": 576, "x": 482}, {"y": 576, "x": 502}, {"y": 587, "x": 502}, {"y": 587, "x": 482}]}, "description": "until"}, {"boundingPoly": {"vertices": [{"y": 576, "x": 508}, {"y": 576, "x": 511}, {"y": 587, "x": 511}, {"y": 587, "x": 508}]}, "description": "in"}, {"boundingPoly": {"vertices": [{"y": 576, "x": 518}, {"y": 576, "x": 559}, {"y": 587, "x": 559}, {"y": 587, "x": 518}]}, "description": "December"}, {"boundingPoly": {"vertices": [{"y": 576, "x": 567}, {"y": 576, "x": 583}, {"y": 587, "x": 583}, {"y": 587, "x": 567}]}, "description": "1918"}, {"boundingPoly": {"vertices": [{"y": 576, "x": 584}, {"y": 576, "x": 586}, {"y": 587, "x": 586}, {"y": 587, "x": 584}]}, "description": ","}, {"boundingPoly": {"vertices": [{"y": 576, "x": 590}, {"y": 576, "x": 612}, {"y": 587, "x": 612}, {"y": 587, "x": 590}]}, "description": "when"}, {"boundingPoly": {"vertices": [{"y": 576, "x": 617}, {"y": 576, "x": 630}, {"y": 587, "x": 630}, {"y": 587, "x": 617}]}, "description": "the"}, {"boundingPoly": {"vertices": [{"y": 586, "x": 69}, {"y": 586, "x": 87}, {"y": 597, "x": 87}, {"y": 597, "x": 69}]}, "description": "price"}, {"boundingPoly": {"vertices": [{"y": 586, "x": 92}, {"y": 586, "x": 98}, {"y": 597, "x": 98}, {"y": 597, "x": 92}]}, "description": "is"}, {"boundingPoly": {"vertices": [{"y": 586, "x": 102}, {"y": 586, "x": 104}, {"y": 597, "x": 104}, {"y": 597, "x": 102}]}, "description": "$"}, {"boundingPoly": {"vertices": [{"y": 586, "x": 108}, {"y": 586, "x": 110}, {"y": 597, "x": 110}, {"y": 597, "x": 108}]}, "description": "4"}, {"boundingPoly": {"vertices": [{"y": 586, "x": 111}, {"y": 586, "x": 113}, {"y": 597, "x": 113}, {"y": 597, "x": 111}]}, "description": "."}, {"boundingPoly": {"vertices": [{"y": 586, "x": 115}, {"y": 586, "x": 123}, {"y": 597, "x": 123}, {"y": 597, "x": 115}]}, "description": "23"}, {"boundingPoly": {"vertices": [{"y": 586, "x": 125}, {"y": 586, "x": 127}, {"y": 597, "x": 127}, {"y": 597, "x": 125}]}, "description": "."}, {"boundingPoly": {"vertices": [{"y": 597, "x": 51}, {"y": 597, "x": 66}, {"y": 608, "x": 66}, {"y": 608, "x": 51}]}, "description": "The"}, {"boundingPoly": {"vertices": [{"y": 597, "x": 70}, {"y": 597, "x": 87}, {"y": 608, "x": 87}, {"y": 608, "x": 70}]}, "description": "cost"}, {"boundingPoly": {"vertices": [{"y": 597, "x": 92}, {"y": 597, "x": 97}, {"y": 608, "x": 97}, {"y": 608, "x": 92}]}, "description": "is"}, {"boundingPoly": {"vertices": [{"y": 597, "x": 104}, {"y": 597, "x": 111}, {"y": 608, "x": 111}, {"y": 608, "x": 104}]}, "description": "as"}, {"boundingPoly": {"vertices": [{"y": 597, "x": 117}, {"y": 597, "x": 147}, {"y": 608, "x": 147}, {"y": 608, "x": 117}]}, "description": "follows"}, {"boundingPoly": {"vertices": [{"y": 597, "x": 148}, {"y": 597, "x": 150}, {"y": 608, "x": 150}, {"y": 608, "x": 148}]}, "description": ":"}, {"boundingPoly": {"vertices": [{"y": 615, "x": 123}, {"y": 615, "x": 138}, {"y": 630, "x": 138}, {"y": 630, "x": 123}]}, "description": "Jan"}, {"boundingPoly": {"vertices": [{"y": 615, "x": 141}, {"y": 615, "x": 144}, {"y": 630, "x": 144}, {"y": 630, "x": 141}]}, "description": "."}, {"boundingPoly": {"vertices": [{"y": 615, "x": 153}, {"y": 615, "x": 156}, {"y": 630, "x": 156}, {"y": 630, "x": 153}]}, "description": "."}, {"boundingPoly": {"vertices": [{"y": 615, "x": 163}, {"y": 615, "x": 166}, {"y": 630, "x": 166}, {"y": 630, "x": 163}]}, "description": "."}, {"boundingPoly": {"vertices": [{"y": 615, "x": 171}, {"y": 615, "x": 174}, {"y": 630, "x": 174}, {"y": 630, "x": 171}]}, "description": "."}, {"boundingPoly": {"vertices": [{"y": 615, "x": 181}, {"y": 615, "x": 184}, {"y": 630, "x": 184}, {"y": 630, "x": 181}]}, "description": "$"}, {"boundingPoly": {"vertices": [{"y": 615, "x": 187}, {"y": 615, "x": 190}, {"y": 630, "x": 190}, {"y": 630, "x": 187}]}, "description": "4"}, {"boundingPoly": {"vertices": [{"y": 615, "x": 192}, {"y": 615, "x": 195}, {"y": 630, "x": 195}, {"y": 630, "x": 192}]}, "description": "."}, {"boundingPoly": {"vertices": [{"y": 615, "x": 196}, {"y": 615, "x": 206}, {"y": 630, "x": 206}, {"y": 630, "x": 196}]}, "description": "12"}, {"boundingPoly": {"vertices": [{"y": 615, "x": 232}, {"y": 615, "x": 252}, {"y": 630, "x": 252}, {"y": 630, "x": 232}]}, "description": "Apr"}, {"boundingPoly": {"vertices": [{"y": 615, "x": 253}, {"y": 615, "x": 256}, {"y": 630, "x": 256}, {"y": 630, "x": 253}]}, "description": "."}, {"boundingPoly": {"vertices": [{"y": 615, "x": 264}, {"y": 615, "x": 267}, {"y": 630, "x": 267}, {"y": 630, "x": 264}]}, "description": "."}, {"boundingPoly": {"vertices": [{"y": 615, "x": 273}, {"y": 615, "x": 276}, {"y": 630, "x": 276}, {"y": 630, "x": 273}]}, "description": "."}, {"boundingPoly": {"vertices": [{"y": 615, "x": 281}, {"y": 615, "x": 284}, {"y": 630, "x": 284}, {"y": 630, "x": 281}]}, "description": "."}, {"boundingPoly": {"vertices": [{"y": 615, "x": 291}, {"y": 615, "x": 294}, {"y": 630, "x": 294}, {"y": 630, "x": 291}]}, "description": "$"}, {"boundingPoly": {"vertices": [{"y": 615, "x": 297}, {"y": 615, "x": 300}, {"y": 630, "x": 300}, {"y": 630, "x": 297}]}, "description": "4"}, {"boundingPoly": {"vertices": [{"y": 615, "x": 302}, {"y": 615, "x": 305}, {"y": 630, "x": 305}, {"y": 630, "x": 302}]}, "description": "."}, {"boundingPoly": {"vertices": [{"y": 615, "x": 306}, {"y": 615, "x": 317}, {"y": 630, "x": 317}, {"y": 630, "x": 306}]}, "description": "15"}, {"boundingPoly": {"vertices": [{"y": 615, "x": 343}, {"y": 615, "x": 364}, {"y": 630, "x": 364}, {"y": 630, "x": 343}]}, "description": "July"}, {"boundingPoly": {"vertices": [{"y": 615, "x": 374}, {"y": 615, "x": 377}, {"y": 630, "x": 377}, {"y": 630, "x": 374}]}, "description": "."}, {"boundingPoly": {"vertices": [{"y": 615, "x": 384}, {"y": 615, "x": 387}, {"y": 630, "x": 387}, {"y": 630, "x": 384}]}, "description": "."}, {"boundingPoly": {"vertices": [{"y": 615, "x": 393}, {"y": 615, "x": 396}, {"y": 630, "x": 396}, {"y": 630, "x": 393}]}, "description": "."}, {"boundingPoly": {"vertices": [{"y": 615, "x": 401}, {"y": 615, "x": 404}, {"y": 630, "x": 404}, {"y": 630, "x": 401}]}, "description": "$"}, {"boundingPoly": {"vertices": [{"y": 615, "x": 408}, {"y": 615, "x": 411}, {"y": 630, "x": 411}, {"y": 630, "x": 408}]}, "description": "4"}, {"boundingPoly": {"vertices": [{"y": 615, "x": 413}, {"y": 615, "x": 416}, {"y": 630, "x": 416}, {"y": 630, "x": 413}]}, "description": "."}, {"boundingPoly": {"vertices": [{"y": 615, "x": 419}, {"y": 615, "x": 427}, {"y": 630, "x": 427}, {"y": 630, "x": 419}]}, "description": "18"}, {"boundingPoly": {"vertices": [{"y": 615, "x": 453}, {"y": 615, "x": 470}, {"y": 630, "x": 470}, {"y": 630, "x": 453}]}, "description": "Oct"}, {"boundingPoly": {"vertices": [{"y": 615, "x": 472}, {"y": 615, "x": 475}, {"y": 630, "x": 475}, {"y": 630, "x": 472}]}, "description": "."}, {"boundingPoly": {"vertices": [{"y": 615, "x": 486}, {"y": 615, "x": 489}, {"y": 630, "x": 489}, {"y": 630, "x": 486}]}, "description": "."}, {"boundingPoly": {"vertices": [{"y": 615, "x": 494}, {"y": 615, "x": 497}, {"y": 630, "x": 497}, {"y": 630, "x": 494}]}, "description": "."}, {"boundingPoly": {"vertices": [{"y": 615, "x": 504}, {"y": 615, "x": 507}, {"y": 630, "x": 507}, {"y": 630, "x": 504}]}, "description": "."}, {"boundingPoly": {"vertices": [{"y": 615, "x": 513}, {"y": 615, "x": 516}, {"y": 630, "x": 516}, {"y": 630, "x": 513}]}, "description": "$"}, {"boundingPoly": {"vertices": [{"y": 615, "x": 520}, {"y": 615, "x": 523}, {"y": 630, "x": 523}, {"y": 630, "x": 520}]}, "description": "4"}, {"boundingPoly": {"vertices": [{"y": 615, "x": 525}, {"y": 615, "x": 528}, {"y": 630, "x": 528}, {"y": 630, "x": 525}]}, "description": "."}, {"boundingPoly": {"vertices": [{"y": 615, "x": 529}, {"y": 615, "x": 540}, {"y": 630, "x": 540}, {"y": 630, "x": 529}]}, "description": "21"}, {"boundingPoly": {"vertices": [{"y": 630, "x": 121}, {"y": 630, "x": 137}, {"y": 642, "x": 137}, {"y": 642, "x": 121}]}, "description": "Feb"}, {"boundingPoly": {"vertices": [{"y": 630, "x": 141}, {"y": 630, "x": 143}, {"y": 642, "x": 143}, {"y": 642, "x": 141}]}, "description": "."}, {"boundingPoly": {"vertices": [{"y": 630, "x": 154}, {"y": 630, "x": 156}, {"y": 642, "x": 156}, {"y": 642, "x": 154}]}, "description": "."}, {"boundingPoly": {"vertices": [{"y": 630, "x": 163}, {"y": 630, "x": 165}, {"y": 642, "x": 165}, {"y": 642, "x": 163}]}, "description": "."}, {"boundingPoly": {"vertices": [{"y": 630, "x": 171}, {"y": 630, "x": 173}, {"y": 642, "x": 173}, {"y": 642, "x": 171}]}, "description": "."}, {"boundingPoly": {"vertices": [{"y": 630, "x": 187}, {"y": 630, "x": 189}, {"y": 642, "x": 189}, {"y": 642, "x": 187}]}, "description": "4"}, {"boundingPoly": {"vertices": [{"y": 630, "x": 192}, {"y": 630, "x": 194}, {"y": 642, "x": 194}, {"y": 642, "x": 192}]}, "description": "."}, {"boundingPoly": {"vertices": [{"y": 630, "x": 196}, {"y": 630, "x": 205}, {"y": 642, "x": 205}, {"y": 642, "x": 196}]}, "description": "13"}, {"boundingPoly": {"vertices": [{"y": 630, "x": 232}, {"y": 630, "x": 254}, {"y": 642, "x": 254}, {"y": 642, "x": 232}]}, "description": "May"}, {"boundingPoly": {"vertices": [{"y": 630, "x": 265}, {"y": 630, "x": 267}, {"y": 642, "x": 267}, {"y": 642, "x": 265}]}, "description": "."}, {"boundingPoly": {"vertices": [{"y": 630, "x": 273}, {"y": 630, "x": 275}, {"y": 642, "x": 275}, {"y": 642, "x": 273}]}, "description": "."}, {"boundingPoly": {"vertices": [{"y": 630, "x": 282}, {"y": 630, "x": 284}, {"y": 642, "x": 284}, {"y": 642, "x": 282}]}, "description": "."}, {"boundingPoly": {"vertices": [{"y": 630, "x": 297}, {"y": 630, "x": 299}, {"y": 642, "x": 299}, {"y": 642, "x": 297}]}, "description": "4"}, {"boundingPoly": {"vertices": [{"y": 630, "x": 302}, {"y": 630, "x": 304}, {"y": 642, "x": 304}, {"y": 642, "x": 302}]}, "description": ":"}, {"boundingPoly": {"vertices": [{"y": 630, "x": 307}, {"y": 630, "x": 315}, {"y": 642, "x": 315}, {"y": 642, "x": 307}]}, "description": "16"}, {"boundingPoly": {"vertices": [{"y": 630, "x": 342}, {"y": 630, "x": 364}, {"y": 642, "x": 364}, {"y": 642, "x": 342}]}, "description": "Aug"}, {"boundingPoly": {"vertices": [{"y": 630, "x": 365}, {"y": 630, "x": 367}, {"y": 642, "x": 367}, {"y": 642, "x": 365}]}, "description": "."}, {"boundingPoly": {"vertices": [{"y": 630, "x": 375}, {"y": 630, "x": 377}, {"y": 642, "x": 377}, {"y": 642, "x": 375}]}, "description": "."}, {"boundingPoly": {"vertices": [{"y": 630, "x": 384}, {"y": 630, "x": 386}, {"y": 642, "x": 386}, {"y": 642, "x": 384}]}, "description": "."}, {"boundingPoly": {"vertices": [{"y": 630, "x": 392}, {"y": 630, "x": 394}, {"y": 642, "x": 394}, {"y": 642, "x": 392}]}, "description": "."}, {"boundingPoly": {"vertices": [{"y": 630, "x": 408}, {"y": 630, "x": 410}, {"y": 642, "x": 410}, {"y": 642, "x": 408}]}, "description": "4"}, {"boundingPoly": {"vertices": [{"y": 630, "x": 413}, {"y": 630, "x": 415}, {"y": 642, "x": 415}, {"y": 642, "x": 413}]}, "description": "."}, {"boundingPoly": {"vertices": [{"y": 630, "x": 416}, {"y": 630, "x": 428}, {"y": 642, "x": 428}, {"y": 642, "x": 416}]}, "description": "19"}, {"boundingPoly": {"vertices": [{"y": 630, "x": 453}, {"y": 630, "x": 472}, {"y": 642, "x": 472}, {"y": 642, "x": 453}]}, "description": "Nov"}, {"boundingPoly": {"vertices": [{"y": 630, "x": 474}, {"y": 630, "x": 476}, {"y": 642, "x": 476}, {"y": 642, "x": 474}]}, "description": "."}, {"boundingPoly": {"vertices": [{"y": 630, "x": 486}, {"y": 630, "x": 488}, {"y": 642, "x": 488}, {"y": 642, "x": 486}]}, "description": "."}, {"boundingPoly": {"vertices": [{"y": 630, "x": 495}, {"y": 630, "x": 497}, {"y": 642, "x": 497}, {"y": 642, "x": 495}]}, "description": "."}, {"boundingPoly": {"vertices": [{"y": 630, "x": 504}, {"y": 630, "x": 506}, {"y": 642, "x": 506}, {"y": 642, "x": 504}]}, "description": "."}, {"boundingPoly": {"vertices": [{"y": 630, "x": 520}, {"y": 630, "x": 522}, {"y": 642, "x": 522}, {"y": 642, "x": 520}]}, "description": "4"}, {"boundingPoly": {"vertices": [{"y": 630, "x": 525}, {"y": 630, "x": 527}, {"y": 642, "x": 527}, {"y": 642, "x": 525}]}, "description": "."}, {"boundingPoly": {"vertices": [{"y": 630, "x": 527}, {"y": 630, "x": 540}, {"y": 642, "x": 540}, {"y": 642, "x": 527}]}, "description": "22"}, {"boundingPoly": {"vertices": [{"y": 643, "x": 120}, {"y": 643, "x": 143}, {"y": 656, "x": 143}, {"y": 656, "x": 120}]}, "description": "Mar"}, {"boundingPoly": {"vertices": [{"y": 643, "x": 143}, {"y": 643, "x": 146}, {"y": 656, "x": 146}, {"y": 656, "x": 143}]}, "description": "."}, {"boundingPoly": {"vertices": [{"y": 643, "x": 155}, {"y": 643, "x": 158}, {"y": 656, "x": 158}, {"y": 656, "x": 155}]}, "description": "."}, {"boundingPoly": {"vertices": [{"y": 643, "x": 163}, {"y": 643, "x": 166}, {"y": 656, "x": 166}, {"y": 656, "x": 163}]}, "description": "."}, {"boundingPoly": {"vertices": [{"y": 643, "x": 171}, {"y": 643, "x": 174}, {"y": 656, "x": 174}, {"y": 656, "x": 171}]}, "description": "."}, {"boundingPoly": {"vertices": [{"y": 643, "x": 187}, {"y": 643, "x": 190}, {"y": 656, "x": 190}, {"y": 656, "x": 187}]}, "description": "4"}, {"boundingPoly": {"vertices": [{"y": 643, "x": 192}, {"y": 643, "x": 195}, {"y": 656, "x": 195}, {"y": 656, "x": 192}]}, "description": "."}, {"boundingPoly": {"vertices": [{"y": 643, "x": 198}, {"y": 643, "x": 205}, {"y": 656, "x": 205}, {"y": 656, "x": 198}]}, "description": "14"}, {"boundingPoly": {"vertices": [{"y": 644, "x": 232}, {"y": 644, "x": 258}, {"y": 657, "x": 258}, {"y": 657, "x": 232}]}, "description": "June"}, {"boundingPoly": {"vertices": [{"y": 644, "x": 265}, {"y": 644, "x": 268}, {"y": 657, "x": 268}, {"y": 657, "x": 265}]}, "description": "."}, {"boundingPoly": {"vertices": [{"y": 644, "x": 274}, {"y": 644, "x": 277}, {"y": 657, "x": 277}, {"y": 657, "x": 274}]}, "description": "."}, {"boundingPoly": {"vertices": [{"y": 644, "x": 282}, {"y": 644, "x": 285}, {"y": 657, "x": 285}, {"y": 657, "x": 282}]}, "description": "."}, {"boundingPoly": {"vertices": [{"y": 644, "x": 297}, {"y": 644, "x": 300}, {"y": 657, "x": 300}, {"y": 657, "x": 297}]}, "description": "4"}, {"boundingPoly": {"vertices": [{"y": 644, "x": 303}, {"y": 644, "x": 306}, {"y": 657, "x": 306}, {"y": 657, "x": 303}]}, "description": "."}, {"boundingPoly": {"vertices": [{"y": 644, "x": 307}, {"y": 644, "x": 316}, {"y": 657, "x": 316}, {"y": 657, "x": 307}]}, "description": "17"}, {"boundingPoly": {"vertices": [{"y": 644, "x": 343}, {"y": 644, "x": 367}, {"y": 657, "x": 367}, {"y": 657, "x": 343}]}, "description": "Sept"}, {"boundingPoly": {"vertices": [{"y": 644, "x": 367}, {"y": 644, "x": 370}, {"y": 657, "x": 370}, {"y": 657, "x": 367}]}, "description": "."}, {"boundingPoly": {"vertices": [{"y": 644, "x": 376}, {"y": 644, "x": 379}, {"y": 657, "x": 379}, {"y": 657, "x": 376}]}, "description": "."}, {"boundingPoly": {"vertices": [{"y": 644, "x": 384}, {"y": 644, "x": 387}, {"y": 657, "x": 387}, {"y": 657, "x": 384}]}, "description": "."}, {"boundingPoly": {"vertices": [{"y": 644, "x": 393}, {"y": 644, "x": 396}, {"y": 657, "x": 396}, {"y": 657, "x": 393}]}, "description": "."}, {"boundingPoly": {"vertices": [{"y": 644, "x": 408}, {"y": 644, "x": 411}, {"y": 657, "x": 411}, {"y": 657, "x": 408}]}, "description": "4"}, {"boundingPoly": {"vertices": [{"y": 644, "x": 414}, {"y": 644, "x": 417}, {"y": 657, "x": 417}, {"y": 657, "x": 414}]}, "description": "."}, {"boundingPoly": {"vertices": [{"y": 644, "x": 417}, {"y": 644, "x": 429}, {"y": 657, "x": 429}, {"y": 657, "x": 417}]}, "description": "20"}, {"boundingPoly": {"vertices": [{"y": 645, "x": 455}, {"y": 645, "x": 472}, {"y": 658, "x": 472}, {"y": 658, "x": 455}]}, "description": "Dec"}, {"boundingPoly": {"vertices": [{"y": 645, "x": 474}, {"y": 645, "x": 477}, {"y": 658, "x": 477}, {"y": 658, "x": 474}]}, "description": "."}, {"boundingPoly": {"vertices": [{"y": 645, "x": 486}, {"y": 645, "x": 489}, {"y": 658, "x": 489}, {"y": 658, "x": 486}]}, "description": "."}, {"boundingPoly": {"vertices": [{"y": 645, "x": 495}, {"y": 645, "x": 498}, {"y": 658, "x": 498}, {"y": 658, "x": 495}]}, "description": "."}, {"boundingPoly": {"vertices": [{"y": 645, "x": 503}, {"y": 645, "x": 506}, {"y": 658, "x": 506}, {"y": 658, "x": 503}]}, "description": "."}, {"boundingPoly": {"vertices": [{"y": 645, "x": 519}, {"y": 645, "x": 522}, {"y": 658, "x": 522}, {"y": 658, "x": 519}]}, "description": "4"}, {"boundingPoly": {"vertices": [{"y": 645, "x": 524}, {"y": 645, "x": 527}, {"y": 658, "x": 527}, {"y": 658, "x": 524}]}, "description": "."}, {"boundingPoly": {"vertices": [{"y": 645, "x": 527}, {"y": 645, "x": 539}, {"y": 658, "x": 539}, {"y": 658, "x": 527}]}, "description": "23"}, {"boundingPoly": {"vertices": [{"y": 663, "x": 49}, {"y": 663, "x": 61}, {"y": 675, "x": 61}, {"y": 675, "x": 49}]}, "description": "No"}, {"boundingPoly": {"vertices": [{"y": 663, "x": 67}, {"y": 663, "x": 121}, {"y": 675, "x": 121}, {"y": 675, "x": 67}]}, "description": "commissions"}, {"boundingPoly": {"vertices": [{"y": 663, "x": 124}, {"y": 663, "x": 137}, {"y": 675, "x": 137}, {"y": 675, "x": 124}]}, "description": "are"}, {"boundingPoly": {"vertices": [{"y": 663, "x": 144}, {"y": 663, "x": 173}, {"y": 675, "x": 173}, {"y": 675, "x": 144}]}, "description": "charged"}, {"boundingPoly": {"vertices": [{"y": 663, "x": 181}, {"y": 663, "x": 186}, {"y": 675, "x": 186}, {"y": 675, "x": 181}]}, "description": "to"}, {"boundingPoly": {"vertices": [{"y": 663, "x": 192}, {"y": 663, "x": 206}, {"y": 675, "x": 206}, {"y": 675, "x": 192}]}, "description": "you"}, {"boundingPoly": {"vertices": [{"y": 663, "x": 208}, {"y": 663, "x": 210}, {"y": 675, "x": 210}, {"y": 675, "x": 208}]}, "description": ","}, {"boundingPoly": {"vertices": [{"y": 663, "x": 213}, {"y": 663, "x": 221}, {"y": 675, "x": 221}, {"y": 675, "x": 213}]}, "description": "or"}, {"boundingPoly": {"vertices": [{"y": 663, "x": 226}, {"y": 663, "x": 242}, {"y": 675, "x": 242}, {"y": 675, "x": 226}]}, "description": "paid"}, {"boundingPoly": {"vertices": [{"y": 663, "x": 249}, {"y": 663, "x": 255}, {"y": 675, "x": 255}, {"y": 675, "x": 249}]}, "description": "to"}, {"boundingPoly": {"vertices": [{"y": 663, "x": 261}, {"y": 663, "x": 290}, {"y": 675, "x": 290}, {"y": 675, "x": 261}]}, "description": "anyone"}, {"boundingPoly": {"vertices": [{"y": 663, "x": 292}, {"y": 663, "x": 294}, {"y": 675, "x": 294}, {"y": 675, "x": 292}]}, "description": "."}, {"boundingPoly": {"vertices": [{"y": 674, "x": 49}, {"y": 674, "x": 65}, {"y": 686, "x": 65}, {"y": 686, "x": 49}]}, "description": "Our"}, {"boundingPoly": {"vertices": [{"y": 674, "x": 72}, {"y": 674, "x": 102}, {"y": 686, "x": 102}, {"y": 686, "x": 72}]}, "description": "soldiers"}, {"boundingPoly": {"vertices": [{"y": 674, "x": 107}, {"y": 674, "x": 121}, {"y": 686, "x": 121}, {"y": 686, "x": 107}]}, "description": "and"}, {"boundingPoly": {"vertices": [{"y": 674, "x": 128}, {"y": 674, "x": 155}, {"y": 686, "x": 155}, {"y": 686, "x": 128}]}, "description": "sailors"}, {"boundingPoly": {"vertices": [{"y": 674, "x": 158}, {"y": 674, "x": 177}, {"y": 686, "x": 177}, {"y": 686, "x": 158}]}, "description": "may"}, {"boundingPoly": {"vertices": [{"y": 674, "x": 181}, {"y": 674, "x": 198}, {"y": 686, "x": 198}, {"y": 686, "x": 181}]}, "description": "give"}, {"boundingPoly": {"vertices": [{"y": 674, "x": 205}, {"y": 674, "x": 224}, {"y": 686, "x": 224}, {"y": 686, "x": 205}]}, "description": "their"}, {"boundingPoly": {"vertices": [{"y": 674, "x": 229}, {"y": 674, "x": 247}, {"y": 686, "x": 247}, {"y": 686, "x": 229}]}, "description": "lives"}, {"boundingPoly": {"vertices": [{"y": 674, "x": 249}, {"y": 674, "x": 251}, {"y": 686, "x": 251}, {"y": 686, "x": 249}]}, "description": ":"}, {"boundingPoly": {"vertices": [{"y": 674, "x": 260}, {"y": 674, "x": 272}, {"y": 686, "x": 272}, {"y": 686, "x": 260}]}, "description": "you"}, {"boundingPoly": {"vertices": [{"y": 674, "x": 278}, {"y": 674, "x": 291}, {"y": 686, "x": 291}, {"y": 686, "x": 278}]}, "description": "are"}, {"boundingPoly": {"vertices": [{"y": 674, "x": 296}, {"y": 674, "x": 319}, {"y": 686, "x": 319}, {"y": 686, "x": 296}]}, "description": "asked"}, {"boundingPoly": {"vertices": [{"y": 674, "x": 324}, {"y": 674, "x": 340}, {"y": 686, "x": 340}, {"y": 686, "x": 324}]}, "description": "only"}, {"boundingPoly": {"vertices": [{"y": 674, "x": 346}, {"y": 674, "x": 352}, {"y": 686, "x": 352}, {"y": 686, "x": 346}]}, "description": "to"}, {"boundingPoly": {"vertices": [{"y": 674, "x": 359}, {"y": 674, "x": 376}, {"y": 686, "x": 376}, {"y": 686, "x": 359}]}, "description": "lend"}, {"boundingPoly": {"vertices": [{"y": 674, "x": 380}, {"y": 674, "x": 399}, {"y": 686, "x": 399}, {"y": 686, "x": 380}]}, "description": "your"}, {"boundingPoly": {"vertices": [{"y": 674, "x": 403}, {"y": 674, "x": 430}, {"y": 686, "x": 430}, {"y": 686, "x": 403}]}, "description": "money"}, {"boundingPoly": {"vertices": [{"y": 674, "x": 432}, {"y": 674, "x": 434}, {"y": 686, "x": 434}, {"y": 686, "x": 432}]}, "description": ","}, {"boundingPoly": {"vertices": [{"y": 697, "x": 29}, {"y": 697, "x": 135}, {"y": 735, "x": 135}, {"y": 735, "x": 29}]}, "description": "Where"}, {"boundingPoly": {"vertices": [{"y": 697, "x": 150}, {"y": 697, "x": 200}, {"y": 735, "x": 200}, {"y": 735, "x": 150}]}, "description": "Can"}, {"boundingPoly": {"vertices": [{"y": 697, "x": 218}, {"y": 697, "x": 228}, {"y": 735, "x": 228}, {"y": 735, "x": 218}]}, "description": "I"}, {"boundingPoly": {"vertices": [{"y": 697, "x": 237}, {"y": 697, "x": 297}, {"y": 735, "x": 297}, {"y": 735, "x": 237}]}, "description": "Buy"}, {"boundingPoly": {"vertices": [{"y": 697, "x": 318}, {"y": 697, "x": 382}, {"y": 735, "x": 382}, {"y": 735, "x": 318}]}, "description": "Them"}, {"boundingPoly": {"vertices": [{"y": 697, "x": 397}, {"y": 697, "x": 407}, {"y": 735, "x": 407}, {"y": 735, "x": 397}]}, "description": "?"}, {"boundingPoly": {"vertices": [{"y": 697, "x": 429}, {"y": 697, "x": 629}, {"y": 735, "x": 629}, {"y": 735, "x": 429}]}, "description": "ARUSSTCOMPAESEBANKS"}, {"boundingPoly": {"vertices": [{"y": 734, "x": 141}, {"y": 734, "x": 187}, {"y": 757, "x": 187}, {"y": 757, "x": 141}]}, "description": "MANY"}, {"boundingPoly": {"vertices": [{"y": 734, "x": 197}, {"y": 734, "x": 246}, {"y": 757, "x": 246}, {"y": 757, "x": 197}]}, "description": "OTHER"}, {"boundingPoly": {"vertices": [{"y": 734, "x": 260}, {"y": 734, "x": 354}, {"y": 757, "x": 354}, {"y": 757, "x": 260}]}, "description": "AUTHORIZED"}, {"boundingPoly": {"vertices": [{"y": 734, "x": 369}, {"y": 734, "x": 432}, {"y": 757, "x": 432}, {"y": 757, "x": 369}]}, "description": "SELLING"}, {"boundingPoly": {"vertices": [{"y": 734, "x": 443}, {"y": 734, "x": 517}, {"y": 757, "x": 517}, {"y": 757, "x": 443}]}, "description": "AGENCIES"}, {"boundingPoly": {"vertices": [{"y": 698, "x": 426}, {"y": 698, "x": 449}, {"y": 715, "x": 449}, {"y": 715, "x": 426}]}, "description": "AT"}, {"boundingPoly": {"vertices": [{"y": 698, "x": 454}, {"y": 698, "x": 493}, {"y": 716, "x": 493}, {"y": 716, "x": 454}]}, "description": "POST"}, {"boundingPoly": {"vertices": [{"y": 699, "x": 499}, {"y": 700, "x": 560}, {"y": 717, "x": 560}, {"y": 716, "x": 499}]}, "description": "OFFICES"}, {"boundingPoly": {"vertices": [{"y": 699, "x": 562}, {"y": 699, "x": 566}, {"y": 716, "x": 566}, {"y": 716, "x": 562}]}, "description": ","}, {"boundingPoly": {"vertices": [{"y": 700, "x": 573}, {"y": 700, "x": 627}, {"y": 717, "x": 627}, {"y": 717, "x": 573}]}, "description": "BANKS"}, {"boundingPoly": {"vertices": [{"y": 700, "x": 627}, {"y": 700, "x": 631}, {"y": 717, "x": 631}, {"y": 717, "x": 627}]}, "description": ","}, {"boundingPoly": {"vertices": [{"y": 715, "x": 400}, {"y": 715, "x": 404}, {"y": 732, "x": 404}, {"y": 732, "x": 400}]}, "description": "\u2022"}, {"boundingPoly": {"vertices": [{"y": 715, "x": 429}, {"y": 716, "x": 478}, {"y": 734, "x": 478}, {"y": 733, "x": 429}]}, "description": "TRUST"}, {"boundingPoly": {"vertices": [{"y": 716, "x": 489}, {"y": 717, "x": 581}, {"y": 735, "x": 581}, {"y": 734, "x": 489}]}, "description": "COMPANIES"}, {"boundingPoly": {"vertices": [{"y": 717, "x": 584}, {"y": 717, "x": 588}, {"y": 734, "x": 588}, {"y": 734, "x": 584}]}, "description": ","}, {"boundingPoly": {"vertices": [{"y": 718, "x": 597}, {"y": 718, "x": 629}, {"y": 735, "x": 629}, {"y": 735, "x": 597}]}, "description": "AND"}, {"boundingPoly": {"vertices": [{"y": 762, "x": 236}, {"y": 762, "x": 297}, {"y": 824, "x": 297}, {"y": 824, "x": 236}]}, "description": "EVERY"}, {"boundingPoly": {"vertices": [{"y": 762, "x": 312}, {"y": 762, "x": 382}, {"y": 824, "x": 382}, {"y": 824, "x": 312}]}, "description": "STAMP"}, {"boundingPoly": {"vertices": [{"y": 762, "x": 385}, {"y": 762, "x": 454}, {"y": 824, "x": 454}, {"y": 824, "x": 385}]}, "description": "HELPS"}, {"boundingPoly": {"vertices": [{"y": 762, "x": 469}, {"y": 762, "x": 493}, {"y": 824, "x": 493}, {"y": 824, "x": 469}]}, "description": "TO"}, {"boundingPoly": {"vertices": [{"y": 762, "x": 507}, {"y": 762, "x": 556}, {"y": 824, "x": 556}, {"y": 824, "x": 507}]}, "description": "SAVE"}, {"boundingPoly": {"vertices": [{"y": 762, "x": 560}, {"y": 762, "x": 577}, {"y": 824, "x": 577}, {"y": 824, "x": 560}]}, "description": "A"}, {"boundingPoly": {"vertices": [{"y": 762, "x": 592}, {"y": 762, "x": 631}, {"y": 824, "x": 631}, {"y": 824, "x": 592}]}, "description": "LIFE"}, {"boundingPoly": {"vertices": [{"y": 826, "x": 231}, {"y": 826, "x": 296}, {"y": 884, "x": 296}, {"y": 884, "x": 231}]}, "description": "EVERY"}, {"boundingPoly": {"vertices": [{"y": 826, "x": 302}, {"y": 826, "x": 376}, {"y": 884, "x": 376}, {"y": 884, "x": 302}]}, "description": "STAMP"}, {"boundingPoly": {"vertices": [{"y": 826, "x": 378}, {"y": 826, "x": 443}, {"y": 884, "x": 443}, {"y": 884, "x": 378}]}, "description": "HELPS"}, {"boundingPoly": {"vertices": [{"y": 826, "x": 457}, {"y": 826, "x": 479}, {"y": 884, "x": 479}, {"y": 884, "x": 457}]}, "description": "TO"}, {"boundingPoly": {"vertices": [{"y": 826, "x": 492}, {"y": 826, "x": 526}, {"y": 884, "x": 526}, {"y": 884, "x": 492}]}, "description": "END"}, {"boundingPoly": {"vertices": [{"y": 826, "x": 541}, {"y": 826, "x": 573}, {"y": 884, "x": 573}, {"y": 884, "x": 541}]}, "description": "THE"}, {"boundingPoly": {"vertices": [{"y": 826, "x": 577}, {"y": 826, "x": 626}, {"y": 884, "x": 626}, {"y": 884, "x": 577}]}, "description": "WAR"}, {"boundingPoly": {"vertices": [{"y": 864, "x": 68}, {"y": 864, "x": 93}, {"y": 877, "x": 93}, {"y": 877, "x": 68}]}, "description": "WAR"}, {"boundingPoly": {"vertices": [{"y": 864, "x": 99}, {"y": 864, "x": 146}, {"y": 877, "x": 146}, {"y": 877, "x": 99}]}, "description": "SAVINGS"}, {"boundingPoly": {"vertices": [{"y": 864, "x": 150}, {"y": 864, "x": 195}, {"y": 877, "x": 195}, {"y": 877, "x": 150}]}, "description": "STAMPS"}, {"boundingPoly": {"vertices": [{"y": 880, "x": 87}, {"y": 880, "x": 125}, {"y": 892, "x": 125}, {"y": 892, "x": 87}]}, "description": "ISSUED"}, {"boundingPoly": {"vertices": [{"y": 880, "x": 132}, {"y": 880, "x": 146}, {"y": 892, "x": 146}, {"y": 892, "x": 132}]}, "description": "BY"}, {"boundingPoly": {"vertices": [{"y": 880, "x": 154}, {"y": 880, "x": 175}, {"y": 892, "x": 175}, {"y": 892, "x": 154}]}, "description": "THE"}, {"boundingPoly": {"vertices": [{"y": 894, "x": 75}, {"y": 894, "x": 129}, {"y": 909, "x": 129}, {"y": 909, "x": 75}]}, "description": "UNITED"}, {"boundingPoly": {"vertices": [{"y": 894, "x": 138}, {"y": 894, "x": 188}, {"y": 909, "x": 188}, {"y": 909, "x": 138}]}, "description": "STATES"}, {"boundingPoly": {"vertices": [{"y": 909, "x": 82}, {"y": 909, "x": 182}, {"y": 926, "x": 182}, {"y": 926, "x": 82}]}, "description": "GOVERNMENT"}, {"boundingPoly": {"vertices": [{"y": 911, "x": 253}, {"y": 911, "x": 310}, {"y": 942, "x": 310}, {"y": 942, "x": 253}]}, "description": "UNITED"}, {"boundingPoly": {"vertices": [{"y": 911, "x": 324}, {"y": 911, "x": 387}, {"y": 942, "x": 387}, {"y": 942, "x": 324}]}, "description": "STATES"}, {"boundingPoly": {"vertices": [{"y": 911, "x": 401}, {"y": 911, "x": 483}, {"y": 942, "x": 483}, {"y": 942, "x": 401}]}, "description": "TREASURY"}, {"boundingPoly": {"vertices": [{"y": 911, "x": 493}, {"y": 911, "x": 610}, {"y": 942, "x": 610}, {"y": 942, "x": 493}]}, "description": "DEPARTMENT"}]]