[[{"boundingPoly": {"vertices": [{"y": 4, "x": 52}, {"y": 4, "x": 617}, {"y": 931, "x": 617}, {"y": 931, "x": 52}]}, "description": "THE\nU.S. MARINES\nWANT YOU\nAPPLY AT\n", "locale": "en"}, {"boundingPoly": {"vertices": [{"y": 4, "x": 252}, {"y": 4, "x": 386}, {"y": 43, "x": 386}, {"y": 43, "x": 252}]}, "description": "THE"}, {"boundingPoly": {"vertices": [{"y": 12, "x": 52}, {"y": 12, "x": 101}, {"y": 178, "x": 101}, {"y": 178, "x": 52}]}, "description": "U"}, {"boundingPoly": {"vertices": [{"y": 12, "x": 102}, {"y": 12, "x": 151}, {"y": 178, "x": 151}, {"y": 178, "x": 102}]}, "description": "."}, {"boundingPoly": {"vertices": [{"y": 12, "x": 136}, {"y": 12, "x": 185}, {"y": 178, "x": 185}, {"y": 178, "x": 136}]}, "description": "S"}, {"boundingPoly": {"vertices": [{"y": 12, "x": 170}, {"y": 12, "x": 219}, {"y": 178, "x": 219}, {"y": 178, "x": 170}]}, "description": "."}, {"boundingPoly": {"vertices": [{"y": 12, "x": 210}, {"y": 12, "x": 617}, {"y": 178, "x": 617}, {"y": 178, "x": 210}]}, "description": "MARINES"}, {"boundingPoly": {"vertices": [{"y": 750, "x": 56}, {"y": 750, "x": 348}, {"y": 912, "x": 348}, {"y": 912, "x": 56}]}, "description": "WANT"}, {"boundingPoly": {"vertices": [{"y": 750, "x": 407}, {"y": 750, "x": 616}, {"y": 912, "x": 616}, {"y": 912, "x": 407}]}, "description": "YOU"}, {"boundingPoly": {"vertices": [{"y": 891, "x": 213}, {"y": 891, "x": 354}, {"y": 931, "x": 354}, {"y": 931, "x": 213}]}, "description": "APPLY"}, {"boundingPoly": {"vertices": [{"y": 891, "x": 380}, {"y": 891, "x": 437}, {"y": 931, "x": 437}, {"y": 931, "x": 380}]}, "description": "AT"}]]