[[{"boundingPoly": {"vertices": [{"y": 407, "x": 45}, {"y": 407, "x": 614}, {"y": 980, "x": 614}, {"y": 980, "x": 45}]}, "description": "AEONE\nBRACKER\nkeep'em\nsmiling!\nhelp\nWar Camp\nCommunity Service\nI SERVICE\n\u201c morale is winning the war\"\nUNITED WAR WORK CAMPAIGN\n", "locale": "en"}, {"boundingPoly": {"vertices": [{"y": 407, "x": 96}, {"y": 407, "x": 124}, {"y": 414, "x": 124}, {"y": 414, "x": 96}]}, "description": "AEONE"}, {"boundingPoly": {"vertices": [{"y": 416, "x": 84}, {"y": 417, "x": 126}, {"y": 425, "x": 126}, {"y": 424, "x": 84}]}, "description": "BRACKER"}, {"boundingPoly": {"vertices": [{"y": 457, "x": 93}, {"y": 457, "x": 263}, {"y": 550, "x": 263}, {"y": 550, "x": 93}]}, "description": "keep"}, {"boundingPoly": {"vertices": [{"y": 457, "x": 272}, {"y": 457, "x": 299}, {"y": 550, "x": 299}, {"y": 550, "x": 272}]}, "description": "'"}, {"boundingPoly": {"vertices": [{"y": 457, "x": 298}, {"y": 457, "x": 367}, {"y": 550, "x": 367}, {"y": 550, "x": 298}]}, "description": "em"}, {"boundingPoly": {"vertices": [{"y": 541, "x": 107}, {"y": 541, "x": 448}, {"y": 637, "x": 448}, {"y": 637, "x": 107}]}, "description": "smiling"}, {"boundingPoly": {"vertices": [{"y": 541, "x": 466}, {"y": 541, "x": 494}, {"y": 637, "x": 494}, {"y": 637, "x": 466}]}, "description": "!"}, {"boundingPoly": {"vertices": [{"y": 682, "x": 341}, {"y": 682, "x": 466}, {"y": 750, "x": 466}, {"y": 750, "x": 341}]}, "description": "help"}, {"boundingPoly": {"vertices": [{"y": 747, "x": 251}, {"y": 750, "x": 376}, {"y": 808, "x": 375}, {"y": 805, "x": 250}]}, "description": "War"}, {"boundingPoly": {"vertices": [{"y": 750, "x": 403}, {"y": 754, "x": 560}, {"y": 813, "x": 558}, {"y": 809, "x": 402}]}, "description": "Camp"}, {"boundingPoly": {"vertices": [{"y": 802, "x": 210}, {"y": 802, "x": 442}, {"y": 864, "x": 442}, {"y": 864, "x": 210}]}, "description": "Community"}, {"boundingPoly": {"vertices": [{"y": 802, "x": 462}, {"y": 802, "x": 614}, {"y": 864, "x": 614}, {"y": 864, "x": 462}]}, "description": "Service"}, {"boundingPoly": {"vertices": [{"y": 880, "x": 110}, {"y": 878, "x": 113}, {"y": 891, "x": 122}, {"y": 893, "x": 119}]}, "description": "I"}, {"boundingPoly": {"vertices": [{"y": 873, "x": 118}, {"y": 840, "x": 165}, {"y": 854, "x": 174}, {"y": 887, "x": 128}]}, "description": "SERVICE"}, {"boundingPoly": {"vertices": [{"y": 896, "x": 45}, {"y": 896, "x": 57}, {"y": 940, "x": 57}, {"y": 940, "x": 45}]}, "description": "\u201c"}, {"boundingPoly": {"vertices": [{"y": 896, "x": 63}, {"y": 896, "x": 191}, {"y": 940, "x": 191}, {"y": 940, "x": 63}]}, "description": "morale"}, {"boundingPoly": {"vertices": [{"y": 896, "x": 221}, {"y": 896, "x": 245}, {"y": 940, "x": 245}, {"y": 940, "x": 221}]}, "description": "is"}, {"boundingPoly": {"vertices": [{"y": 896, "x": 261}, {"y": 896, "x": 413}, {"y": 940, "x": 413}, {"y": 940, "x": 261}]}, "description": "winning"}, {"boundingPoly": {"vertices": [{"y": 896, "x": 432}, {"y": 896, "x": 489}, {"y": 940, "x": 489}, {"y": 940, "x": 432}]}, "description": "the"}, {"boundingPoly": {"vertices": [{"y": 896, "x": 497}, {"y": 896, "x": 573}, {"y": 940, "x": 573}, {"y": 940, "x": 497}]}, "description": "war"}, {"boundingPoly": {"vertices": [{"y": 896, "x": 580}, {"y": 896, "x": 592}, {"y": 940, "x": 592}, {"y": 940, "x": 580}]}, "description": "\""}, {"boundingPoly": {"vertices": [{"y": 947, "x": 141}, {"y": 947, "x": 222}, {"y": 980, "x": 222}, {"y": 980, "x": 141}]}, "description": "UNITED"}, {"boundingPoly": {"vertices": [{"y": 947, "x": 240}, {"y": 947, "x": 287}, {"y": 980, "x": 287}, {"y": 980, "x": 240}]}, "description": "WAR"}, {"boundingPoly": {"vertices": [{"y": 947, "x": 306}, {"y": 947, "x": 366}, {"y": 980, "x": 366}, {"y": 980, "x": 306}]}, "description": "WORK"}, {"boundingPoly": {"vertices": [{"y": 947, "x": 381}, {"y": 947, "x": 489}, {"y": 980, "x": 489}, {"y": 980, "x": 381}]}, "description": "CAMPAIGN"}]]