[[{"boundingPoly": {"vertices": [{"y": 28, "x": 51}, {"y": 28, "x": 600}, {"y": 896, "x": 600}, {"y": 896, "x": 51}]}, "description": "INCREASE\nYOUR INCOME\nWHY be satisfied\nwith LESS when\nYou can obtain\n.5724.\nVICTORY\nBONDS\n", "locale": "en"}, {"boundingPoly": {"vertices": [{"y": 28, "x": 57}, {"y": 28, "x": 582}, {"y": 163, "x": 582}, {"y": 163, "x": 57}]}, "description": "INCREASE"}, {"boundingPoly": {"vertices": [{"y": 153, "x": 51}, {"y": 153, "x": 261}, {"y": 222, "x": 261}, {"y": 222, "x": 51}]}, "description": "YOUR"}, {"boundingPoly": {"vertices": [{"y": 153, "x": 301}, {"y": 153, "x": 600}, {"y": 222, "x": 600}, {"y": 222, "x": 301}]}, "description": "INCOME"}, {"boundingPoly": {"vertices": [{"y": 278, "x": 84}, {"y": 280, "x": 225}, {"y": 339, "x": 224}, {"y": 337, "x": 83}]}, "description": "WHY"}, {"boundingPoly": {"vertices": [{"y": 281, "x": 239}, {"y": 282, "x": 302}, {"y": 340, "x": 301}, {"y": 339, "x": 238}]}, "description": "be"}, {"boundingPoly": {"vertices": [{"y": 282, "x": 326}, {"y": 286, "x": 527}, {"y": 345, "x": 526}, {"y": 341, "x": 325}]}, "description": "satisfied"}, {"boundingPoly": {"vertices": [{"y": 330, "x": 89}, {"y": 332, "x": 197}, {"y": 391, "x": 196}, {"y": 389, "x": 88}]}, "description": "with"}, {"boundingPoly": {"vertices": [{"y": 333, "x": 239}, {"y": 335, "x": 367}, {"y": 393, "x": 366}, {"y": 391, "x": 238}]}, "description": "LESS"}, {"boundingPoly": {"vertices": [{"y": 336, "x": 395}, {"y": 338, "x": 530}, {"y": 396, "x": 529}, {"y": 394, "x": 394}]}, "description": "when"}, {"boundingPoly": {"vertices": [{"y": 390, "x": 100}, {"y": 390, "x": 196}, {"y": 452, "x": 196}, {"y": 452, "x": 100}]}, "description": "You"}, {"boundingPoly": {"vertices": [{"y": 390, "x": 228}, {"y": 390, "x": 317}, {"y": 452, "x": 317}, {"y": 452, "x": 228}]}, "description": "can"}, {"boundingPoly": {"vertices": [{"y": 390, "x": 345}, {"y": 390, "x": 519}, {"y": 452, "x": 519}, {"y": 452, "x": 345}]}, "description": "obtain"}, {"boundingPoly": {"vertices": [{"y": 532, "x": 93}, {"y": 532, "x": 130}, {"y": 658, "x": 130}, {"y": 658, "x": 93}]}, "description": "."}, {"boundingPoly": {"vertices": [{"y": 532, "x": 147}, {"y": 532, "x": 449}, {"y": 658, "x": 449}, {"y": 658, "x": 147}]}, "description": "5724"}, {"boundingPoly": {"vertices": [{"y": 532, "x": 500}, {"y": 532, "x": 537}, {"y": 658, "x": 537}, {"y": 658, "x": 500}]}, "description": "."}, {"boundingPoly": {"vertices": [{"y": 677, "x": 79}, {"y": 692, "x": 566}, {"y": 809, "x": 562}, {"y": 794, "x": 75}]}, "description": "VICTORY"}, {"boundingPoly": {"vertices": [{"y": 809, "x": 102}, {"y": 809, "x": 535}, {"y": 896, "x": 535}, {"y": 896, "x": 102}]}, "description": "BONDS"}]]