[[{"boundingPoly": {"vertices": [{"y": 89, "x": 80}, {"y": 89, "x": 603}, {"y": 925, "x": 603}, {"y": 925, "x": 80}]}, "description": "Think what you can\nafford to give\n\u2013 then double it\nA life\nmay depend on it\n-do you dare do less?\nAll of the Red Cross War Fund\ngoes for War Relief\n", "locale": "en"}, {"boundingPoly": {"vertices": [{"y": 89, "x": 121}, {"y": 91, "x": 241}, {"y": 157, "x": 240}, {"y": 155, "x": 120}]}, "description": "Think"}, {"boundingPoly": {"vertices": [{"y": 92, "x": 269}, {"y": 94, "x": 386}, {"y": 159, "x": 385}, {"y": 157, "x": 268}]}, "description": "what"}, {"boundingPoly": {"vertices": [{"y": 94, "x": 404}, {"y": 95, "x": 488}, {"y": 161, "x": 487}, {"y": 160, "x": 403}]}, "description": "you"}, {"boundingPoly": {"vertices": [{"y": 96, "x": 509}, {"y": 97, "x": 584}, {"y": 162, "x": 583}, {"y": 161, "x": 508}]}, "description": "can"}, {"boundingPoly": {"vertices": [{"y": 157, "x": 109}, {"y": 157, "x": 250}, {"y": 227, "x": 250}, {"y": 227, "x": 109}]}, "description": "afford"}, {"boundingPoly": {"vertices": [{"y": 157, "x": 283}, {"y": 157, "x": 321}, {"y": 227, "x": 321}, {"y": 227, "x": 283}]}, "description": "to"}, {"boundingPoly": {"vertices": [{"y": 157, "x": 351}, {"y": 157, "x": 452}, {"y": 227, "x": 452}, {"y": 227, "x": 351}]}, "description": "give"}, {"boundingPoly": {"vertices": [{"y": 227, "x": 180}, {"y": 227, "x": 200}, {"y": 299, "x": 201}, {"y": 299, "x": 181}]}, "description": "\u2013"}, {"boundingPoly": {"vertices": [{"y": 226, "x": 225}, {"y": 224, "x": 323}, {"y": 297, "x": 324}, {"y": 299, "x": 226}]}, "description": "then"}, {"boundingPoly": {"vertices": [{"y": 224, "x": 361}, {"y": 221, "x": 520}, {"y": 293, "x": 521}, {"y": 296, "x": 362}]}, "description": "double"}, {"boundingPoly": {"vertices": [{"y": 220, "x": 556}, {"y": 219, "x": 583}, {"y": 291, "x": 584}, {"y": 292, "x": 557}]}, "description": "it"}, {"boundingPoly": {"vertices": [{"y": 596, "x": 114}, {"y": 596, "x": 134}, {"y": 666, "x": 134}, {"y": 666, "x": 114}]}, "description": "A"}, {"boundingPoly": {"vertices": [{"y": 596, "x": 165}, {"y": 596, "x": 239}, {"y": 666, "x": 239}, {"y": 666, "x": 165}]}, "description": "life"}, {"boundingPoly": {"vertices": [{"y": 668, "x": 140}, {"y": 666, "x": 239}, {"y": 735, "x": 240}, {"y": 737, "x": 141}]}, "description": "may"}, {"boundingPoly": {"vertices": [{"y": 666, "x": 268}, {"y": 663, "x": 440}, {"y": 732, "x": 441}, {"y": 735, "x": 269}]}, "description": "depend"}, {"boundingPoly": {"vertices": [{"y": 662, "x": 464}, {"y": 661, "x": 515}, {"y": 731, "x": 516}, {"y": 732, "x": 465}]}, "description": "on"}, {"boundingPoly": {"vertices": [{"y": 661, "x": 553}, {"y": 661, "x": 579}, {"y": 730, "x": 580}, {"y": 730, "x": 554}]}, "description": "it"}, {"boundingPoly": {"vertices": [{"y": 740, "x": 80}, {"y": 740, "x": 100}, {"y": 812, "x": 100}, {"y": 812, "x": 80}]}, "description": "-"}, {"boundingPoly": {"vertices": [{"y": 740, "x": 107}, {"y": 740, "x": 160}, {"y": 812, "x": 160}, {"y": 812, "x": 107}]}, "description": "do"}, {"boundingPoly": {"vertices": [{"y": 740, "x": 180}, {"y": 740, "x": 263}, {"y": 812, "x": 263}, {"y": 812, "x": 180}]}, "description": "you"}, {"boundingPoly": {"vertices": [{"y": 740, "x": 289}, {"y": 740, "x": 383}, {"y": 812, "x": 383}, {"y": 812, "x": 289}]}, "description": "dare"}, {"boundingPoly": {"vertices": [{"y": 740, "x": 406}, {"y": 740, "x": 460}, {"y": 812, "x": 460}, {"y": 812, "x": 406}]}, "description": "do"}, {"boundingPoly": {"vertices": [{"y": 740, "x": 482}, {"y": 740, "x": 566}, {"y": 812, "x": 566}, {"y": 812, "x": 482}]}, "description": "less"}, {"boundingPoly": {"vertices": [{"y": 740, "x": 583}, {"y": 740, "x": 603}, {"y": 812, "x": 603}, {"y": 812, "x": 583}]}, "description": "?"}, {"boundingPoly": {"vertices": [{"y": 852, "x": 111}, {"y": 852, "x": 144}, {"y": 890, "x": 144}, {"y": 890, "x": 111}]}, "description": "All"}, {"boundingPoly": {"vertices": [{"y": 852, "x": 158}, {"y": 852, "x": 187}, {"y": 890, "x": 187}, {"y": 890, "x": 158}]}, "description": "of"}, {"boundingPoly": {"vertices": [{"y": 852, "x": 200}, {"y": 852, "x": 238}, {"y": 890, "x": 238}, {"y": 890, "x": 200}]}, "description": "the"}, {"boundingPoly": {"vertices": [{"y": 852, "x": 255}, {"y": 852, "x": 309}, {"y": 890, "x": 309}, {"y": 890, "x": 255}]}, "description": "Red"}, {"boundingPoly": {"vertices": [{"y": 852, "x": 329}, {"y": 852, "x": 409}, {"y": 890, "x": 409}, {"y": 890, "x": 329}]}, "description": "Cross"}, {"boundingPoly": {"vertices": [{"y": 852, "x": 421}, {"y": 852, "x": 487}, {"y": 890, "x": 487}, {"y": 890, "x": 421}]}, "description": "War"}, {"boundingPoly": {"vertices": [{"y": 852, "x": 503}, {"y": 852, "x": 584}, {"y": 890, "x": 584}, {"y": 890, "x": 503}]}, "description": "Fund"}, {"boundingPoly": {"vertices": [{"y": 891, "x": 220}, {"y": 890, "x": 277}, {"y": 924, "x": 278}, {"y": 925, "x": 221}]}, "description": "goes"}, {"boundingPoly": {"vertices": [{"y": 889, "x": 288}, {"y": 888, "x": 322}, {"y": 923, "x": 323}, {"y": 924, "x": 289}]}, "description": "for"}, {"boundingPoly": {"vertices": [{"y": 889, "x": 332}, {"y": 888, "x": 385}, {"y": 922, "x": 386}, {"y": 923, "x": 333}]}, "description": "War"}, {"boundingPoly": {"vertices": [{"y": 887, "x": 392}, {"y": 885, "x": 473}, {"y": 920, "x": 474}, {"y": 922, "x": 393}]}, "description": "Relief"}]]