[[{"boundingPoly": {"vertices": [{"y": 47, "x": -81}, {"y": 47, "x": 1265}, {"y": 1037, "x": 1265}, {"y": 1037, "x": -81}]}, "description": "\u56dbi 2\n3\n4\n5\n6\n7\n8\n9\n\u96f7 1\n2\n3\n4\n5\n6\n7\n8\n9\n\u5f0f\u53ca\u9ec4\u7a81\u6dfb\u967d\n\u51a0S\u963f\n\u6df1\u690d\u6eaa\u561b\u5708\n\u8272S\u573a\n\u79c0\u4ea7\u53efp\n\u6253\u79c1\u7269\n\u5e03\u4e01\n\u4f5c\u5929\u300b\n\u5341\u5584\u3002\n\u70ba\u516d\u65b9\u5171\u540c\n\u76d2\u5f0f\u7b49\u9644\u591a\u51fa?\u9f99\u4e0d\n\u90e8\u95e8\u591a\u6b21\u3002\n\u5347\u4e86\u5e76\u9a6c\u53ef\u4e50\n\u5927\u5ddd\u4e2d~~\u6c38\u5be7\u5185\n\u3050\u3089~\u6b21\u767a\u305d\u308c\n~\u6c38\u9009\u8863\u4e4b\u4ee5\n\u6309\u75be\u4e01\u56e0\n\u571f4\u9879,\u519b\u963f\u4e2d\n\u725b\u820d\u53ef\u20ac\u65f6\u6ce8\n\u4e8e2\u4e01\u76ee\n\u4f30\u57285\n\u9648\u5766\u4e4e?\n\u82cf\u5929\u516d\n\u5f52\u4e8e\u81ea\u4f4f\u5404\n\u672c\u9580\u3002 3\n\u4e01\u56e0\u5e9c3\n\u3059\u3066\u6c17\u306c\u3051\n\u516b\u4e01\u540c\n\u5bf9\u904b\u4e0a\u4e24\n\u548c\u4e2d\n\u5e73\u5bf9\u7f55\u540c\n\u4e01\u540c\u7a76\n\u540cSFM\nf\u5343\u4e94\n- 16 by\n\u7269?\n\u5ca9\nDIUM\n\u592a\u7530\u53ef\u8fdb\u3002\n\u300c\u672c\u753a\u4e8c\u4e012\u4e01\n\u6bcf\u76db\nAT\nTIE II 8 ||\n\u65f6\u95f4\u8868\n\u304b\u308b\u3002\n\u4ea7\n& TR\n\u5929\u63a5\u54c1\n|\n\u90ed\nTR\n\u4eba\u4e0d\u4f1a\u5fc3\u6c34\n\u7b26\u72ec\u745e\n*\n\u52fe\u5f15\n\u904b\u4e0a\n5\n|\n||||||||||\n\u8377\u683c\u745e\n\u5c0f\u91ce:\u706bura Cinder=105103 S3\nSony\n|\n", "locale": "zh"}, {"boundingPoly": {"vertices": [{"y": 47, "x": 1248}, {"y": 47, "x": 1265}, {"y": 79, "x": 1265}, {"y": 79, "x": 1248}]}, "description": "\u56dbi"}, {"boundingPoly": {"vertices": [{"y": 91, "x": 1248}, {"y": 91, "x": 1265}, {"y": 95, "x": 1265}, {"y": 95, "x": 1248}]}, "description": "2"}, {"boundingPoly": {"vertices": [{"y": 117, "x": 1247}, {"y": 117, "x": 1264}, {"y": 121, "x": 1264}, {"y": 121, "x": 1247}]}, "description": "3"}, {"boundingPoly": {"vertices": [{"y": 142, "x": 1247}, {"y": 142, "x": 1264}, {"y": 146, "x": 1264}, {"y": 146, "x": 1247}]}, "description": "4"}, {"boundingPoly": {"vertices": [{"y": 163, "x": 1247}, {"y": 163, "x": 1264}, {"y": 167, "x": 1264}, {"y": 167, "x": 1247}]}, "description": "5"}, {"boundingPoly": {"vertices": [{"y": 189, "x": 1247}, {"y": 189, "x": 1264}, {"y": 193, "x": 1264}, {"y": 193, "x": 1247}]}, "description": "6"}, {"boundingPoly": {"vertices": [{"y": 214, "x": 1247}, {"y": 214, "x": 1264}, {"y": 218, "x": 1264}, {"y": 218, "x": 1247}]}, "description": "7"}, {"boundingPoly": {"vertices": [{"y": 235, "x": 1246}, {"y": 235, "x": 1263}, {"y": 239, "x": 1263}, {"y": 239, "x": 1246}]}, "description": "8"}, {"boundingPoly": {"vertices": [{"y": 261, "x": 1246}, {"y": 261, "x": 1263}, {"y": 265, "x": 1263}, {"y": 265, "x": 1246}]}, "description": "9"}, {"boundingPoly": {"vertices": [{"y": 289, "x": 1246}, {"y": 289, "x": 1263}, {"y": 293, "x": 1263}, {"y": 293, "x": 1246}]}, "description": "\u96f7"}, {"boundingPoly": {"vertices": [{"y": 299, "x": 1246}, {"y": 299, "x": 1263}, {"y": 301, "x": 1263}, {"y": 301, "x": 1246}]}, "description": "1"}, {"boundingPoly": {"vertices": [{"y": 324, "x": 1246}, {"y": 324, "x": 1263}, {"y": 326, "x": 1263}, {"y": 326, "x": 1246}]}, "description": "2"}, {"boundingPoly": {"vertices": [{"y": 358, "x": 1245}, {"y": 358, "x": 1262}, {"y": 362, "x": 1262}, {"y": 362, "x": 1245}]}, "description": "3"}, {"boundingPoly": {"vertices": [{"y": 379, "x": 1245}, {"y": 379, "x": 1262}, {"y": 383, "x": 1262}, {"y": 383, "x": 1245}]}, "description": "4"}, {"boundingPoly": {"vertices": [{"y": 405, "x": 1245}, {"y": 405, "x": 1262}, {"y": 409, "x": 1262}, {"y": 409, "x": 1245}]}, "description": "5"}, {"boundingPoly": {"vertices": [{"y": 426, "x": 1245}, {"y": 426, "x": 1262}, {"y": 430, "x": 1262}, {"y": 430, "x": 1245}]}, "description": "6"}, {"boundingPoly": {"vertices": [{"y": 451, "x": 1245}, {"y": 451, "x": 1262}, {"y": 455, "x": 1262}, {"y": 455, "x": 1245}]}, "description": "7"}, {"boundingPoly": {"vertices": [{"y": 477, "x": 1244}, {"y": 477, "x": 1261}, {"y": 481, "x": 1261}, {"y": 481, "x": 1244}]}, "description": "8"}, {"boundingPoly": {"vertices": [{"y": 498, "x": 1244}, {"y": 498, "x": 1261}, {"y": 502, "x": 1261}, {"y": 502, "x": 1244}]}, "description": "9"}, {"boundingPoly": {"vertices": [{"y": 155, "x": 1094}, {"y": 159, "x": 1142}, {"y": 449, "x": 1119}, {"y": 445, "x": 1071}]}, "description": "\u5f0f\u53ca\u9ec4\u7a81\u6dfb\u967d"}, {"boundingPoly": {"vertices": [{"y": 788, "x": 1101}, {"y": 789, "x": 1120}, {"y": 828, "x": 1119}, {"y": 827, "x": 1100}]}, "description": "\u51a0S\u963f"}, {"boundingPoly": {"vertices": [{"y": 147, "x": 1061}, {"y": 144, "x": 1108}, {"y": 437, "x": 1127}, {"y": 440, "x": 1081}]}, "description": "\u6df1\u690d\u6eaa\u561b\u5708"}, {"boundingPoly": {"vertices": [{"y": 541, "x": 1084}, {"y": 541, "x": 1105}, {"y": 603, "x": 1105}, {"y": 603, "x": 1084}]}, "description": "\u8272S\u573a"}, {"boundingPoly": {"vertices": [{"y": 655, "x": 1067}, {"y": 657, "x": 1085}, {"y": 756, "x": 1076}, {"y": 755, "x": 1058}]}, "description": "\u79c0\u4ea7\u53efp"}, {"boundingPoly": {"vertices": [{"y": 729, "x": 1051}, {"y": 731, "x": 1072}, {"y": 797, "x": 1064}, {"y": 795, "x": 1043}]}, "description": "\u6253\u79c1\u7269"}, {"boundingPoly": {"vertices": [{"y": 854, "x": 986}, {"y": 854, "x": 1011}, {"y": 882, "x": 1011}, {"y": 882, "x": 986}]}, "description": "\u5e03\u4e01"}, {"boundingPoly": {"vertices": [{"y": 501, "x": 947}, {"y": 505, "x": 960}, {"y": 525, "x": 955}, {"y": 521, "x": 941}]}, "description": "\u4f5c\u5929"}, {"boundingPoly": {"vertices": [{"y": 536, "x": 937}, {"y": 540, "x": 950}, {"y": 543, "x": 950}, {"y": 539, "x": 936}]}, "description": "\u300b"}, {"boundingPoly": {"vertices": [{"y": 795, "x": 883}, {"y": 795, "x": 900}, {"y": 847, "x": 900}, {"y": 847, "x": 883}]}, "description": "\u5341\u5584"}, {"boundingPoly": {"vertices": [{"y": 855, "x": 883}, {"y": 855, "x": 900}, {"y": 859, "x": 900}, {"y": 859, "x": 883}]}, "description": "\u3002"}, {"boundingPoly": {"vertices": [{"y": 159, "x": 1024}, {"y": 159, "x": 1048}, {"y": 340, "x": 1048}, {"y": 340, "x": 1024}]}, "description": "\u70ba\u516d\u65b9\u5171\u540c"}, {"boundingPoly": {"vertices": [{"y": 145, "x": 1001}, {"y": 145, "x": 1024}, {"y": 283, "x": 1022}, {"y": 283, "x": 999}]}, "description": "\u76d2\u5f0f\u7b49\u9644\u591a\u51fa"}, {"boundingPoly": {"vertices": [{"y": 295, "x": 1000}, {"y": 295, "x": 1022}, {"y": 300, "x": 1022}, {"y": 300, "x": 1000}]}, "description": "?"}, {"boundingPoly": {"vertices": [{"y": 319, "x": 999}, {"y": 319, "x": 1021}, {"y": 344, "x": 1021}, {"y": 344, "x": 999}]}, "description": "\u9f99\u4e0d"}, {"boundingPoly": {"vertices": [{"y": 145, "x": 978}, {"y": 145, "x": 998}, {"y": 327, "x": 998}, {"y": 327, "x": 978}]}, "description": "\u90e8\u95e8\u591a\u6b21"}, {"boundingPoly": {"vertices": [{"y": 329, "x": 978}, {"y": 329, "x": 998}, {"y": 334, "x": 998}, {"y": 334, "x": 978}]}, "description": "\u3002"}, {"boundingPoly": {"vertices": [{"y": 129, "x": 954}, {"y": 129, "x": 977}, {"y": 339, "x": 977}, {"y": 339, "x": 954}]}, "description": "\u5347\u4e86\u5e76\u9a6c\u53ef\u4e50"}, {"boundingPoly": {"vertices": [{"y": 135, "x": 932}, {"y": 135, "x": 956}, {"y": 191, "x": 956}, {"y": 191, "x": 932}]}, "description": "\u5927\u5ddd\u4e2d"}, {"boundingPoly": {"vertices": [{"y": 202, "x": 932}, {"y": 202, "x": 956}, {"y": 208, "x": 956}, {"y": 208, "x": 932}]}, "description": "~"}, {"boundingPoly": {"vertices": [{"y": 237, "x": 932}, {"y": 237, "x": 956}, {"y": 243, "x": 956}, {"y": 243, "x": 932}]}, "description": "~"}, {"boundingPoly": {"vertices": [{"y": 256, "x": 932}, {"y": 256, "x": 956}, {"y": 333, "x": 956}, {"y": 333, "x": 932}]}, "description": "\u6c38\u5be7\u5185"}, {"boundingPoly": {"vertices": [{"y": 137, "x": 911}, {"y": 137, "x": 934}, {"y": 172, "x": 934}, {"y": 172, "x": 911}]}, "description": "\u3050\u3089"}, {"boundingPoly": {"vertices": [{"y": 171, "x": 911}, {"y": 171, "x": 934}, {"y": 177, "x": 934}, {"y": 177, "x": 911}]}, "description": "~"}, {"boundingPoly": {"vertices": [{"y": 189, "x": 911}, {"y": 189, "x": 934}, {"y": 301, "x": 934}, {"y": 301, "x": 911}]}, "description": "\u6b21\u767a\u305d\u308c"}, {"boundingPoly": {"vertices": [{"y": 159, "x": 888}, {"y": 159, "x": 912}, {"y": 165, "x": 912}, {"y": 165, "x": 888}]}, "description": "~"}, {"boundingPoly": {"vertices": [{"y": 179, "x": 888}, {"y": 179, "x": 912}, {"y": 297, "x": 912}, {"y": 297, "x": 888}]}, "description": "\u6c38\u9009\u8863\u4e4b\u4ee5"}, {"boundingPoly": {"vertices": [{"y": 212, "x": 868}, {"y": 212, "x": 889}, {"y": 311, "x": 889}, {"y": 311, "x": 868}]}, "description": "\u6309\u75be\u4e01\u56e0"}, {"boundingPoly": {"vertices": [{"y": 132, "x": 847}, {"y": 132, "x": 868}, {"y": 194, "x": 868}, {"y": 194, "x": 847}]}, "description": "\u571f4\u9879"}, {"boundingPoly": {"vertices": [{"y": 195, "x": 847}, {"y": 195, "x": 868}, {"y": 200, "x": 868}, {"y": 200, "x": 847}]}, "description": ","}, {"boundingPoly": {"vertices": [{"y": 222, "x": 847}, {"y": 222, "x": 868}, {"y": 339, "x": 868}, {"y": 339, "x": 847}]}, "description": "\u519b\u963f\u4e2d"}, {"boundingPoly": {"vertices": [{"y": 136, "x": 827}, {"y": 136, "x": 847}, {"y": 340, "x": 842}, {"y": 340, "x": 822}]}, "description": "\u725b\u820d\u53ef\u20ac\u65f6\u6ce8"}, {"boundingPoly": {"vertices": [{"y": 145, "x": 805}, {"y": 145, "x": 825}, {"y": 244, "x": 825}, {"y": 244, "x": 805}]}, "description": "\u4e8e2\u4e01\u76ee"}, {"boundingPoly": {"vertices": [{"y": 138, "x": 784}, {"y": 138, "x": 803}, {"y": 254, "x": 801}, {"y": 254, "x": 782}]}, "description": "\u4f30\u57285"}, {"boundingPoly": {"vertices": [{"y": 143, "x": 761}, {"y": 143, "x": 782}, {"y": 198, "x": 782}, {"y": 198, "x": 761}]}, "description": "\u9648\u5766\u4e4e"}, {"boundingPoly": {"vertices": [{"y": 211, "x": 761}, {"y": 211, "x": 782}, {"y": 216, "x": 782}, {"y": 216, "x": 761}]}, "description": "?"}, {"boundingPoly": {"vertices": [{"y": 145, "x": 739}, {"y": 145, "x": 758}, {"y": 257, "x": 758}, {"y": 257, "x": 739}]}, "description": "\u82cf\u5929\u516d"}, {"boundingPoly": {"vertices": [{"y": 136, "x": 717}, {"y": 136, "x": 738}, {"y": 244, "x": 738}, {"y": 244, "x": 717}]}, "description": "\u5f52\u4e8e\u81ea\u4f4f\u5404"}, {"boundingPoly": {"vertices": [{"y": 141, "x": 696}, {"y": 141, "x": 716}, {"y": 179, "x": 716}, {"y": 179, "x": 696}]}, "description": "\u672c\u9580"}, {"boundingPoly": {"vertices": [{"y": 181, "x": 696}, {"y": 181, "x": 716}, {"y": 186, "x": 716}, {"y": 186, "x": 696}]}, "description": "\u3002"}, {"boundingPoly": {"vertices": [{"y": 227, "x": 696}, {"y": 227, "x": 716}, {"y": 232, "x": 716}, {"y": 232, "x": 696}]}, "description": "3"}, {"boundingPoly": {"vertices": [{"y": 150, "x": 673}, {"y": 150, "x": 694}, {"y": 240, "x": 694}, {"y": 240, "x": 673}]}, "description": "\u4e01\u56e0\u5e9c3"}, {"boundingPoly": {"vertices": [{"y": 139, "x": 651}, {"y": 139, "x": 672}, {"y": 246, "x": 672}, {"y": 246, "x": 651}]}, "description": "\u3059\u3066\u6c17\u306c\u3051"}, {"boundingPoly": {"vertices": [{"y": 193, "x": 630}, {"y": 193, "x": 651}, {"y": 255, "x": 651}, {"y": 255, "x": 630}]}, "description": "\u516b\u4e01\u540c"}, {"boundingPoly": {"vertices": [{"y": 134, "x": 608}, {"y": 134, "x": 629}, {"y": 221, "x": 629}, {"y": 221, "x": 608}]}, "description": "\u5bf9\u904b\u4e0a\u4e24"}, {"boundingPoly": {"vertices": [{"y": 133, "x": 587}, {"y": 133, "x": 606}, {"y": 183, "x": 606}, {"y": 183, "x": 587}]}, "description": "\u548c\u4e2d"}, {"boundingPoly": {"vertices": [{"y": 142, "x": 568}, {"y": 142, "x": 586}, {"y": 239, "x": 586}, {"y": 239, "x": 568}]}, "description": "\u5e73\u5bf9\u7f55\u540c"}, {"boundingPoly": {"vertices": [{"y": 154, "x": 546}, {"y": 154, "x": 566}, {"y": 232, "x": 567}, {"y": 232, "x": 547}]}, "description": "\u4e01\u540c\u7a76"}, {"boundingPoly": {"vertices": [{"y": 176, "x": 523}, {"y": 176, "x": 545}, {"y": 232, "x": 545}, {"y": 232, "x": 523}]}, "description": "\u540cSFM"}, {"boundingPoly": {"vertices": [{"y": 488, "x": 822}, {"y": 497, "x": 822}, {"y": 497, "x": 778}, {"y": 488, "x": 778}]}, "description": "f\u5343\u4e94"}, {"boundingPoly": {"vertices": [{"y": 573, "x": 791}, {"y": 575, "x": 791}, {"y": 576, "x": 780}, {"y": 574, "x": 780}]}, "description": "-"}, {"boundingPoly": {"vertices": [{"y": 579, "x": 792}, {"y": 596, "x": 793}, {"y": 597, "x": 781}, {"y": 580, "x": 780}]}, "description": "16"}, {"boundingPoly": {"vertices": [{"y": 605, "x": 794}, {"y": 614, "x": 795}, {"y": 615, "x": 783}, {"y": 606, "x": 782}]}, "description": "by"}, {"boundingPoly": {"vertices": [{"y": 797, "x": 779}, {"y": 797, "x": 800}, {"y": 802, "x": 800}, {"y": 802, "x": 779}]}, "description": "\u7269"}, {"boundingPoly": {"vertices": [{"y": 810, "x": 779}, {"y": 810, "x": 800}, {"y": 815, "x": 800}, {"y": 815, "x": 779}]}, "description": "?"}, {"boundingPoly": {"vertices": [{"y": 837, "x": 779}, {"y": 837, "x": 800}, {"y": 842, "x": 800}, {"y": 842, "x": 779}]}, "description": "\u5ca9"}, {"boundingPoly": {"vertices": [{"y": 317, "x": 737}, {"y": 313, "x": 766}, {"y": 325, "x": 767}, {"y": 329, "x": 738}]}, "description": "DIUM"}, {"boundingPoly": {"vertices": [{"y": 437, "x": 717}, {"y": 422, "x": 722}, {"y": 445, "x": 800}, {"y": 460, "x": 796}]}, "description": "\u592a\u7530\u53ef\u8fdb"}, {"boundingPoly": {"vertices": [{"y": 459, "x": 794}, {"y": 445, "x": 798}, {"y": 445, "x": 801}, {"y": 460, "x": 797}]}, "description": "\u3002"}, {"boundingPoly": {"vertices": [{"y": 568, "x": 789}, {"y": 587, "x": 789}, {"y": 587, "x": 784}, {"y": 568, "x": 784}]}, "description": "\u300c"}, {"boundingPoly": {"vertices": [{"y": 567, "x": 765}, {"y": 586, "x": 765}, {"y": 584, "x": 660}, {"y": 565, "x": 660}]}, "description": "\u672c\u753a\u4e8c\u4e012\u4e01"}, {"boundingPoly": {"vertices": [{"y": 660, "x": 648}, {"y": 660, "x": 759}, {"y": 681, "x": 759}, {"y": 681, "x": 648}]}, "description": "\u6bcf\u76db"}, {"boundingPoly": {"vertices": [{"y": 817, "x": 677}, {"y": 817, "x": 693}, {"y": 847, "x": 693}, {"y": 847, "x": 677}]}, "description": "AT"}, {"boundingPoly": {"vertices": [{"y": 479, "x": 593}, {"y": 435, "x": 594}, {"y": 436, "x": 629}, {"y": 480, "x": 628}]}, "description": "TIE"}, {"boundingPoly": {"vertices": [{"y": 420, "x": 594}, {"y": 376, "x": 595}, {"y": 377, "x": 630}, {"y": 421, "x": 629}]}, "description": "II"}, {"boundingPoly": {"vertices": [{"y": 345, "x": 596}, {"y": 336, "x": 596}, {"y": 337, "x": 630}, {"y": 346, "x": 630}]}, "description": "8"}, {"boundingPoly": {"vertices": [{"y": 322, "x": 597}, {"y": 313, "x": 597}, {"y": 314, "x": 631}, {"y": 323, "x": 631}]}, "description": "|"}, {"boundingPoly": {"vertices": [{"y": 313, "x": 597}, {"y": 304, "x": 597}, {"y": 305, "x": 631}, {"y": 314, "x": 631}]}, "description": "|"}, {"boundingPoly": {"vertices": [{"y": 334, "x": 606}, {"y": 327, "x": 657}, {"y": 350, "x": 660}, {"y": 357, "x": 609}]}, "description": "\u65f6\u95f4\u8868"}, {"boundingPoly": {"vertices": [{"y": 813, "x": 579}, {"y": 813, "x": 598}, {"y": 849, "x": 598}, {"y": 849, "x": 579}]}, "description": "\u304b\u308b"}, {"boundingPoly": {"vertices": [{"y": 859, "x": 579}, {"y": 859, "x": 598}, {"y": 864, "x": 598}, {"y": 864, "x": 579}]}, "description": "\u3002"}, {"boundingPoly": {"vertices": [{"y": 408, "x": 520}, {"y": 415, "x": 553}, {"y": 424, "x": 551}, {"y": 417, "x": 518}]}, "description": "\u4ea7"}, {"boundingPoly": {"vertices": [{"y": 563, "x": 573}, {"y": 582, "x": 573}, {"y": 582, "x": 568}, {"y": 563, "x": 568}]}, "description": "&"}, {"boundingPoly": {"vertices": [{"y": 562, "x": 556}, {"y": 582, "x": 556}, {"y": 581, "x": 513}, {"y": 561, "x": 513}]}, "description": "TR"}, {"boundingPoly": {"vertices": [{"y": 133, "x": 499}, {"y": 135, "x": 528}, {"y": 249, "x": 519}, {"y": 247, "x": 490}]}, "description": "\u5929\u63a5\u54c1"}, {"boundingPoly": {"vertices": [{"y": 810, "x": 476}, {"y": 809, "x": 495}, {"y": 814, "x": 495}, {"y": 815, "x": 476}]}, "description": "|"}, {"boundingPoly": {"vertices": [{"y": 838, "x": 477}, {"y": 837, "x": 496}, {"y": 842, "x": 496}, {"y": 843, "x": 477}]}, "description": "\u90ed"}, {"boundingPoly": {"vertices": [{"y": 560, "x": 452}, {"y": 579, "x": 452}, {"y": 578, "x": 409}, {"y": 559, "x": 409}]}, "description": "TR"}, {"boundingPoly": {"vertices": [{"y": 673, "x": 307}, {"y": 673, "x": 427}, {"y": 690, "x": 427}, {"y": 690, "x": 307}]}, "description": "\u4eba\u4e0d\u4f1a\u5fc3\u6c34"}, {"boundingPoly": {"vertices": [{"y": 689, "x": 361}, {"y": 689, "x": 375}, {"y": 731, "x": 375}, {"y": 731, "x": 361}]}, "description": "\u7b26\u72ec\u745e"}, {"boundingPoly": {"vertices": [{"y": 454, "x": 360}, {"y": 454, "x": 363}, {"y": 467, "x": 363}, {"y": 467, "x": 360}]}, "description": "*"}, {"boundingPoly": {"vertices": [{"y": 558, "x": 299}, {"y": 558, "x": 360}, {"y": 574, "x": 360}, {"y": 574, "x": 299}]}, "description": "\u52fe\u5f15"}, {"boundingPoly": {"vertices": [{"y": 606, "x": 330}, {"y": 606, "x": 349}, {"y": 627, "x": 349}, {"y": 627, "x": 330}]}, "description": "\u904b\u4e0a"}, {"boundingPoly": {"vertices": [{"y": 454, "x": 324}, {"y": 454, "x": 327}, {"y": 467, "x": 327}, {"y": 467, "x": 324}]}, "description": "5"}, {"boundingPoly": {"vertices": [{"y": 454, "x": 304}, {"y": 454, "x": 307}, {"y": 467, "x": 307}, {"y": 467, "x": 304}]}, "description": "|"}, {"boundingPoly": {"vertices": [{"y": 972, "x": 117}, {"y": 972, "x": 133}, {"y": 1028, "x": 133}, {"y": 1028, "x": 117}]}, "description": "|"}, {"boundingPoly": {"vertices": [{"y": 972, "x": 140}, {"y": 972, "x": 156}, {"y": 1028, "x": 156}, {"y": 1028, "x": 140}]}, "description": "|"}, {"boundingPoly": {"vertices": [{"y": 972, "x": 163}, {"y": 972, "x": 179}, {"y": 1028, "x": 179}, {"y": 1028, "x": 163}]}, "description": "|"}, {"boundingPoly": {"vertices": [{"y": 972, "x": 188}, {"y": 972, "x": 222}, {"y": 1028, "x": 222}, {"y": 1028, "x": 188}]}, "description": "|"}, {"boundingPoly": {"vertices": [{"y": 972, "x": 231}, {"y": 972, "x": 247}, {"y": 1028, "x": 247}, {"y": 1028, "x": 231}]}, "description": "|"}, {"boundingPoly": {"vertices": [{"y": 972, "x": 291}, {"y": 972, "x": 313}, {"y": 1028, "x": 313}, {"y": 1028, "x": 291}]}, "description": "|"}, {"boundingPoly": {"vertices": [{"y": 972, "x": 322}, {"y": 972, "x": 338}, {"y": 1028, "x": 338}, {"y": 1028, "x": 322}]}, "description": "|"}, {"boundingPoly": {"vertices": [{"y": 972, "x": 348}, {"y": 972, "x": 370}, {"y": 1028, "x": 370}, {"y": 1028, "x": 348}]}, "description": "|"}, {"boundingPoly": {"vertices": [{"y": 972, "x": 379}, {"y": 972, "x": 395}, {"y": 1028, "x": 395}, {"y": 1028, "x": 379}]}, "description": "|"}, {"boundingPoly": {"vertices": [{"y": 972, "x": 425}, {"y": 972, "x": 441}, {"y": 1028, "x": 441}, {"y": 1028, "x": 425}]}, "description": "|"}, {"boundingPoly": {"vertices": [{"y": 683, "x": 222}, {"y": 683, "x": 240}, {"y": 721, "x": 240}, {"y": 721, "x": 222}]}, "description": "\u8377\u683c\u745e"}, {"boundingPoly": {"vertices": [{"y": 1023, "x": 130}, {"y": 1023, "x": 151}, {"y": 1034, "x": 151}, {"y": 1034, "x": 130}]}, "description": "\u5c0f\u91ce"}, {"boundingPoly": {"vertices": [{"y": 1023, "x": 150}, {"y": 1023, "x": 152}, {"y": 1034, "x": 152}, {"y": 1034, "x": 150}]}, "description": ":"}, {"boundingPoly": {"vertices": [{"y": 1023, "x": 154}, {"y": 1024, "x": 199}, {"y": 1036, "x": 199}, {"y": 1035, "x": 154}]}, "description": "\u706bura"}, {"boundingPoly": {"vertices": [{"y": 1024, "x": 201}, {"y": 1024, "x": 228}, {"y": 1036, "x": 228}, {"y": 1036, "x": 201}]}, "description": "Cinder"}, {"boundingPoly": {"vertices": [{"y": 1025, "x": 234}, {"y": 1025, "x": 238}, {"y": 1036, "x": 238}, {"y": 1036, "x": 234}]}, "description": "="}, {"boundingPoly": {"vertices": [{"y": 1025, "x": 240}, {"y": 1026, "x": 283}, {"y": 1037, "x": 283}, {"y": 1036, "x": 240}]}, "description": "105103"}, {"boundingPoly": {"vertices": [{"y": 1026, "x": 285}, {"y": 1026, "x": 297}, {"y": 1037, "x": 297}, {"y": 1037, "x": 285}]}, "description": "S3"}, {"boundingPoly": {"vertices": [{"y": 612, "x": 191}, {"y": 663, "x": 186}, {"y": 661, "x": 171}, {"y": 611, "x": 176}]}, "description": "Sony"}, {"boundingPoly": {"vertices": [{"y": 622, "x": -81}, {"y": 622, "x": 5}, {"y": 911, "x": 5}, {"y": 911, "x": -81}]}, "description": "|"}]]