[[{"boundingPoly": {"vertices": [{"y": 18, "x": 33}, {"y": 18, "x": 899}, {"y": 1086, "x": 899}, {"y": 1086, "x": 33}]}, "description": "\u5c0f\u91ce:\u6771\u4eac\u65e5\u3005\u65b0\u805e 031 Code=0301031 SS\n\u65b0\u5d0e\u5de7\u307f\u78ba\u4eba\n\u65ad\u4e0b\uff64\u91dc\u3005\u898b\u3066\u898b\u3088\u3046\u3068\n\u76d7ng>\u4ee5\u3066\u7b56\u3092\u958b\u3068\n\u6b66\u3066\u89e3\u56fa\u3066\u5225\u5de7\u3046\n\u8ff7\u5b50\u300f\u3092\u6539\u3093\u30b5\u7684\u523a\u5668\u4ed8\n\u300c\u3046~\u592b\u5a66\u4e2d\u4f9b\u6050\u7387\u3092\n\u5f15\u9000\u3059\u591c\u76d7\u307f\n\u300c\u516c\u3092\u767d\u7389\u306e\u5c31\u6b69\u884c\n?\u6d3e\u66f4\u304b\u3048\u305f\u3044\n\u5973\u623f\u304c\u9020\u308b\u306e\u5bb6\u5bb6\u3078\u5fcd\n\u6b21\u3078\u3068\u3048\u4f55\u3082\u898b\u3068\u62b1\u304d\n\u30ed\u5973\u5b50\u9ad8\n2 3 4 5 6 7 8 9\u53f7\n1\numlululululululululululululululululululululululululululululululululan\n31 2 3 4 5 6 7 8 9\n\u805e\u65b0\u51ac\u65e5\u4eac\u6771\n\u85ac\u304c\u7834\u6570\u3092\u8981\u3057\u3066\u6226\u5834\u3092\u596a\u3057\n\u7b20\u677e\u6771\u795e\u304c\u66b4\u9732\n\u5bb6\u8a08\u3075\u300d\u304b\u3089\u3001\u5225\u306e\u65e5\u3092\u3042\u308b\uff61\n\u5929\u5019\u4ee5\u6765~\u91ce\u8302\u68ee\u672c\u3081\n\u7d99\u3084\u3064\u304b\u306a\u304b\u3046\u307e\u3044\n\u516b\u767e\u4e16\u8a66\u53f7\n\u571f\u6587\u6975\u5e7b\u5f71\u5b66\nT\n", "locale": "ja"}, {"boundingPoly": {"vertices": [{"y": 1051, "x": 883}, {"y": 1021, "x": 883}, {"y": 1021, "x": 899}, {"y": 1051, "x": 899}]}, "description": "\u5c0f\u91ce"}, {"boundingPoly": {"vertices": [{"y": 1026, "x": 883}, {"y": 1022, "x": 883}, {"y": 1022, "x": 899}, {"y": 1026, "x": 899}]}, "description": ":"}, {"boundingPoly": {"vertices": [{"y": 1009, "x": 882}, {"y": 933, "x": 881}, {"y": 933, "x": 898}, {"y": 1009, "x": 899}]}, "description": "\u6771\u4eac\u65e5\u3005\u65b0\u805e"}, {"boundingPoly": {"vertices": [{"y": 931, "x": 881}, {"y": 913, "x": 881}, {"y": 913, "x": 898}, {"y": 931, "x": 898}]}, "description": "031"}, {"boundingPoly": {"vertices": [{"y": 904, "x": 881}, {"y": 875, "x": 881}, {"y": 875, "x": 897}, {"y": 904, "x": 897}]}, "description": "Code"}, {"boundingPoly": {"vertices": [{"y": 873, "x": 881}, {"y": 869, "x": 881}, {"y": 869, "x": 897}, {"y": 873, "x": 897}]}, "description": "="}, {"boundingPoly": {"vertices": [{"y": 863, "x": 880}, {"y": 817, "x": 879}, {"y": 817, "x": 896}, {"y": 863, "x": 897}]}, "description": "0301031"}, {"boundingPoly": {"vertices": [{"y": 809, "x": 880}, {"y": 798, "x": 880}, {"y": 798, "x": 896}, {"y": 809, "x": 896}]}, "description": "SS"}, {"boundingPoly": {"vertices": [{"y": 912, "x": 674}, {"y": 912, "x": 693}, {"y": 1022, "x": 694}, {"y": 1022, "x": 675}]}, "description": "\u65b0\u5d0e\u5de7\u307f\u78ba\u4eba"}, {"boundingPoly": {"vertices": [{"y": 406, "x": 666}, {"y": 406, "x": 688}, {"y": 422, "x": 688}, {"y": 422, "x": 666}]}, "description": "\u65ad\u4e0b"}, {"boundingPoly": {"vertices": [{"y": 444, "x": 666}, {"y": 444, "x": 688}, {"y": 449, "x": 688}, {"y": 449, "x": 666}]}, "description": "\uff64"}, {"boundingPoly": {"vertices": [{"y": 459, "x": 666}, {"y": 459, "x": 688}, {"y": 659, "x": 688}, {"y": 659, "x": 666}]}, "description": "\u91dc\u3005\u898b\u3066\u898b\u3088\u3046\u3068"}, {"boundingPoly": {"vertices": [{"y": 396, "x": 637}, {"y": 396, "x": 664}, {"y": 460, "x": 664}, {"y": 460, "x": 637}]}, "description": "\u76d7ng"}, {"boundingPoly": {"vertices": [{"y": 458, "x": 637}, {"y": 458, "x": 664}, {"y": 465, "x": 664}, {"y": 465, "x": 637}]}, "description": ">"}, {"boundingPoly": {"vertices": [{"y": 476, "x": 637}, {"y": 476, "x": 664}, {"y": 603, "x": 664}, {"y": 603, "x": 637}]}, "description": "\u4ee5\u3066\u7b56\u3092\u958b\u3068"}, {"boundingPoly": {"vertices": [{"y": 365, "x": 615}, {"y": 366, "x": 639}, {"y": 532, "x": 635}, {"y": 531, "x": 611}]}, "description": "\u6b66\u3066\u89e3\u56fa\u3066\u5225\u5de7\u3046"}, {"boundingPoly": {"vertices": [{"y": 335, "x": 586}, {"y": 335, "x": 608}, {"y": 360, "x": 608}, {"y": 360, "x": 586}]}, "description": "\u8ff7\u5b50"}, {"boundingPoly": {"vertices": [{"y": 366, "x": 586}, {"y": 366, "x": 608}, {"y": 371, "x": 608}, {"y": 371, "x": 586}]}, "description": "\u300f"}, {"boundingPoly": {"vertices": [{"y": 375, "x": 586}, {"y": 375, "x": 608}, {"y": 496, "x": 610}, {"y": 496, "x": 588}]}, "description": "\u3092\u6539\u3093\u30b5\u7684\u523a\u5668\u4ed8"}, {"boundingPoly": {"vertices": [{"y": 298, "x": 558}, {"y": 298, "x": 585}, {"y": 305, "x": 585}, {"y": 305, "x": 558}]}, "description": "\u300c"}, {"boundingPoly": {"vertices": [{"y": 326, "x": 558}, {"y": 326, "x": 585}, {"y": 333, "x": 585}, {"y": 333, "x": 558}]}, "description": "\u3046"}, {"boundingPoly": {"vertices": [{"y": 342, "x": 558}, {"y": 342, "x": 585}, {"y": 349, "x": 585}, {"y": 349, "x": 558}]}, "description": "~"}, {"boundingPoly": {"vertices": [{"y": 350, "x": 558}, {"y": 350, "x": 585}, {"y": 423, "x": 585}, {"y": 423, "x": 558}]}, "description": "\u592b\u5a66\u4e2d\u4f9b"}, {"boundingPoly": {"vertices": [{"y": 428, "x": 558}, {"y": 428, "x": 585}, {"y": 476, "x": 585}, {"y": 476, "x": 558}]}, "description": "\u6050\u7387\u3092"}, {"boundingPoly": {"vertices": [{"y": 319, "x": 535}, {"y": 319, "x": 557}, {"y": 415, "x": 557}, {"y": 415, "x": 535}]}, "description": "\u5f15\u9000\u3059\u591c\u76d7\u307f"}, {"boundingPoly": {"vertices": [{"y": 274, "x": 510}, {"y": 274, "x": 534}, {"y": 280, "x": 534}, {"y": 280, "x": 510}]}, "description": "\u300c"}, {"boundingPoly": {"vertices": [{"y": 291, "x": 510}, {"y": 291, "x": 534}, {"y": 403, "x": 534}, {"y": 403, "x": 510}]}, "description": "\u516c\u3092\u767d\u7389\u306e\u5c31\u6b69\u884c"}, {"boundingPoly": {"vertices": [{"y": 280, "x": 482}, {"y": 279, "x": 508}, {"y": 286, "x": 508}, {"y": 287, "x": 482}]}, "description": "?"}, {"boundingPoly": {"vertices": [{"y": 304, "x": 482}, {"y": 303, "x": 509}, {"y": 374, "x": 512}, {"y": 375, "x": 485}]}, "description": "\u6d3e\u66f4\u304b\u3048\u305f\u3044"}, {"boundingPoly": {"vertices": [{"y": 271, "x": 456}, {"y": 271, "x": 477}, {"y": 406, "x": 477}, {"y": 406, "x": 456}]}, "description": "\u5973\u623f\u304c\u9020\u308b\u306e\u5bb6\u5bb6\u3078\u5fcd"}, {"boundingPoly": {"vertices": [{"y": 271, "x": 432}, {"y": 271, "x": 457}, {"y": 415, "x": 457}, {"y": 415, "x": 432}]}, "description": "\u6b21\u3078\u3068\u3048\u4f55\u3082\u898b\u3068\u62b1\u304d"}, {"boundingPoly": {"vertices": [{"y": 281, "x": 408}, {"y": 280, "x": 425}, {"y": 359, "x": 429}, {"y": 360, "x": 412}]}, "description": "\u30ed\u5973\u5b50\u9ad8"}, {"boundingPoly": {"vertices": [{"y": 18, "x": 388}, {"y": 18, "x": 393}, {"y": 38, "x": 393}, {"y": 38, "x": 388}]}, "description": "2"}, {"boundingPoly": {"vertices": [{"y": 18, "x": 413}, {"y": 18, "x": 418}, {"y": 38, "x": 418}, {"y": 38, "x": 413}]}, "description": "3"}, {"boundingPoly": {"vertices": [{"y": 18, "x": 442}, {"y": 18, "x": 447}, {"y": 38, "x": 447}, {"y": 38, "x": 442}]}, "description": "4"}, {"boundingPoly": {"vertices": [{"y": 18, "x": 472}, {"y": 18, "x": 477}, {"y": 38, "x": 477}, {"y": 38, "x": 472}]}, "description": "5"}, {"boundingPoly": {"vertices": [{"y": 18, "x": 501}, {"y": 18, "x": 506}, {"y": 38, "x": 506}, {"y": 38, "x": 501}]}, "description": "6"}, {"boundingPoly": {"vertices": [{"y": 18, "x": 530}, {"y": 18, "x": 535}, {"y": 38, "x": 535}, {"y": 38, "x": 530}]}, "description": "7"}, {"boundingPoly": {"vertices": [{"y": 18, "x": 556}, {"y": 18, "x": 561}, {"y": 38, "x": 561}, {"y": 38, "x": 556}]}, "description": "8"}, {"boundingPoly": {"vertices": [{"y": 18, "x": 577}, {"y": 18, "x": 622}, {"y": 38, "x": 622}, {"y": 38, "x": 577}]}, "description": "9\u53f7"}, {"boundingPoly": {"vertices": [{"y": 18, "x": 337}, {"y": 18, "x": 341}, {"y": 38, "x": 341}, {"y": 38, "x": 337}]}, "description": "1"}, {"boundingPoly": {"vertices": [{"y": 36, "x": 69}, {"y": 36, "x": 613}, {"y": 48, "x": 613}, {"y": 48, "x": 69}]}, "description": "umlululululululululululululululululululululululululululululululululan"}, {"boundingPoly": {"vertices": [{"y": 18, "x": 48}, {"y": 18, "x": 78}, {"y": 38, "x": 78}, {"y": 38, "x": 48}]}, "description": "31"}, {"boundingPoly": {"vertices": [{"y": 18, "x": 102}, {"y": 18, "x": 107}, {"y": 38, "x": 107}, {"y": 38, "x": 102}]}, "description": "2"}, {"boundingPoly": {"vertices": [{"y": 18, "x": 127}, {"y": 18, "x": 132}, {"y": 38, "x": 132}, {"y": 38, "x": 127}]}, "description": "3"}, {"boundingPoly": {"vertices": [{"y": 18, "x": 157}, {"y": 18, "x": 162}, {"y": 38, "x": 162}, {"y": 38, "x": 157}]}, "description": "4"}, {"boundingPoly": {"vertices": [{"y": 18, "x": 186}, {"y": 18, "x": 191}, {"y": 38, "x": 191}, {"y": 38, "x": 186}]}, "description": "5"}, {"boundingPoly": {"vertices": [{"y": 18, "x": 215}, {"y": 18, "x": 220}, {"y": 38, "x": 220}, {"y": 38, "x": 215}]}, "description": "6"}, {"boundingPoly": {"vertices": [{"y": 18, "x": 245}, {"y": 18, "x": 250}, {"y": 38, "x": 250}, {"y": 38, "x": 245}]}, "description": "7"}, {"boundingPoly": {"vertices": [{"y": 18, "x": 270}, {"y": 18, "x": 275}, {"y": 38, "x": 275}, {"y": 38, "x": 270}]}, "description": "8"}, {"boundingPoly": {"vertices": [{"y": 18, "x": 278}, {"y": 18, "x": 282}, {"y": 38, "x": 282}, {"y": 38, "x": 278}]}, "description": "9"}, {"boundingPoly": {"vertices": [{"y": 165, "x": 249}, {"y": 165, "x": 554}, {"y": 239, "x": 554}, {"y": 239, "x": 249}]}, "description": "\u805e\u65b0\u51ac\u65e5\u4eac\u6771"}, {"boundingPoly": {"vertices": [{"y": 768, "x": 316}, {"y": 768, "x": 340}, {"y": 967, "x": 340}, {"y": 967, "x": 316}]}, "description": "\u85ac\u304c\u7834\u6570\u3092\u8981\u3057\u3066\u6226\u5834\u3092\u596a\u3057"}, {"boundingPoly": {"vertices": [{"y": 767, "x": 289}, {"y": 766, "x": 307}, {"y": 921, "x": 312}, {"y": 922, "x": 294}]}, "description": "\u7b20\u677e\u6771\u795e\u304c\u66b4\u9732"}, {"boundingPoly": {"vertices": [{"y": 771, "x": 265}, {"y": 771, "x": 283}, {"y": 806, "x": 284}, {"y": 806, "x": 266}]}, "description": "\u5bb6\u8a08\u3075"}, {"boundingPoly": {"vertices": [{"y": 807, "x": 266}, {"y": 807, "x": 283}, {"y": 811, "x": 283}, {"y": 811, "x": 266}]}, "description": "\u300d"}, {"boundingPoly": {"vertices": [{"y": 813, "x": 266}, {"y": 813, "x": 284}, {"y": 845, "x": 285}, {"y": 845, "x": 267}]}, "description": "\u304b\u3089"}, {"boundingPoly": {"vertices": [{"y": 851, "x": 267}, {"y": 851, "x": 284}, {"y": 855, "x": 284}, {"y": 855, "x": 267}]}, "description": "\u3001"}, {"boundingPoly": {"vertices": [{"y": 865, "x": 267}, {"y": 865, "x": 285}, {"y": 952, "x": 287}, {"y": 952, "x": 269}]}, "description": "\u5225\u306e\u65e5\u3092\u3042\u308b"}, {"boundingPoly": {"vertices": [{"y": 955, "x": 270}, {"y": 955, "x": 287}, {"y": 959, "x": 287}, {"y": 959, "x": 270}]}, "description": "\uff61"}, {"boundingPoly": {"vertices": [{"y": 789, "x": 240}, {"y": 789, "x": 258}, {"y": 885, "x": 260}, {"y": 885, "x": 242}]}, "description": "\u5929\u5019\u4ee5\u6765"}, {"boundingPoly": {"vertices": [{"y": 885, "x": 242}, {"y": 885, "x": 260}, {"y": 889, "x": 260}, {"y": 889, "x": 242}]}, "description": "~"}, {"boundingPoly": {"vertices": [{"y": 909, "x": 242}, {"y": 909, "x": 261}, {"y": 975, "x": 262}, {"y": 975, "x": 243}]}, "description": "\u91ce\u8302\u68ee\u672c\u3081"}, {"boundingPoly": {"vertices": [{"y": 884, "x": 217}, {"y": 884, "x": 235}, {"y": 1028, "x": 235}, {"y": 1028, "x": 217}]}, "description": "\u7d99\u3084\u3064\u304b\u306a\u304b\u3046\u307e\u3044"}, {"boundingPoly": {"vertices": [{"y": 190, "x": 178}, {"y": 189, "x": 201}, {"y": 296, "x": 207}, {"y": 297, "x": 184}]}, "description": "\u516b\u767e\u4e16\u8a66\u53f7"}, {"boundingPoly": {"vertices": [{"y": 929, "x": 72}, {"y": 929, "x": 94}, {"y": 1086, "x": 94}, {"y": 1086, "x": 72}]}, "description": "\u571f\u6587\u6975\u5e7b\u5f71\u5b66"}, {"boundingPoly": {"vertices": [{"y": 36, "x": 33}, {"y": 36, "x": 35}, {"y": 48, "x": 35}, {"y": 48, "x": 33}]}, "description": "T"}]]